Workbook

Sheet フォームの回答 1
A1: タイムスタンプ | B1: 無題の質問

Sheet 支払い回答
A1: タイムスタンプ | B1: メールアドレス | C1: どの決済方法での支払いになりますか？ | D1: どの支出項目に計上される支払いですか？ | E1: 金額はいくらですか？（短文記述） | F1: 何を買いましたか？or何に使いましたか？（長文） | G1: いまどんな気持ちですか？(チェックボックス) | H1: いまどんな気持ちですか？(プルダウン) | I1: いまどんな気持ちですか？(均等目盛) | J1: いまの気分は？(評価) | K1: いまの気分は？(グリッド選択式) [第一象限] | L1: いまの気分は？(チェックボックスグリッド) [合理的（金銭的）] | M1: 今日の日付は？ | N1: 今の時刻は？ | O1: ★入力済み
A2: 45903.697 | B2: lycourgos.yoshioka@gmail.com | C2: oliveカード支払い | D2: 昼飯 | E2: 夏季休暇 | F2: 夏季休暇めっちゃありがたい | G2: 最高, 普通 | H2: 最高 | I2: 7 | J2: 6 | K2: 第二象限 | L2: 体調（良い） | M2: 45903 | N2: 0.69652778 | O2: TRUE
A3: 45909.355 | B3: lycourgos.yoshioka@gmail.com | C3: PayPayカード支払い | D3: 物品購入費 | E3: 3,300円 | F3: 仕事頑張ろう | G3: 最高, 普通 | H3: 最高 | I3: 5 | J3: 4 | M3: 45910 | N3: 0.35486111 | O3: TRUE
A4: 45909.361 | B4: lycourgos.yoshioka@gmail.com | C4: メルペイ | D4: スーパー | E4: 560 | F4: お茶4本 | G4: 最高 | H4: 最高 | I4: 5 | J4: 5 | O4: TRUE
A5: 45922.87 | B5: lycourgos.yoshioka@gmail.com | C5: PayPay残高支払い | D5: 夜飯 | E5: 181 | F5: サラダチキンバー | G5: 普通 | H5: 普通 | I5: 4 | J5: 4 | O5: TRUE
O6: FALSE
O7: FALSE
O8: FALSE
O9: FALSE
O10: FALSE
O11: FALSE
O12: FALSE
O13: FALSE
O14: FALSE
O15: FALSE
O16: FALSE
O17: FALSE
... O125: FALSE

Sheet サマリ
B2: 30歳までの目標 | M2: 2026年度にやりたいこと
B4: テーマ | D4: 映画やドラマのようなストーリー | M4: 稼ぎ | O4: 年収1,000万を稼ぐ経験をする（2026年1月～2026年12月）
B6: 夢 | D6: 好きな人と生きていく（自分も主役となり友達と事業をして生きていきたい） | M6: 美容 | O6: 年間予算120万円を投下して外見磨きを行う（脱毛、眉毛サロン、歯科矯正、パーソナルジム）
B8: 目標 | D8: 30歳まで(2028年3月10日)に実際に事業継承か起業で勝てるビジネスを始める | M8: 旅行 | O8: 予算を決めて海外旅行に2回以上行く（バンコク&グアム＆ベトナム？）
B10: やること | D10: 生活習慣とお金を管理し資産1,000万円~3,000万円を固く作りに行く | M10: 読書・発信 | O10: 年間50冊の読書&noteの発信活動（毎日投稿）
B13: (FY-1収支) | G13: (FY-2収支) | L13: (FY-3収支) | Q13: (FY-4収支)
B14: 月 | C14: 支出 | D14: 収入 | E14: 収支 | G14: 月 | H14: 支出 | I14: 収入 | J14: 収支 | L14: 月 | M14: 支出 | N14: 収入 | O14: 収支 | Q14: 月 | R14: 支出 | S14: 収入 | T14: 収支
B15: 2024年5月 | C15: 201303 | D15: 304485 | E15: 103182 | G15: 2025年4月 | H15: ='FY-2(月次)支出'!D3 -> 328579 | I15: ='FY-2(月次)収入'!D3 -> 362756 | J15: =I15-H15 -> 34177 | L15: 2026年4月 | M15: ='FY-3(月次)支出 '!D3 -> 440344 | N15: ='FY-3(月次)収入'!D3 -> 575013.96 | O15: =N15-M15 -> 134669.96 | Q15: 2027年4月 | T15: =S15-R15 -> 0
B16: 2024年6月 | C16: 204637 | D16: 408757 | E16: 204120 | G16: 2025年5月 | H16: ='FY-2(月次)支出'!E3 -> 458043 | I16: ='FY-2(月次)収入'!E3 -> 280024 | J16: =I16-H16 -> -178019 | L16: 2026年5月 | M16: ='FY-3(月次)支出 '!E3 -> 447333 | N16: ='FY-3(月次)収入'!E3 -> 518059.08 | O16: =N16-M16 -> 70726.075 | Q16: 2027年5月 | T16: =S16-R16 -> 0
B17: 2024年7月 | C17: 206041 | D17: 339296 | E17: 133255 | G17: 2025年6月 | H17: ='FY-2(月次)支出'!F3 -> 320775 | I17: ='FY-2(月次)収入'!F3 -> 68896 | J17: =I17-H17 -> -251879 | L17: 2026年6月 | M17: ='FY-3(月次)支出 '!F3 -> 392616 | N17: ='FY-3(月次)収入'!F3 -> 549667.74 | O17: =N17-M17 -> 157051.74 | Q17: 2027年6月 | T17: =S17-R17 -> 0
B18: 2024年8月 | C18: 229626 | D18: 338764 | E18: 109138 | G18: 2025年7月 | H18: ='FY-2(月次)支出'!G3 -> 314993 | I18: ='FY-2(月次)収入'!G3 -> 473086 | J18: =I18-H18 -> 158093 | L18: 2026年7月 | M18: ='FY-3(月次)支出 '!G3 -> 494717 | N18: ='FY-3(月次)収入'!G3 -> 538747.85 | O18: =N18-M18 -> 44030.85 | Q18: 2027年7月 | T18: =S18-R18 -> 0
B19: 2024年9月 | C19: 210893 | D19: 318196 | E19: 107303 | G19: 2025年8月 | H19: ='FY-2(月次)支出'!H3 -> 335534 | I19: ='FY-2(月次)収入'!H3 -> 502474 | J19: =I19-H19 -> 166940 | L19: 2026年8月 | M19: ='FY-3(月次)支出 '!H3 -> 588753 | N19: ='FY-3(月次)収入'!H3 -> 745190.1 | O19: =N19-M19 -> 156437.1 | Q19: 2027年8月 | T19: =S19-R19 -> 0
B20: 2024年10月 | C20: 270707 | D20: 361408 | E20: 90701 | G20: 2025年9月 | H20: ='FY-2(月次)支出'!I3 -> 340477 | I20: ='FY-2(月次)収入'!I3 -> 584444 | J20: =I20-H20 -> 243967 | L20: 2026年9月 | M20: ='FY-3(月次)支出 '!I3 -> 849403 | N20: ='FY-3(月次)収入'!I3 -> 861996.07 | O20: =N20-M20 -> 12593.07 | Q20: 2027年9月 | T20: =S20-R20 -> 0
B21: 2024年11月 | C21: 281773 | D21: 360882 | E21: 79109 | G21: 2025年10月 | H21: ='FY-2(月次)支出'!J3 -> 514909 | I21: ='FY-2(月次)収入'!J3 -> 524857 | J21: =I21-H21 -> 9948 | L21: 2026年10月 | M21: ='FY-3(月次)支出 '!J3 -> 529403 | N21: ='FY-3(月次)収入'!J3 -> 757549.43 | O21: =N21-M21 -> 228146.43 | Q21: 2027年10月 | T21: =S21-R21 -> 0
B22: 2024年12月 | C22: 341879 | D22: 332786 | E22: -9093 | G22: 2025年11月 | H22: ='FY-2(月次)支出'!K3 -> 566502 | I22: ='FY-2(月次)収入'!K3 -> 584601.18 | J22: =I22-H22 -> 18099.183 | L22: 2026年11月 | M22: ='FY-3(月次)支出 '!K3 -> 529403 | N22: ='FY-3(月次)収入'!K3 -> 1161938.8 | O22: =N22-M22 -> 632535.77 | Q22: 2027年11月 | T22: =S22-R22 -> 0
B23: 2025年1月 | C23: 269836 | D23: 361916 | E23: 92080 | G23: 2025年12月 | H23: ='FY-2(月次)支出'!L3 -> 557359 | I23: ='FY-2(月次)収入'!L3 -> 703578.01 | J23: =I23-H23 -> 146219.01 | L23: 2026年12月 | M23: ='FY-3(月次)支出 '!L3 -> 409403 | N23: ='FY-3(月次)収入'!L3 -> 898415.79 | O23: =N23-M23 -> 489012.79 | Q23: 2027年12月 | T23: =S23-R23 -> 0
B24: 2025年2月 | C24: 235258 | D24: 374138 | E24: 138880 | G24: 2026年1月 | H24: ='FY-2(月次)支出'!M3 -> 821287 | I24: ='FY-2(月次)収入'!M3 -> 752868.15 | J24: =I24-H24 -> -68418.849 | L24: 2027年1月 | M24: ='FY-3(月次)支出 '!M3 -> 499403 | N24: ='FY-3(月次)収入'!M3 -> 775574.21 | O24: =N24-M24 -> 276171.21 | Q24: 2028年1月 | T24: =S24-R24 -> 0
B25: 2025年3月 | C25: 263558 | D25: 309616 | E25: 46058 | G25: 2026年2月 | H25: ='FY-2(月次)支出'!N3 -> 382867 | I25: ='FY-2(月次)収入'!N3 -> 581951.13 | J25: =I25-H25 -> 199084.13 | L25: 2027年2月 | M25: ='FY-3(月次)支出 '!N3 -> 409371 | N25: ='FY-3(月次)収入'!N3 -> 1161464.2 | O25: =N25-M25 -> 752093.16 | Q25: 2028年2月 | T25: =S25-R25 -> 0
B26: 2025年4月 | C26: 330716 | D26: 362471 | E26: 31755 | G26: 2026年3月 | H26: ='FY-2(月次)支出'!O3 -> 570863 | I26: ='FY-2(月次)収入'!O3 -> 773052.25 | J26: =I26-H26 -> 202189.25 | L26: 2027年3月 | M26: ='FY-3(月次)支出 '!O3 -> 499403 | N26: ='FY-3(月次)収入'!O3 -> 747941.85 | O26: =N26-M26 -> 248538.85 | Q26: 2028年3月 | T26: =S26-R26 -> 0
B27: 合計 | C27: =SUM(C15:C26) -> 3046227 | D27: =SUM(D15:D26) -> 4172715 | E27: =SUM(E15:E26) -> 1126488 | G27: 合計 | H27: =SUM(H15:H26) -> 5512188 | I27: =SUM(I15:I26) -> 6192587.7 | J27: =SUM(J15:J26) -> 680399.72 | L27: 合計 | M27: =SUM(M15:M26) -> 6089552 | N27: =SUM(N15:N26) -> 9291559 | O27: =SUM(O15:O26) -> 3202007 | Q27: 合計 | R27: =SUM(R15:R26) -> 0 | S27: =SUM(S15:S26) -> 0 | T27: =SUM(T15:T26) -> 0
B29: (FY-3)年間予算達成率
B30: 【 予実対比 】 | D30: 2026年4月 | E30: 2026年5月 | F30: 2026年6月 | G30: 2026年7月 | H30: 2026年8月 | I30: 2026年9月 | J30: 2026年10月 | K30: 2026年11月 | L30: 2026年12月 | M30: 2027年1月 | N30: 2027年2月 | O30: 2027年3月 | P30: 合計 | Q30: 達成率
B31: 予算 | C31: 収入 | D31: 556810.19 | E31: 562468.19 | F31: 778785.69 | G31: 759686.75 | H31: 756528.31 | I31: 1173447.2 | J31: 769052.83 | K31: 1173388.3 | L31: 900997.58 | M31: 778205.15 | N31: 1164875.1 | O31: 751402.69 | P31: =IF(D31="","",SUM(D31:O31)) -> 10125648 | Q31: /
C32: 支出 | D32: 472674 | E32: 437674 | F32: 527674 | G32: 607674 | H32: 617674 | I32: 877674 | J32: 557674 | K32: 657674 | L32: 437674 | M32: 527674 | N32: 437642 | O32: 527674 | P32: =IF(D32="","",SUM(D32:O32)) -> 6687056 | Q32: /
C33: 収支 | D33: =D31-D32 -> 84136.19 | E33: =E31-E32 -> 124794.19 | F33: =F31-F32 -> 251111.69 | G33: =G31-G32 -> 152012.75 | H33: =H31-H32 -> 138854.31 | I33: =I31-I32 -> 295773.24 | J33: =J31-J32 -> 211378.83 | K33: =K31-K32 -> 515714.31 | ... O33: =O31-O32 -> 223728.69 | P33: =IF(D33="","",SUM(D33:O33)) -> 3438592.1 | Q33: /
B34: 実績 | C34: 収入 | D34: =N15 -> 575013.96 | E34: =N16 -> 518059.08 | F34: =N17 -> 549667.74 | G34: =N18 -> 538747.85 | H34: =N19 -> 745190.1 | I34: =N20 -> 861996.07 | J34: =N21 -> 757549.43 | K34: =N22 -> 1161938.8 | L34: =N23 -> 898415.79 | M34: =N24 -> 775574.21 | N34: =N25 -> 1161464.2 | O34: =N26 -> 747941.85 | P34: =IF(D34="","",SUM(D34:O34)) -> 9291559 | Q34: =P34/P31 -> 0.91762611
C35: 支出 | D35: =M15 -> 440344 | E35: =M16 -> 447333 | F35: =M17 -> 392616 | G35: =M18 -> 494717 | H35: =M19 -> 588753 | I35: =M20 -> 849403 | J35: =M21 -> 529403 | K35: =M22 -> 529403 | L35: =M23 -> 409403 | M35: =M24 -> 499403 | N35: =M25 -> 409371 | O35: =M26 -> 499403 | P35: =IF(D35="","",SUM(D35:O35)) -> 6089552 | Q35: =P35/P32 -> 0.91064768
C36: 収支 | D36: =D34-D35 -> 134669.96 | E36: =E34-E35 -> 70726.075 | F36: =F34-F35 -> 157051.74 | G36: =G34-G35 -> 44030.85 | H36: =H34-H35 -> 156437.1 | I36: =I34-I35 -> 12593.07 | J36: =J34-J35 -> 228146.43 | K36: =K34-K35 -> 632535.77 | ... O36: =O34-O35 -> 248538.85 | P36: =IF(D36="","",SUM(D36:O36)) -> 3202007 | Q36: =P36/P33 -> 0.93119711
B37: 差異 (実績-予算) | C37: 収入 | D37: =D34-D31 -> 18203.767 | E37: =E34-E31 -> -44409.115 | F37: =F34-F31 -> -229117.94 | G37: =G34-G31 -> -220938.9 | H37: =H34-H31 -> -11338.206 | I37: =I34-I31 -> -311451.17 | J37: =J34-J31 -> -11503.402 | K37: =K34-K31 -> -11449.537 | ... O37: =O34-O31 -> -3460.84 | P37: =IF(D37="","",SUM(D37:O37)) -> -834089.05 | Q37: /
C38: 支出 | D38: =D35-D32 -> -32330 | E38: =E35-E32 -> 9659 | F38: =F35-F32 -> -135058 | G38: =G35-G32 -> -112957 | H38: =H35-H32 -> -28921 | I38: =I35-I32 -> -28271 | J38: =J35-J32 -> -28271 | K38: =K35-K32 -> -128271 | ... O38: =O35-O32 -> -28271 | P38: =IF(D38="","",SUM(D38:O38)) -> -597504 | Q38: /
C39: 収支 | D39: =D36-D33 -> 50533.767 | E39: =E36-E33 -> -54068.115 | F39: =F36-F33 -> -94059.945 | G39: =G36-G33 -> -107981.9 | H39: =H36-H33 -> 17582.794 | I39: =I36-I33 -> -283180.17 | J39: =J36-J33 -> 16767.598 | K39: =K36-K33 -> 116821.46 | ... O39: =O36-O33 -> 24810.16 | P39: =IF(D39="","",SUM(D39:O39)) -> -236585.05 | Q39: /
B41: (FY-2)年間予算達成率
B42: 【 予実対比 】 | D42: 2025年4月 | E42: 2025年5月 | F42: 2025年6月 | G42: 2025年7月 | H42: 2025年8月 | I42: 2025年9月 | J42: 2025年10月 | K42: 2025年11月 | L42: 2025年12月 | M42: 2026年1月 | N42: 2026年2月 | O42: 2026年3月 | P42: 合計 | Q42: 達成率
B43: 予算 | C43: 収入 | D43: 347771 | E43: 275744 | F43: 0 | G43: 388759 | H43: 388759 | I43: 388759 | J43: 388759 | K43: 388759 | L43: 448759 | M43: 388759 | N43: 388759 | O43: 388759 | P43: =IF(D43="","",SUM(D43:O43)) -> 4182346 | Q43: /
C44: 支出 | D44: 337608 | E44: 423456 | F44: 297375 | G44: 285200 | H44: 300200 | I44: 335200 | J44: 305200 | K44: 300200 | L44: 340200 | M44: 305200 | N44: 300200 | O44: 300200 | P44: =IF(D44="","",SUM(D44:O44)) -> 3830239 | Q44: /
C45: 収支 | D45: =D43-D44 -> 10163 | E45: =E43-E44 -> -147712 | F45: =F43-F44 -> -297375 | G45: =G43-G44 -> 103559 | H45: =H43-H44 -> 88559 | I45: =I43-I44 -> 53559 | J45: =J43-J44 -> 83559 | K45: =K43-K44 -> 88559 | ... O45: =O43-O44 -> 88559 | P45: =IF(D45="","",SUM(D45:O45)) -> 352107 | Q45: /
B46: 実績 | C46: 収入 | D46: =I15 -> 362756 | E46: =I16 -> 280024 | F46: =I17 -> 68896 | G46: =I18 -> 473086 | H46: =I19 -> 502474 | I46: =I20 -> 584444 | J46: =I21 -> 524857 | K46: =I22 -> 584601.18 | L46: =I23 -> 703578.01 | M46: =I24 -> 752868.15 | N46: =I25 -> 581951.13 | O46: =I26 -> 773052.25 | P46: =IF(D46="","",SUM(D46:O46)) -> 6192587.7 | Q46: =P46/P43 -> 1.4806493
C47: 支出 | D47: =H15 -> 328579 | E47: =H16 -> 458043 | F47: =H17 -> 320775 | G47: =H18 -> 314993 | H47: =H19 -> 335534 | I47: =H20 -> 340477 | J47: =H21 -> 514909 | K47: =H22 -> 566502 | L47: =H23 -> 557359 | M47: =H24 -> 821287 | N47: =H25 -> 382867 | O47: =H26 -> 570863 | P47: =IF(D47="","",SUM(D47:O47)) -> 5512188 | Q47: =P47/P44 -> 1.4391238
C48: 収支 | D48: =D46-D47 -> 34177 | E48: =E46-E47 -> -178019 | F48: =F46-F47 -> -251879 | G48: =G46-G47 -> 158093 | H48: =H46-H47 -> 166940 | I48: =I46-I47 -> 243967 | J48: =J46-J47 -> 9948 | K48: =K46-K47 -> 18099.183 | ... O48: =O46-O47 -> 202189.25 | P48: =IF(D48="","",SUM(D48:O48)) -> 680399.72 | Q48: =P48/P45 -> 1.9323664
B49: 差異 (実績-予算) | C49: 収入 | D49: =D46-D43 -> 14985 | E49: =E46-E43 -> 4280 | F49: =F46-F43 -> 68896 | G49: =G46-G43 -> 84327 | H49: =H46-H43 -> 113715 | I49: =I46-I43 -> 195685 | J49: =J46-J43 -> 136098 | K49: =K46-K43 -> 195842.18 | ... O49: =O46-O43 -> 384293.25 | P49: =IF(D49="","",SUM(D49:O49)) -> 2010241.7 | Q49: /
C50: 支出 | D50: =D47-D44 -> -9029 | E50: =E47-E44 -> 34587 | F50: =F47-F44 -> 23400 | G50: =G47-G44 -> 29793 | H50: =H47-H44 -> 35334 | I50: =I47-I44 -> 5277 | J50: =J47-J44 -> 209709 | K50: =K47-K44 -> 266302 | ... O50: =O47-O44 -> 270663 | P50: =IF(D50="","",SUM(D50:O50)) -> 1681949 | Q50: /
C51: 収支 | D51: =D48-D45 -> 24014 | E51: =E48-E45 -> -30307 | F51: =F48-F45 -> 45496 | G51: =G48-G45 -> 54534 | H51: =H48-H45 -> 78381 | I51: =I48-I45 -> 190408 | J51: =J48-J45 -> -73611 | K51: =K48-K45 -> -70459.817 | ... O51: =O48-O45 -> 113630.25 | P51: =IF(D51="","",SUM(D51:O51)) -> 328292.72 | Q51: /
B53: バージョン管理（1➡数字、Ⅰ➡ルーティン）
B54: ver | C54: 日付 | D54: 機能
B55: 1代目 | C55: 45413 | D55: 人生設計シート運用スタート（PPの2期目スタート時）
B56: Ⅰ代目 | C56: 45809 | D56: 別シートでルーティン記録シート運用スタート（X入社時）
B57: Ⅱ代目 | C57: 45839 | D57: サマリ機能の追加
B58: 1 | C58: 45886 | D58: 三井住友銀行の追加・クレカの管理方法変更・paypayカード導入
B59: 2 | C59: 45891 | D59: 5か年PLのタブ追加
B60: 3 | C60: 45903 | D60: Googleフォームの質問と回答タブを追加
B61: 4 | C61: 45903 | D61: 打った文字にリンクを挿入する技を身に付け月次収入タブの税金らへんに導入 | J61: ここ
B62: 5 | C62: 45920 | D62: 数式が入ったセルを入力する際に警告表示機能を追加
B63: 6 | C63: 45923 | D63: 温泉（館内での食事代含む）タブを削除⇒1人なら体験へ。メシ代はメシ代へ計上に！
B64: 7 | C64: 46043 | D64: 保険料のシート更新（協会けんぽのままだったが東京都情報サービス産業健康保険組合追加
B65: 8 | C65: 46054 | D65: ARRAYFORMULA関数を導入（日次シート）→1番上以外は一切触れない
B66: 9 | C66: 46060 | D66: 減価償却的に書いてた年間プラン削除→物品をまとめて1年分買ったという計上とする。
B67: Ⅰ代目
B68: 1 | C68: 45923 | D68: 月の目標（テーマ）とその月の振返りを1番上に記載できるように変更

Sheet (FY-2)資産管理
B2: ※月末時点の情報を入力 | C2: ※確定 | D2: ※確定 | E2: ※確定 | F2: ※確定 | G2: ※確定 | H2: ※確定 | I2: ※確定 | J2: ※確定 | K2: ※確定 | L2: ※確定 | M2: ※確定 | N2: ※確定
B3: (FY-2)資産管理表 | C3: 2025年4月 | D3: 2025年5月 | E3: 2025年6月 | F3: 2025年7月 | G3: 2025年8月 | H3: 2025年9月 | I3: 2025年10月 | J3: 2025年11月 | K3: 2025年12月 | L3: 2026年1月 | M3: 2026年2月 | N3: 2026年3月 | O3: 合計 | P3: 平均
A4: ※ | B4: 銀行預金 | C4: =SUM(C5:C8) -> 109418 | D4: =SUM(D5:D8) -> 163655 | E4: =SUM(E5:E8) -> 48459 | F4: =SUM(F5:F8) -> 20957 | G4: =SUM(G5:G8) -> 21010 | H4: =SUM(H5:H8) -> 25539 | I4: =SUM(I5:I8) -> 48910 | J4: =SUM(J5:J8) -> 30359 | ... N4: =SUM(N5:N8) -> 166502 | O4: =SUM(C4:N4) -> 1031073 | P4: =IFERROR(AVERAGE(C4:N4),"") -> 85922.75
B5: ①みずほ銀行／浜松町支店 | C5: =みずほ!J33 -> 101400 | D5: =みずほ!J64 -> 110380 | E5: =みずほ!J94 -> 35621 | F5: =みずほ!J125 -> 14033 | G5: =みずほ!J156 -> 13905 | H5: =みずほ!J186 -> 13900 | I5: =みずほ!J217 -> 34634 | J5: =みずほ!J247 -> 22620 | K5: =みずほ!J278 -> 58393 | L5: =みずほ!J309 -> 34755 | M5: =みずほ!J337 -> 23123 | N5: =みずほ!J368 -> 30684 | O5: =SUM(C5:N5) -> 493448 | P5: =IFERROR(AVERAGE(C5:N5),"") -> 41120.667
B6: ②三菱UFJ銀行／国立支店 | C6: =UFJ!I33 -> 8018 | D6: =UFJ!I64 -> 53275 | E6: =UFJ!I94 -> 12838 | F6: =UFJ!I125 -> 6924 | G6: =UFJ!I156 -> 325 | H6: =UFJ!I186 -> 325 | I6: =UFJ!I217 -> 325 | J6: =UFJ!I247 -> 325 | K6: =UFJ!I278 -> 325 | L6: =UFJ!I309 -> 325 | M6: =UFJ!I337 -> 0 | N6: =UFJ!I368 -> 0 | O6: =SUM(C6:N6) -> 83005 | P6: =IFERROR(AVERAGE(C6:N6),"") -> 6917.0833
B7: ③三井住友銀行／オリーブECRU(871)支店 | C7: =三井住友!I33 -> / | D7: =三井住友!I64 -> / | E7: =三井住友!I94 -> / | F7: =三井住友!I125 -> 0 | G7: =三井住友!I156 -> 6780 | H7: =三井住友!I186 -> 11314 | I7: =三井住友!I217 -> 13951 | J7: =三井住友!I247 -> 7414 | K7: =三井住友!I278 -> 27387 | L7: =三井住友!I309 -> 172576 | M7: =三井住友!I337 -> 78526 | N7: =三井住友!I368 -> 110842 | O7: =SUM(C7:N7) -> 428790 | P7: =IFERROR(AVERAGE(C7:N7),"") -> 47643.333
B8: ④楽天銀行／ベース支店 | C8: 0 | D8: 0 | E8: 0 | F8: 0 | G8: 0 | H8: 0 | I8: 0 | J8: 0 | K8: 0 | L8: 428 | M8: =楽天!J337 -> 426 | N8: =楽天!J368 -> 24976 | O8: =SUM(C8:N8) -> 25830 | P8: =IFERROR(AVERAGE(C8:N8),"") -> 2152.5
A9: ※ | B9: キャッシュレス残高 | C9: =SUM(C10:C19) -> 0 | D9: =SUM(D10:D19) -> 0 | E9: =SUM(E10:E19) -> 0 | F9: =SUM(F10:F19) -> 0 | G9: =SUM(G10:G19) -> 0 | H9: =SUM(H10:H19) -> 0 | I9: =SUM(I10:I19) -> 48221 | J9: =SUM(J10:J19) -> 59786 | ... N9: =SUM(N10:N19) -> 44002 | O9: =SUM(C9:N9) -> 288124 | P9: =IFERROR(AVERAGE(C9:N9),"") -> 24010.333
B10: ①PASMO残高 | C10: - | D10: - | E10: - | F10: - | G10: - | H10: - | I10: 19203 | J10: 19364 | K10: 18377 | L10: 13333 | M10: 19509 | N10: 2696 | O10: =SUM(C10:N10) -> 92482 | P10: =IFERROR(AVERAGE(C10:N10),"") -> 15413.667
B11: ②ANAPay残高 | C11: - | D11: - | E11: - | F11: - | G11: - | H11: - | I11: 8048 | J11: 21460 | K11: 870 | L11: 9160 | M11: 2740 | N11: 15740 | O11: =SUM(C11:N11) -> 58018 | P11: =IFERROR(AVERAGE(C11:N11),"") -> 9669.6667
B12: ③JALPay残高 | C12: - | D12: - | E12: - | F12: - | G12: - | H12: - | I12: 2 | J12: 0 | K12: 0 | L12: 0 | M12: 0 | N12: 0 | O12: =SUM(C12:N12) -> 2 | P12: =IFERROR(AVERAGE(C12:N12),"") -> 0.33333333
B13: ④PayPay残高 | C13: - | D13: - | E13: - | F13: - | G13: - | H13: - | I13: 5822 | J13: 9685 | K13: 17906 | L13: 11173 | M13: 309 | N13: 2980 | O13: =SUM(C13:N13) -> 47875 | P13: =IFERROR(AVERAGE(C13:N13),"") -> 7979.1667
B14: ⑤VポイントPay残高 | I14: 7693 | J14: 2798 | K14: 1126 | L14: 216 | M14: 216 | N14: 302 | O14: =SUM(C14:N14) -> 12351 | P14: =IFERROR(AVERAGE(C14:N14),"") -> 2058.5
B15: ⑥メルペイ残高 | I15: 1753 | J15: 381 | K15: 381 | L15: 381 | M15: 34 | N15: 34 | O15: =SUM(C15:N15) -> 2964 | P15: =IFERROR(AVERAGE(C15:N15),"") -> 494
B16: ⑦Pontaポイント | I16: 654 | J16: 657 | K16: 75 | L16: 533 | M16: 75 | N16: 86 | O16: =SUM(C16:N16) -> 2080 | P16: =IFERROR(AVERAGE(C16:N16),"") -> 346.66667
B17: ⑧dポイント | M17: 315 | N17: 5 | O17: =SUM(C17:N17) -> 320 | P17: =IFERROR(AVERAGE(C17:N17),"") -> 160
B18: ⑨PayPayポイント（自動運用） | C18: - | D18: - | E18: - | F18: - | G18: - | H18: - | I18: 4901 | J18: 5436 | K18: 7323 | L18: 14242 | M18: 17806 | N18: 22154 | O18: =SUM(C18:N18) -> 71862 | P18: =IFERROR(AVERAGE(C18:N18),"") -> 11977
B19: ICOCA残高 | C19: - | D19: - | E19: - | F19: - | G19: - | H19: - | I19: 145 | J19: 5 | K19: 5 | L19: 5 | M19: 5 | N19: 5 | O19: =SUM(C19:N19) -> 170 | P19: =IFERROR(AVERAGE(C19:N19),"") -> 28.333333
A20: ※ | B20: 暗号通貨(bitFlyer)*月末時点の総資産 | C20: 0 | D20: 0 | E20: 0 | F20: =F23+F26+F29 -> 6000 | G20: 12200 | H20: 18870 | I20: 23902 | J20: =J23+J26+J29 -> 6000 | K20: =K23+K26+K29 -> 6000 | L20: =L23+L26+L29 -> 0 | M20: =M23+M26+M29 -> 0 | N20: =N23+N26+N29 -> 0 | O20: =SUM(C20:N20) -> 72972 | P20: =IFERROR(AVERAGE(C20:N20),"") -> 6081
B21: 買い注文した額 | C21: / | D21: / | E21: / | F21: =F23+F26+F29 -> 6000 | G21: =G23+G26+G29 -> 6500 | H21: 6000 | I21: 6000 | J21: 6000 | K21: 6000 | L21: 0 | M21: 0 | N21: 0 | O21: =SUM(C21:N21) -> 36500 | P21: =IFERROR(AVERAGE(C21:N21),"") -> 4055.5556
B22: USD→JPY 為替 | C22: ¥149.93 / $1 | D22: ¥145.34 / $1 | E22: ¥144.51 / $1 | F22: ¥143.41 / $1 | G22: ¥147.32 / $1 | H22: ¥147.10 / $1 | I22: ¥152.50 / $1 | J22: ¥154.00 / $1 | K22: ¥155.80 / $1 | L22: 0 | M22: 0 | N22: 0 | O22: =SUM(C22:N22) -> 0 | P22: =IFERROR(AVERAGE(C22:N22),"") -> 0
B23: ①イーサリアム(Ethereum)/ETH | C23: 0 | D23: 0 | E23: 0 | F23: 3000 | G23: 3500 | H23: 3000 | I23: 5756 | J23: 3000 | K23: 4400 | L23: 0 | M23: 0 | N23: 0 | O23: =SUM(C23:N23) -> 22656 | P23: =IFERROR(AVERAGE(C23:N23),"") -> 1888
B24: ETH価格（JPY） | C24: 272950 | D24: 267320 | E24: 365460 | F24: 345190 | G24: 515970 | H24: 652915 | I24: 573675 | J24: 600833 | K24: 468144 | L24: 0 | M24: 0 | N24: 0 | O24: =SUM(C24:N24) -> 4062457 | P24: =IFERROR(AVERAGE(C24:N24),"") -> 338538.08
B25: ETH価格（USD） | C25: $1,822.14 | D25: $1,838.83 | E25: $2,529.32 | F25: $2,405.70 | G25: $3,508.6 | H25: $4,406.51 | I25: $3,762.46 | J25: $3,899.74 | K25: $2,842.8 | L25: 0 | M25: 0 | N25: 0 | O25: =SUM(C25:N25) -> 0 | P25: =IFERROR(AVERAGE(C25:N25),"") -> 0
B26: ②ビットコイン(Bitcoin)/BTC | C26: 0 | D26: 0 | E26: 0 | F26: 2000 | G26: 2000 | H26: 2000 | I26: 0 | J26: 2000 | K26: 1000 | L26: 0 | M26: 0 | N26: 0 | O26: =SUM(C26:N26) -> 9000 | P26: =IFERROR(AVERAGE(C26:N26),"") -> 750
B27: BTC価格（JPY） | C27: 12772240 | D27: 15217000 | E27: 15340000 | F27: 15349296 | G27: 16708900 | H27: 16100344 | I27: 16919257 | J27: 17025072 | K27: 14096354 | L27: 0 | M27: 0 | N27: 0 | O27: =SUM(C27:N27) -> 139528463 | P27: =IFERROR(AVERAGE(C27:N27),"") -> 11627372
B28: BTC価格（USD） | C28: $85,190 | D28: $104,638 | E28: $106,159 | F28: $106,800 | G28: $113,396 | H28: $109,216 | I28: $110,923 | J28: $110,660 | K28: $86,563.4 | L28: 0 | M28: 0 | N28: 0 | O28: =SUM(C28:N28) -> 0 | P28: =IFERROR(AVERAGE(C28:N28),"") -> 0
B29: ③エックスアールピー(XRP)/XRP | C29: 0 | D29: 0 | E29: 0 | F29: 1000 | G29: 1000 | H29: 1000 | I29: 244 | J29: 1000 | K29: 600 | L29: 0 | M29: 0 | N29: 0 | O29: =SUM(C29:N29) -> 4844 | P29: =IFERROR(AVERAGE(C29:N29),"") -> 403.66667
B30: XRP価格（JPY） | C30: 314 | D30: 368 | E30: 361 | F30: 400 | G30: 432 | H30: 411.89 | I30: 369.65 | J30: 388 | K30: 337.4 | L30: 0 | M30: 0 | N30: 0 | O30: =SUM(C30:N30) -> 3381.94 | P30: =IFERROR(AVERAGE(C30:N30),"") -> 281.82833
B31: XRP価格（USD） | C31: $2.10 | D31: $2.53 | E31: $2.50 | F31: $2.79 | G31: $2.94 | H31: $2.77 | I31: $2.43 | J31: $2.5 | K31: $2.05 | L31: 0 | M31: 0 | N31: 0 | O31: =SUM(C31:N31) -> 0 | P31: =IFERROR(AVERAGE(C31:N31),"") -> 0
A32: ※ | B32: 証券口座 | C32: =SUM(C33:C35) -> 0 | D32: =SUM(D33:D35) -> 0 | E32: =SUM(E33:E35) -> 0 | F32: =SUM(F33:F35) -> 0 | G32: =SUM(G33:G35) -> 0 | H32: =SUM(H33:H35) -> 0 | I32: =SUM(I33:I35) -> 0 | J32: =SUM(J33:J35) -> 0 | ... N32: =SUM(N33:N35) -> 0 | O32: =SUM(C32:N32) -> 94680 | P32: =IFERROR(AVERAGE(C32:N32),"") -> 7890
B33: ①楽天証券 | C33: 0 | D33: 0 | E33: 0 | F33: 0 | G33: 0 | H33: 0 | I33: 0 | J33: 0 | K33: 0 | L33: 94680 | M33: 0 | N33: 0 | O33: =SUM(C33:N33) -> 94680 | P33: =IFERROR(AVERAGE(C33:N33),"") -> 7890
B34: ② | C34: 0 | D34: 0 | E34: 0 | F34: 0 | G34: 0 | H34: 0 | I34: 0 | J34: 0 | K34: 0 | L34: 0 | M34: 0 | N34: 0 | O34: =SUM(C34:N34) -> 0 | P34: =IFERROR(AVERAGE(C34:N34),"") -> 0
B35: ③ | C35: 0 | D35: 0 | E35: 0 | F35: 0 | G35: 0 | H35: 0 | I35: 0 | J35: 0 | K35: 0 | L35: 0 | M35: 0 | N35: 0 | O35: =SUM(C35:N35) -> 0 | P35: =IFERROR(AVERAGE(C35:N35),"") -> 0
B36: 株式資産／国内株式 | C36: =SUM(C37:C39) -> 0 | D36: =SUM(D37:D39) -> 0 | E36: =SUM(E37:E39) -> 0 | F36: =SUM(F37:F39) -> 0 | G36: =SUM(G37:G39) -> 0 | H36: =SUM(H37:H39) -> 0 | I36: =SUM(I37:I39) -> 0 | J36: =SUM(J37:J39) -> 0 | ... N36: =SUM(N37:N39) -> 0 | O36: =SUM(C36:N36) -> 94680 | P36: =IFERROR(AVERAGE(C36:N36),"") -> 7890
B37: ①サンリオ | C37: 0 | D37: 0 | E37: 0 | F37: 0 | G37: 0 | H37: 0 | I37: 0 | J37: 0 | K37: 0 | L37: 94680 | M37: 0 | N37: 0 | O37: =SUM(C37:N37) -> 94680 | P37: =IFERROR(AVERAGE(C37:N37),"") -> 7890
B38: ② | C38: 0 | D38: 0 | E38: 0 | F38: 0 | G38: 0 | H38: 0 | I38: 0 | J38: 0 | K38: 0 | L38: 0 | M38: 0 | N38: 0 | O38: =SUM(C38:N38) -> 0 | P38: =IFERROR(AVERAGE(C38:N38),"") -> 0
B39: ③ | C39: 0 | D39: 0 | E39: 0 | F39: 0 | G39: 0 | H39: 0 | I39: 0 | J39: 0 | K39: 0 | L39: 0 | M39: 0 | N39: 0 | O39: =SUM(C39:N39) -> 0 | P39: =IFERROR(AVERAGE(C39:N39),"") -> 0
B40: 株式資産／米国株式 | C40: =SUM(C41:C43) -> 0 | D40: =SUM(D41:D43) -> 0 | E40: =SUM(E41:E43) -> 0 | F40: =SUM(F41:F43) -> 0 | G40: =SUM(G41:G43) -> 0 | H40: =SUM(H41:H43) -> 0 | I40: =SUM(I41:I43) -> 0 | J40: =SUM(J41:J43) -> 0 | ... N40: =SUM(N41:N43) -> 0 | O40: =SUM(C40:N40) -> 0 | P40: =IFERROR(AVERAGE(C40:N40),"") -> 0
B41: ① | C41: 0 | D41: 0 | E41: 0 | F41: 0 | G41: 0 | H41: 0 | I41: 0 | J41: 0 | K41: 0 | L41: 0 | M41: 0 | N41: 0 | O41: =SUM(C41:N41) -> 0 | P41: =IFERROR(AVERAGE(C41:N41),"") -> 0
B42: ② | C42: 0 | D42: 0 | E42: 0 | F42: 0 | G42: 0 | H42: 0 | I42: 0 | J42: 0 | K42: 0 | L42: 0 | M42: 0 | N42: 0 | O42: =SUM(C42:N42) -> 0 | P42: =IFERROR(AVERAGE(C42:N42),"") -> 0
B43: ③ | C43: 0 | D43: 0 | E43: 0 | F43: 0 | G43: 0 | H43: 0 | I43: 0 | J43: 0 | K43: 0 | L43: 0 | M43: 0 | N43: 0 | O43: =SUM(C43:N43) -> 0 | P43: =IFERROR(AVERAGE(C43:N43),"") -> 0
B44: 投資信託 | C44: =SUM(C45:C47) -> 0 | D44: =SUM(D45:D47) -> 0 | E44: =SUM(E45:E47) -> 0 | F44: =SUM(F45:F47) -> 0 | G44: =SUM(G45:G47) -> 0 | H44: =SUM(H45:H47) -> 0 | I44: =SUM(I45:I47) -> 0 | J44: =SUM(J45:J47) -> 0 | ... N44: =SUM(N45:N47) -> 0 | O44: =SUM(C44:N44) -> 0 | P44: =IFERROR(AVERAGE(C44:N44),"") -> 0
B45: ① | C45: 0 | D45: 0 | E45: 0 | F45: 0 | G45: 0 | H45: 0 | I45: 0 | J45: 0 | K45: 0 | L45: 0 | M45: 0 | N45: 0 | O45: =SUM(C45:N45) -> 0 | P45: =IFERROR(AVERAGE(C45:N45),"") -> 0
B46: ② | C46: 0 | D46: 0 | E46: 0 | F46: 0 | G46: 0 | H46: 0 | I46: 0 | J46: 0 | K46: 0 | L46: 0 | M46: 0 | N46: 0
B47: ③ | C47: 0 | D47: 0 | E47: 0 | F47: 0 | G47: 0 | H47: 0 | I47: 0 | J47: 0 | K47: 0 | L47: 0 | M47: 0 | N47: 0 | O47: =SUM(C47:N47) -> 0 | P47: =IFERROR(AVERAGE(C47:N47),"") -> 0
B48: その他、投資 | C48: =SUM(C49:C50) -> 0 | D48: =SUM(D49:D50) -> 0 | E48: =SUM(E49:E50) -> 0 | F48: =SUM(F49:F50) -> 0 | G48: =SUM(G49:G50) -> 0 | H48: =SUM(H49:H50) -> 0 | I48: =SUM(I49:I50) -> 0 | J48: =SUM(J49:J50) -> 0 | ... N48: =SUM(N49:N50) -> 46000 | O48: =SUM(C48:N48) -> 46000 | P48: =IFERROR(AVERAGE(C48:N48),"") -> 3833.3333
B49: ①iDeCo積立 | C49: 0 | D49: 0 | E49: 0 | F49: 0 | G49: 0 | H49: 0 | I49: 0 | J49: 0 | K49: 0 | L49: 0 | M49: 0 | N49: 46000 | O49: =SUM(C49:N49) -> 46000 | P49: =IFERROR(AVERAGE(C49:N49),"") -> 3833.3333
B50: ② | C50: 0 | D50: 0 | E50: 0 | F50: 0 | G50: 0 | H50: 0 | I50: 0 | J50: 0 | K50: 0 | L50: 0 | M50: 0 | N50: 0 | O50: =SUM(C50:N50) -> 0 | P50: =IFERROR(AVERAGE(C50:N50),"") -> 0
B51: 配当金 | C51: =SUM(C52:C53) -> 0 | D51: =SUM(D52:D53) -> 0 | E51: =SUM(E52:E53) -> 0 | F51: =SUM(F52:F53) -> 0 | G51: =SUM(G52:G53) -> 0 | H51: =SUM(H52:H53) -> 0 | I51: =SUM(I52:I53) -> 0 | J51: =SUM(J52:J53) -> 0 | ... N51: =SUM(N52:N53) -> 0 | O51: =SUM(C51:N51) -> 0 | P51: =IFERROR(AVERAGE(C51:N51),"") -> 0
B52: ①〇〇 | C52: 0 | D52: 0 | E52: 0 | F52: 0 | G52: 0 | H52: 0 | I52: 0 | J52: 0 | K52: 0 | L52: 0 | M52: 0 | N52: 0 | O52: =SUM(C52:N52) -> 0 | P52: =IFERROR(AVERAGE(C52:N52),"") -> 0
B53: ②〇〇 | C53: 0 | D53: 0 | E53: 0 | F53: 0 | G53: 0 | H53: 0 | I53: 0 | J53: 0 | K53: 0 | L53: 0 | M53: 0 | N53: 0 | O53: =SUM(C53:N53) -> 0 | P53: =IFERROR(AVERAGE(C53:N53),"") -> 0
A54: ★ | B54: 総資産 | C54: =C4+C9+C20+C32+C48 -> 109418 | D54: =D4+D9+D20+D32+D48 -> 163655 | E54: =E4+E9+E20+E32+E48 -> 48459 | F54: =F4+F9+F20+F32+F48 -> 26957 | G54: =G4+G9+G20+G32+G48 -> 33210 | H54: =H4+H9+H20+H32+H48 -> 44409 | I54: =I4+I9+I20+I32+I48 -> 121033 | J54: =J4+J9+J20+J32+J48 -> 96145 | ... N54: =N4+N9+N20+N32+N48 -> 256504 | O54: =SUM(C54:N54) -> 1532849 | P54: =IFERROR(AVERAGE(C54:N54),"") -> 127737.42
B55: 目標 | C55: 100000 | D55: 100000 | E55: 100000 | F55: 100000 | G55: 100000 | H55: 100000 | I55: 100000 | J55: 100000 | K55: 100000 | L55: 100000 | M55: 100000 | N55: 100000 | O55: =SUM(C55:N55) -> 1200000 | P55: =IFERROR(AVERAGE(C55:N55),"") -> 100000
B56: 達成率 | C56: =SUM(C54)/(C55) -> 1.09418 | D56: =SUM(D54)/(D55) -> 1.63655 | E56: =SUM(E54)/(E55) -> 0.48459 | F56: =SUM(F54)/(F55) -> 0.26957 | G56: =SUM(G54)/(G55) -> 0.3321 | H56: =SUM(H54)/(H55) -> 0.44409 | I56: =SUM(I54)/(I55) -> 1.21033 | J56: =SUM(J54)/(J55) -> 0.96145 | ... N56: =SUM(N54)/(N55) -> 2.56504 | O56: =SUM(C56:N56) -> 15.32849 | P56: =IFERROR(AVERAGE(C56:N56),"") -> 1.2773742
B75: ■配当収入推移 | C75: 1月 | D75: 2月 | E75: 3月 | F75: 4月 | G75: 5月 | H75: 6月 | I75: 7月 | J75: 8月 | K75: 9月 | L75: 10月 | M75: 11月 | N75: 12月 | O75: 合計
B76: 2025年 | C76: 0 | D76: 0 | E76: 0 | F76: 0 | G76: 0 | H76: 0 | I76: 0 | J76: 0 | K76: 0 | L76: 0 | M76: 0 | N76: 0 | O76: =SUM(C76:N76) -> 0
B77: 2026年 | C77: 0 | D77: 0 | E77: 0 | F77: 0 | G77: 0 | H77: 0 | I77: 0 | J77: 0 | K77: 0 | L77: 0 | M77: 0 | N77: 0 | O77: =SUM(C77:N77) -> 0

Sheet (FY-3)資産管理
B2: ※月末時点の情報を入力 | C2: ※確定 | D2: ※確定 | E2: ※確定 | F2: 未確定 | G2: 未確定 | H2: 未確定 | I2: 未確定 | J2: 未確定 | K2: 未確定 | L2: 未確定 | M2: 未確定 | N2: 未確定
B3: (FY-3)資産管理表 | C3: 2026年4月 | D3: 2026年5月 | E3: 2026年6月 | F3: 2026年7月 | G3: 2026年8月 | H3: 2026年9月 | I3: 2026年10月 | J3: 2026年11月 | K3: 2026年12月 | L3: 2027年1月 | M3: 2027年2月 | N3: 2027年3月 | O3: 平均
A4: ※ | B4: 銀行預金 | C4: =SUM(C5:C8) -> 931 | D4: =SUM(D5:D8) -> 53860 | E4: =SUM(E5:E8) -> 151188 | F4: =SUM(F5:F8) -> 293091 | G4: =SUM(G5:G8) -> 462994 | H4: =SUM(H5:H8) -> 582897 | I4: =SUM(I5:I8) -> 702800 | J4: =SUM(J5:J8) -> 822703 | ... N4: =SUM(N5:N8) -> 1302315 | O4: =IFERROR(AVERAGE(C4:N4),"") -> 630025.5
B5: ①みずほ銀行／浜松町支店 | C5: =みずほ!J398 -> 8 | D5: =みずほ!J429 -> 32259 | E5: =みずほ!J459 -> 72765 | F5: =みずほ!J490 -> 252668 | G5: =みずほ!J521 -> 422571 | H5: =みずほ!J551 -> 442474 | I5: =みずほ!J582 -> 462377 | J5: =みずほ!J612 -> 482280 | K5: =みずほ!J643 -> 502183 | L5: =みずほ!J674 -> 522086 | M5: =みずほ!J702 -> 541989 | N5: =みずほ!J733 -> 561892 | O5: =IFERROR(AVERAGE(C5:N5),"") -> 357962.67
B6: ②三菱UFJ銀行／国立支店 | C6: =UFJ!I398 -> 0 | D6: =UFJ!I429 -> 0 | E6: =UFJ!I459 -> 0 | F6: =UFJ!I490 -> 0 | G6: =UFJ!I521 -> 0 | H6: =UFJ!I551 -> 0 | I6: =UFJ!I582 -> 0 | J6: =UFJ!I612 -> 0 | K6: =UFJ!I643 -> 0 | L6: =UFJ!I674 -> 0 | M6: =UFJ!I702 -> 0 | N6: =UFJ!I733 -> 0 | O6: =IFERROR(AVERAGE(C6:N6),"") -> 0
B7: ③三井住友銀行／オリーブECRU(871)支店 | C7: =三井住友!I398 -> 909 | D7: =三井住友!I429 -> 4210 | E7: =三井住友!I459 -> 57550 | F7: =三井住友!I490 -> 19550 | G7: =三井住友!I521 -> 19550 | H7: =三井住友!I551 -> 119550 | I7: =三井住友!I582 -> 219550 | J7: =三井住友!I612 -> 319550 | K7: =三井住友!I643 -> 419550 | L7: =三井住友!I674 -> 519550 | M7: =三井住友!I702 -> 619550 | N7: =三井住友!I733 -> 719550 | O7: =IFERROR(AVERAGE(C7:N7),"") -> 253218.25
B8: ④楽天銀行／ベース支店 | C8: =楽天!J398 -> 14 | D8: =楽天!J429 -> 17391 | E8: =楽天!J459 -> 20873 | F8: =楽天!J490 -> 20873 | G8: =楽天!J521 -> 20873 | H8: =楽天!J551 -> 20873 | I8: =楽天!J582 -> 20873 | J8: =楽天!J612 -> 20873 | K8: =楽天!J643 -> 20873 | L8: =楽天!J674 -> 20873 | M8: =楽天!J702 -> 20873 | N8: =楽天!J733 -> 20873 | O8: =IFERROR(AVERAGE(C8:N8),"") -> 18844.583
A9: ※ | B9: キャッシュレス残高 | C9: =SUM(C10:C19) -> 52921 | D9: =SUM(D10:D19) -> 70655 | E9: =SUM(E10:E19) -> 22611 | F9: =SUM(F10:F19) -> 0 | G9: =SUM(G10:G19) -> 0 | H9: =SUM(H10:H19) -> 0 | I9: =SUM(I10:I19) -> 145 | J9: =SUM(J10:J19) -> 5 | ... N9: =SUM(N10:N19) -> 5 | O9: =IFERROR(AVERAGE(C9:N9),"") -> 12256.167
B10: ①PASMO残高 | C10: 10000 | D10: 18283 | E10: 17924 | O10: =IFERROR(AVERAGE(C10:N10),"") -> 15402.333
B11: ②ANAPay残高 | C11: 5000 | D11: 6860 | E11: 2060 | O11: =IFERROR(AVERAGE(C11:N11),"") -> 4640
B12: ③JALPay残高 | C12: 0 | D12: 0 | E12: 0 | O12: =IFERROR(AVERAGE(C12:N12),"") -> 0
B13: ④PayPay残高 | C13: 273 | D13: 4575 | E13: 9 | O13: =IFERROR(AVERAGE(C13:N13),"") -> 1619
B14: ⑤VポイントPay残高 | C14: 302 | D14: 302 | E14: 302 | O14: =IFERROR(AVERAGE(C14:N14),"") -> 302
B15: ⑥メルペイ残高 | C15: 34 | D15: 34 | E15: 34 | O15: =IFERROR(AVERAGE(C15:N15),"") -> 34
B16: ⑦Pontaポイント | C16: 607 | D16: 7 | E16: 109 | O16: =IFERROR(AVERAGE(C16:N16),"") -> 241
B17: ⑧dポイント | C17: 1105 | D17: 65 | E17: 65 | O17: =IFERROR(AVERAGE(C17:N17),"") -> 411.66667
B18: ⑨PayPayポイント（自動運用） | C18: 35600 | D18: 40529 | E18: 2108 | O18: =IFERROR(AVERAGE(C18:N18),"") -> 26079
B19: ICOCA残高 | C19: - | D19: - | E19: - | F19: - | G19: - | H19: - | I19: 145 | J19: 5 | K19: 5 | L19: 5 | M19: 722 | N19: 5 | O19: =IFERROR(AVERAGE(C19:N19),"") -> 147.83333
A20: ※ | B20: 暗号通貨(bitFlyer)*月末時点の総資産 | C20: 0 | D20: 0 | E20: 0 | F20: =F23+F26+F29 -> 6000 | G20: 12200 | H20: 18870 | I20: 23902 | J20: =J23+J26+J29 -> 6000 | K20: =K23+K26+K29 -> 6000 | L20: =L23+L26+L29 -> 0 | M20: =M23+M26+M29 -> 0 | N20: =N23+N26+N29 -> 0 | O20: =IFERROR(AVERAGE(C20:N20),"") -> 6081
B21: 買い注文した額 | C21: / | D21: / | E21: / | F21: =F23+F26+F29 -> 6000 | G21: =G23+G26+G29 -> 6500 | H21: 6000 | I21: 6000 | J21: 6000 | K21: 6000 | L21: 0 | M21: 0 | N21: =N23+N26+N29 -> 0 | O21: =IFERROR(AVERAGE(C21:N21),"") -> 4055.5556
B22: USD→JPY 為替 | C22: ¥149.93 / $1 | D22: ¥145.34 / $1 | E22: ¥144.51 / $1 | F22: ¥143.41 / $1 | G22: ¥147.32 / $1 | H22: ¥147.10 / $1 | I22: ¥152.50 / $1 | J22: ¥154.00 / $1 | K22: ¥155.80 / $1 | L22: 0 | M22: 0 | O22: =IFERROR(AVERAGE(C22:N22),"") -> 0
B23: ①イーサリアム(Ethereum)/ETH | C23: 0 | D23: 0 | E23: 0 | F23: 3000 | G23: 3500 | H23: 3000 | I23: 5756 | J23: 3000 | K23: 4400 | L23: 0 | M23: 0 | N23: 0 | O23: =IFERROR(AVERAGE(C23:N23),"") -> 1888
B24: ETH価格（JPY） | C24: 272950 | D24: 267320 | E24: 365460 | F24: 345190 | G24: 515970 | H24: 652915 | I24: 573675 | J24: 600833 | K24: 468144 | L24: 0 | M24: 0 | O24: =IFERROR(AVERAGE(C24:N24),"") -> 369314.27
B25: ETH価格（USD） | C25: $1,822.14 | D25: $1,838.83 | E25: $2,529.32 | F25: $2,405.70 | G25: $3,508.6 | H25: $4,406.51 | I25: $3,762.46 | J25: $3,899.74 | K25: $2,842.8 | L25: 0 | M25: 0 | O25: =IFERROR(AVERAGE(C25:N25),"") -> 0
B26: ②ビットコイン(Bitcoin)/BTC | C26: 0 | D26: 0 | E26: 0 | F26: 2000 | G26: 2000 | H26: 2000 | I26: 0 | J26: 2000 | K26: 1000 | L26: 0 | M26: 0 | N26: 0 | O26: =IFERROR(AVERAGE(C26:N26),"") -> 750
B27: BTC価格（JPY） | C27: 12772240 | D27: 15217000 | E27: 15340000 | F27: 15349296 | G27: 16708900 | H27: 16100344 | I27: 16919257 | J27: 17025072 | K27: 14096354 | L27: 0 | M27: 0 | O27: =IFERROR(AVERAGE(C27:N27),"") -> 12684406
B28: BTC価格（USD） | C28: $85,190 | D28: $104,638 | E28: $106,159 | F28: $106,800 | G28: $113,396 | H28: $109,216 | I28: $110,923 | J28: $110,660 | K28: $86,563.4 | L28: 0 | M28: 0 | O28: =IFERROR(AVERAGE(C28:N28),"") -> 0
B29: ③エックスアールピー(XRP)/XRP | C29: 0 | D29: 0 | E29: 0 | F29: 1000 | G29: 1000 | H29: 1000 | I29: 244 | J29: 1000 | K29: 600 | L29: 0 | M29: 0 | N29: 0 | O29: =IFERROR(AVERAGE(C29:N29),"") -> 403.66667
B30: XRP価格（JPY） | C30: 314 | D30: 368 | E30: 361 | F30: 400 | G30: 432 | H30: 411.89 | I30: 369.65 | J30: 388 | K30: 337.4 | L30: 0 | M30: 0 | O30: =IFERROR(AVERAGE(C30:N30),"") -> 307.44909
B31: XRP価格（USD） | C31: $2.10 | D31: $2.53 | E31: $2.50 | F31: $2.79 | G31: $2.94 | H31: $2.77 | I31: $2.43 | J31: $2.5 | K31: $2.05 | L31: 0 | M31: 0 | O31: =IFERROR(AVERAGE(C31:N31),"") -> 0
A32: ※ | B32: 証券口座 | C32: =SUM(C33:C35) -> 0 | D32: =SUM(D33:D35) -> 0 | E32: =SUM(E33:E35) -> 0 | F32: =SUM(F33:F35) -> 0 | G32: =SUM(G33:G35) -> 0 | H32: =SUM(H33:H35) -> 0 | I32: =SUM(I33:I35) -> 0 | J32: =SUM(J33:J35) -> 0 | ... N32: =SUM(N33:N35) -> 0 | O32: =IFERROR(AVERAGE(C32:N32),"") -> 7890
B33: ①楽天証券 | C33: 0 | D33: 0 | E33: 0 | F33: 0 | G33: 0 | H33: 0 | I33: 0 | J33: 0 | K33: 0 | L33: 94680 | M33: 0 | N33: 0 | O33: =IFERROR(AVERAGE(C33:N33),"") -> 7890
B34: ② | C34: 0 | D34: 0 | E34: 0 | F34: 0 | G34: 0 | H34: 0 | I34: 0 | J34: 0 | K34: 0 | L34: 0 | M34: 0 | N34: 0 | O34: =IFERROR(AVERAGE(C34:N34),"") -> 0
B35: ③ | C35: 0 | D35: 0 | E35: 0 | F35: 0 | G35: 0 | H35: 0 | I35: 0 | J35: 0 | K35: 0 | L35: 0 | M35: 0 | N35: 0 | O35: =IFERROR(AVERAGE(C35:N35),"") -> 0
B36: 株式資産／国内株式 | C36: =SUM(C37:C39) -> 0 | D36: =SUM(D37:D39) -> 0 | E36: =SUM(E37:E39) -> 0 | F36: =SUM(F37:F39) -> 0 | G36: =SUM(G37:G39) -> 0 | H36: =SUM(H37:H39) -> 0 | I36: =SUM(I37:I39) -> 0 | J36: =SUM(J37:J39) -> 0 | ... N36: =SUM(N37:N39) -> 0 | O36: =IFERROR(AVERAGE(C36:N36),"") -> 7890
B37: ①サンリオ | C37: 0 | D37: 0 | E37: 0 | F37: 0 | G37: 0 | H37: 0 | I37: 0 | J37: 0 | K37: 0 | L37: 94680 | M37: 0 | N37: 0 | O37: =IFERROR(AVERAGE(C37:N37),"") -> 7890
B38: ② | C38: 0 | D38: 0 | E38: 0 | F38: 0 | G38: 0 | H38: 0 | I38: 0 | J38: 0 | K38: 0 | L38: 0 | M38: 0 | N38: 0 | O38: =IFERROR(AVERAGE(C38:N38),"") -> 0
B39: ③ | C39: 0 | D39: 0 | E39: 0 | F39: 0 | G39: 0 | H39: 0 | I39: 0 | J39: 0 | K39: 0 | L39: 0 | M39: 0 | N39: 0 | O39: =IFERROR(AVERAGE(C39:N39),"") -> 0
B40: 株式資産／米国株式 | C40: =SUM(C41:C43) -> 0 | D40: =SUM(D41:D43) -> 0 | E40: =SUM(E41:E43) -> 0 | F40: =SUM(F41:F43) -> 0 | G40: =SUM(G41:G43) -> 0 | H40: =SUM(H41:H43) -> 0 | I40: =SUM(I41:I43) -> 0 | J40: =SUM(J41:J43) -> 0 | ... N40: =SUM(N41:N43) -> 0 | O40: =IFERROR(AVERAGE(C40:N40),"") -> 0
B41: ① | C41: 0 | D41: 0 | E41: 0 | F41: 0 | G41: 0 | H41: 0 | I41: 0 | J41: 0 | K41: 0 | L41: 0 | M41: 0 | N41: 0 | O41: =IFERROR(AVERAGE(C41:N41),"") -> 0
B42: ② | C42: 0 | D42: 0 | E42: 0 | F42: 0 | G42: 0 | H42: 0 | I42: 0 | J42: 0 | K42: 0 | L42: 0 | M42: 0 | N42: 0 | O42: =IFERROR(AVERAGE(C42:N42),"") -> 0
B43: ③ | C43: 0 | D43: 0 | E43: 0 | F43: 0 | G43: 0 | H43: 0 | I43: 0 | J43: 0 | K43: 0 | L43: 0 | M43: 0 | N43: 0 | O43: =IFERROR(AVERAGE(C43:N43),"") -> 0
B44: 投資信託 | C44: =SUM(C45:C47) -> 0 | D44: =SUM(D45:D47) -> 0 | E44: =SUM(E45:E47) -> 0 | F44: =SUM(F45:F47) -> 0 | G44: =SUM(G45:G47) -> 0 | H44: =SUM(H45:H47) -> 0 | I44: =SUM(I45:I47) -> 0 | J44: =SUM(J45:J47) -> 0 | ... N44: =SUM(N45:N47) -> 0 | O44: =IFERROR(AVERAGE(C44:N44),"") -> 0
B45: ① | C45: 0 | D45: 0 | E45: 0 | F45: 0 | G45: 0 | H45: 0 | I45: 0 | J45: 0 | K45: 0 | L45: 0 | M45: 0 | N45: 0 | O45: =IFERROR(AVERAGE(C45:N45),"") -> 0
B46: ② | C46: 0 | D46: 0 | E46: 0 | F46: 0 | G46: 0 | H46: 0 | I46: 0 | J46: 0 | K46: 0 | L46: 0 | M46: 0 | N46: 0
B47: ③ | C47: 0 | D47: 0 | E47: 0 | F47: 0 | G47: 0 | H47: 0 | I47: 0 | J47: 0 | K47: 0 | L47: 0 | M47: 0 | N47: 0 | O47: =IFERROR(AVERAGE(C47:N47),"") -> 0
B48: その他、投資 | C48: =SUM(C49:C50) -> 23000 | D48: =SUM(D49:D50) -> 23000 | E48: =SUM(E49:E50) -> 23000 | F48: =SUM(F49:F50) -> 23000 | G48: =SUM(G49:G50) -> 23000 | H48: =SUM(H49:H50) -> 23000 | I48: =SUM(I49:I50) -> 23000 | J48: =SUM(J49:J50) -> 23000 | ... N48: =SUM(N49:N50) -> 23000 | O48: =IFERROR(AVERAGE(C48:N48),"") -> 23000
B49: ①iDeCo積立 | C49: 23000 | D49: 23000 | E49: 23000 | F49: 23000 | G49: 23000 | H49: 23000 | I49: 23000 | J49: 23000 | K49: 23000 | L49: 23000 | M49: 23000 | N49: 23000 | O49: =IFERROR(AVERAGE(C49:N49),"") -> 23000
B50: ② | C50: 0 | D50: 0 | E50: 0 | F50: 0 | G50: 0 | H50: 0 | I50: 0 | J50: 0 | K50: 0 | L50: 0 | M50: 0 | N50: 0 | O50: =IFERROR(AVERAGE(C50:N50),"") -> 0
B51: 配当金 | C51: =SUM(C52:C53) -> 0 | D51: =SUM(D52:D53) -> 0 | E51: =SUM(E52:E53) -> 0 | F51: =SUM(F52:F53) -> 0 | G51: =SUM(G52:G53) -> 0 | H51: =SUM(H52:H53) -> 0 | I51: =SUM(I52:I53) -> 0 | J51: =SUM(J52:J53) -> 0 | ... N51: =SUM(N52:N53) -> 0 | O51: =IFERROR(AVERAGE(C51:N51),"") -> 0
B52: ①〇〇 | C52: 0 | D52: 0 | E52: 0 | F52: 0 | G52: 0 | H52: 0 | I52: 0 | J52: 0 | K52: 0 | L52: 0 | M52: 0 | N52: 0 | O52: =IFERROR(AVERAGE(C52:N52),"") -> 0
B53: ②〇〇 | C53: 0 | D53: 0 | E53: 0 | F53: 0 | G53: 0 | H53: 0 | I53: 0 | J53: 0 | K53: 0 | L53: 0 | M53: 0 | N53: 0 | O53: =IFERROR(AVERAGE(C53:N53),"") -> 0
A54: ★ | B54: 総資産 | C54: =C4+C9+C20+C32+C48 -> 76852 | D54: =D4+D9+D20+D32+D48 -> 147515 | E54: =E4+E9+E20+E32+E48 -> 196799 | F54: =F4+F9+F20+F32+F48 -> 322091 | G54: =G4+G9+G20+G32+G48 -> 498194 | H54: =H4+H9+H20+H32+H48 -> 624767 | I54: =I4+I9+I20+I32+I48 -> 749847 | J54: =J4+J9+J20+J32+J48 -> 851708 | ... N54: =N4+N9+N20+N32+N48 -> 1325320 | O54: =IFERROR(AVERAGE(C54:N54),"") -> 679252.67
B55: 目標 | C55: 100000 | D55: 100000 | E55: 100000 | F55: 100000 | G55: 100000 | H55: 100000 | I55: 100000 | J55: 100000 | K55: 100000 | L55: 100000 | M55: 100000 | N55: 100000 | O55: =IFERROR(AVERAGE(C55:N55),"") -> 100000
B56: 達成率 | C56: =SUM(C54)/(C55) -> 0.76852 | D56: =SUM(D54)/(D55) -> 1.47515 | E56: =SUM(E54)/(E55) -> 1.96799 | F56: =SUM(F54)/(F55) -> 3.22091 | G56: =SUM(G54)/(G55) -> 4.98194 | H56: =SUM(H54)/(H55) -> 6.24767 | I56: =SUM(I54)/(I55) -> 7.49847 | J56: =SUM(J54)/(J55) -> 8.51708 | ... N56: =SUM(N54)/(N55) -> 13.2532 | O56: =IFERROR(AVERAGE(C56:N56),"") -> 6.7925267
B75: ■配当収入推移 | C75: 1月 | D75: 2月 | E75: 3月 | F75: 4月 | G75: 5月 | H75: 6月 | I75: 7月 | J75: 8月 | K75: 9月 | L75: 10月 | M75: 11月 | N75: 12月
B76: 2025年 | C76: 0 | D76: 0 | E76: 0 | F76: 0 | G76: 0 | H76: 0 | I76: 0 | J76: 0 | K76: 0 | L76: 0 | M76: 0 | N76: 0
B77: 2026年 | C77: 0 | D77: 0 | E77: 0 | F77: 0 | G77: 0 | H77: 0 | I77: 0 | J77: 0 | K77: 0 | L77: 0 | M77: 0 | N77: 0

Sheet 5か年PL
D1: 前月比 | F1: =F5-E5 -> 96503 | G1: =G5-F5 -> -50436 | H1: =H5-G5 -> 12000 | I1: =I5-H5 -> -22000 | J1: =J5-I5 -> 50020 | K1: =K5-J5 -> 3980 | L1: =L5-K5 -> -54000 | M1: =M5-L5 -> 50300 | ... BK1: =BK5-BJ5 -> -50000
E2: ※確定 | F2: ※確定 | G2: ※確定 | H2: ※確定 | I2: ※確定 | J2: ※確定 | K2: ※確定 | L2: ※確定 | M2: ※確定 | N2: ※確定 | O2: ※確定 | P2: ※確定 | Q2: ※確定 | R2: ※確定 | S2: ※確定 | T2: ※確定 | U2: ※確定 | V2: ※確定 | W2: ※確定 | X2: ※確定 | Y2: ※確定 | Z2: ※確定 | AA2: ※確定 | AB2: ※確定 | AC2: ※確定 | AD2: 未確定 | AE2: 未確定 | AF2: 未確定 | AG2: 未確定 | AH2: 未確定 | AI2: 未確定 | AJ2: 未確定 | AK2: 未確定 | AL2: 未確定 | AM2: 未確定 | AN2: 未確定 | AO2: 未確定 | AP2: 未確定 | AQ2: 未確定 | AR2: 未確定 | AS2: 未確定 | AT2: 未確定 | AU2: 未確定 | AV2: 未確定 | AW2: 未確定 | AX2: 未確定 | AY2: 未確定 | AZ2: 未確定 | BA2: 未確定 | BB2: 未確定 | BC2: 未確定 | BD2: 未確定 | BE2: 未確定 | BF2: 未確定 | BG2: 未確定 | BH2: 未確定 | BI2: 未確定 | BJ2: 未確定 | BK2: 未確定 | BL2: E～O | BN2: P～AA | BP2: AB～AM | BR2: AN～AY | BT2: AZ～BK
C3: 個人用PL | E3: FY-1（2024年5月～2025年3月） | P3: FY-2（2025年4月～2026年3月） | AB3: FY-3（2026年4月～2027年3月） | AN3: FY-4（2027年4月～2028年3月） | AZ3: FY-5（2028年4月～2029年3月） | BL3: FY-1 | BN3: FY-2 | BP3: FY-3 | BR3: FY-4 | BT3: FY-5
C4: 大項目 | D4: 小項目 | E4: 5月 | F4: 6月 | G4: 7月 | H4: 8月 | I4: 9月 | J4: 10月 | K4: 11月 | L4: 12月 | M4: 1月 | N4: 2月 | O4: 3月 | P4: 4月 | Q4: 5月 | R4: 6月 | S4: 7月 | T4: 8月 | U4: 9月 | V4: 10月 | W4: 11月 | X4: 12月 | Y4: 1月 | Z4: 2月 | AA4: 3月 | AB4: 4月 | AC4: 5月 | AD4: 6月 | AE4: 7月 | AF4: 8月 | AG4: 9月 | AH4: 10月 | AI4: 11月 | AJ4: 12月 | AK4: 1月 | AL4: 2月 | AM4: 3月 | AN4: 4月 | AO4: 5月 | AP4: 6月 | AQ4: 7月 | AR4: 8月 | AS4: 9月 | AT4: 10月 | AU4: 11月 | AV4: 12月 | AW4: 1月 | AX4: 2月 | AY4: 3月 | AZ4: 4月 | BA4: 5月 | BB4: 6月 | BC4: 7月 | BD4: 8月 | BE4: 9月 | BF4: 10月 | BG4: 11月 | BH4: 12月 | BI4: 1月 | BJ4: 2月 | BK4: 3月 | BL4: 通期 | BM4: (昨対比) | BN4: 通期 | BO4: (昨対比) | BP4: 通期 | BQ4: (昨対比) | BR4: 通期 | BS4: (昨対比) | BT4: 通期 | BU4: (昨対比)
C5: 収入 | D5: 合計 | E5: =SUM(E6:E10) -> 365933 | F5: =SUM(F6:F10) -> 462436 | G5: =SUM(G6:G10) -> 412000 | H5: =SUM(H6:H10) -> 424000 | I5: =SUM(I6:I10) -> 402000 | J5: =SUM(J6:J10) -> 452020 | K5: =SUM(K6:K10) -> 456000 | L5: =SUM(L6:L10) -> 402000 | ... BK5: =SUM(BK6:BK10) -> 650000 | BL5: =SUM(E5:O5) -> 4698729 | BM5: - | BN5: =SUM(P5:AA5) -> 7536362 | BO5: =BN5/BL5 -> 1.603915 | BP5: =SUM(AB5:AM5) -> 11000467 | BQ5: =BP5/BN5 -> 1.4596522 | BR5: =SUM(AN5:AY5) -> 9872000 | BS5: =BR5/BP5 -> 0.89741645 | BT5: =SUM(AZ5:BK5) -> 8172000 | BU5: =BT5/BR5 -> 0.82779579
D6: 総支給額(給与) | E6: ='FY-1(月次)収入予実'!F9 -> 353933 | F6: ='FY-1(月次)収入予実'!G9 -> 462436 | G6: ='FY-1(月次)収入予実'!H9 -> 400000 | H6: ='FY-1(月次)収入予実'!I9 -> 422000 | I6: ='FY-1(月次)収入予実'!J9 -> 400000 | J6: ='FY-1(月次)収入予実'!K9 -> 438020 | K6: ='FY-1(月次)収入予実'!L9 -> 454000 | L6: ='FY-1(月次)収入予実'!M9 -> 400000 | ... O6: ='FY-1(月次)収入予実'!P9 -> 400000 | P6: ='FY-2(月次)収入'!D10 -> 438020 | Q6: ='FY-2(月次)収入'!E10 -> 396656 | R6: ='FY-2(月次)収入'!F10 -> 0 | S6: ='FY-2(月次)収入'!G10 -> 544857 | T6: ='FY-2(月次)収入'!H10 -> 588222 | U6: ='FY-2(月次)収入'!I10 -> 687312 | V6: ='FY-2(月次)収入'!J10 -> 648517 | W6: ='FY-2(月次)収入'!K10 -> 668694 | ... AA6: ='FY-2(月次)収入'!O10 -> 563046 | AB6: ='FY-3(月次)収入'!D10 -> 687826 | AC6: ='FY-3(月次)収入'!E10 -> 562185 | AD6: ='FY-3(月次)収入'!F10 -> 562651 | AE6: ='FY-3(月次)収入'!G10 -> 664030 | AF6: ='FY-3(月次)収入'!H10 -> 559179 | AG6: ='FY-3(月次)収入'!I10 -> 671386 | AH6: ='FY-3(月次)収入'!J10 -> 566915 | AI6: ='FY-3(月次)収入'!K10 -> 674646 | ... AM6: ='FY-3(月次)収入'!O10 -> 561030 | AN6: 700000 | AO6: 700000 | AP6: 750000 | AQ6: 750000 | AR6: 750000 | AS6: 750000 | AT6: 750000 | AU6: 750000 | AV6: 750000 | AW6: 750000 | AX6: 750000 | AY6: 750000 | AZ6: 600000 | BA6: 600000 | BB6: 600000 | BC6: 600000 | BD6: 600000 | BE6: 600000 | BF6: 600000 | BG6: 600000 | BH6: 600000 | BI6: 600000 | BJ6: 600000 | BK6: 600000 | BL6: =SUM(E6:O6) -> 4593389 | BM6: - | BN6: =SUM(P6:AA6) -> 6417998 | BO6: =BN6/BL6 -> 1.397225 | BP6: =SUM(AB6:AM6) -> 7408817 | BQ6: =BP6/BN6 -> 1.1543813 | BR6: =SUM(AN6:AY6) -> 8900000 | BS6: =BR6/BP6 -> 1.2012714 | BT6: =SUM(AZ6:BK6) -> 7200000 | BU6: =BT6/BR6 -> 0.80898876
D7: 経費精算 | E7: - | F7: - | G7: - | H7: - | I7: - | J7: - | K7: - | L7: - | M7: - | N7: - | O7: - | P7: - | Q7: - | R7: ='FY-2(月次)収入'!F5 -> 28513 | S7: ='FY-2(月次)収入'!G5 -> 318 | T7: ='FY-2(月次)収入'!H5 -> 17116 | U7: ='FY-2(月次)収入'!I5 -> 0 | V7: ='FY-2(月次)収入'!J5 -> 2392 | W7: ='FY-2(月次)収入'!K5 -> 7764 | X7: ='FY-2(月次)収入'!L5 -> 128190 | Y7: ='FY-2(月次)収入'!M5 -> 24803 | ... AA7: ='FY-2(月次)収入'!O5 -> 4374 | AB7: ='FY-3(月次)収入'!D5 -> 3318 | AC7: ='FY-3(月次)収入'!E5 -> 3977 | AD7: ='FY-3(月次)収入'!F5 -> 3668 | AE7: ='FY-3(月次)収入'!G5 -> 663 | AF7: ='FY-3(月次)収入'!H5 -> 500 | AG7: ='FY-3(月次)収入'!I5 -> 500 | AH7: ='FY-3(月次)収入'!J5 -> 500 | AI7: ='FY-3(月次)収入'!K5 -> 500 | ... AM7: ='FY-3(月次)収入'!O5 -> 500 | AN7: 0 | AO7: 0 | AP7: 0 | AQ7: 0 | AR7: 0 | AS7: 10000 | AT7: 0 | AU7: 0 | AV7: 0 | AW7: 0 | AX7: 0 | AY7: 0 | AZ7: 0 | BA7: 0 | BB7: 0 | BC7: 0 | BD7: 0 | BE7: 10000 | BF7: 0 | BG7: 0 | BH7: 0 | BI7: 0 | BJ7: 0 | BK7: 0 | BL7: =SUM(E7:O7) -> 0 | BM7: - | BN7: =SUM(P7:AA7) -> 218449 | BO7: =BN7/BL7 -> #DIV/0! | BP7: =SUM(AB7:AM7) -> 15626 | BQ7: =BP7/BN7 -> 0.07153157 | BR7: =SUM(AN7:AY7) -> 10000 | BS7: =BR7/BP7 -> 0.63995904 | BT7: =SUM(AZ7:BK7) -> 10000 | BU7: =BT7/BR7 -> 1
D8: 家族収入 | E8: ='FY-1(月次)収入予実'!F7 -> 10000 | F8: ='FY-1(月次)収入予実'!G7 -> 0 | G8: ='FY-1(月次)収入予実'!H7 -> 10000 | H8: ='FY-1(月次)収入予実'!I7 -> 0 | I8: ='FY-1(月次)収入予実'!J7 -> 0 | J8: ='FY-1(月次)収入予実'!K7 -> 10000 | K8: ='FY-1(月次)収入予実'!L7 -> 0 | L8: ='FY-1(月次)収入予実'!M7 -> 0 | ... O8: ='FY-1(月次)収入予実'!P7 -> 0 | P8: ='FY-2(月次)収入'!D6 -> 0 | Q8: ='FY-2(月次)収入'!E6 -> 20000 | R8: ='FY-2(月次)収入'!F6 -> 10000 | S8: ='FY-2(月次)収入'!G6 -> 0 | T8: ='FY-2(月次)収入'!H6 -> 18000 | U8: ='FY-2(月次)収入'!I6 -> 10000 | V8: ='FY-2(月次)収入'!J6 -> 0 | W8: ='FY-2(月次)収入'!K6 -> 0 | ... AA8: ='FY-2(月次)収入'!O6 -> 0 | AB8: ='FY-3(月次)収入'!D6 -> 0 | AC8: ='FY-3(月次)収入'!E6 -> 10000 | AD8: ='FY-3(月次)収入'!F6 -> 0 | AE8: ='FY-3(月次)収入'!G6 -> 0 | AF8: ='FY-3(月次)収入'!H6 -> 0 | AG8: ='FY-3(月次)収入'!I6 -> 0 | AH8: ='FY-3(月次)収入'!J6 -> 0 | AI8: ='FY-3(月次)収入'!K6 -> 0 | ... AM8: ='FY-3(月次)収入'!O6 -> 0 | AN8: 0 | AO8: 0 | AP8: 0 | AQ8: 0 | AR8: 0 | AS8: 0 | AT8: 0 | AU8: 0 | AV8: 50000 | AW8: 0 | AX8: 0 | AY8: 0 | AZ8: 0 | BA8: 0 | BB8: 0 | BC8: 0 | BD8: 0 | BE8: 0 | BF8: 0 | BG8: 0 | BH8: 50000 | BI8: 0 | BJ8: 0 | BL8: =SUM(E8:O8) -> 80000 | BM8: - | BN8: =SUM(P8:AA8) -> 97500 | BO8: =BN8/BL8 -> 1.21875 | BP8: =SUM(AB8:AM8) -> 49500 | BQ8: =BP8/BN8 -> 0.50769231 | BR8: =SUM(AN8:AY8) -> 50000 | BS8: =BR8/BP8 -> 1.010101 | BT8: =SUM(AZ8:BK8) -> 50000 | BU8: =BT8/BR8 -> 1
D9: その他収入 | E9: ='FY-1(月次)収入予実'!F8 -> 0 | F9: ='FY-1(月次)収入予実'!G8 -> 0 | G9: ='FY-1(月次)収入予実'!H8 -> 0 | H9: ='FY-1(月次)収入予実'!I8 -> 0 | I9: ='FY-1(月次)収入予実'!J8 -> 0 | J9: ='FY-1(月次)収入予実'!K8 -> 0 | K9: ='FY-1(月次)収入予実'!L8 -> 0 | L9: ='FY-1(月次)収入予実'!M8 -> 0 | ... O9: ='FY-1(月次)収入予実'!P8 -> 0 | P9: ='FY-2(月次)収入'!D7 -> 11000 | Q9: ='FY-2(月次)収入'!E7 -> 5000 | R9: ='FY-2(月次)収入'!F7 -> 0 | S9: ='FY-2(月次)収入'!G7 -> 42000 | T9: ='FY-2(月次)収入'!H7 -> 981 | U9: ='FY-2(月次)収入'!I7 -> 21382 | V9: ='FY-2(月次)収入'!J7 -> 1323 | W9: ='FY-2(月次)収入'!K7 -> 42292 | ... AA9: ='FY-2(月次)収入'!O7 -> 329075 | AB9: ='FY-3(月次)収入'!D7 -> 30000 | AC9: ='FY-3(月次)収入'!E7 -> 68524 | AD9: ='FY-3(月次)収入'!F7 -> 72440 | AE9: ='FY-3(月次)収入'!G7 -> 28000 | AF9: ='FY-3(月次)収入'!H7 -> 328000 | AG9: ='FY-3(月次)収入'!I7 -> 328000 | AH9: ='FY-3(月次)収入'!J7 -> 328000 | AI9: ='FY-3(月次)収入'!K7 -> 628000 | ... AM9: ='FY-3(月次)収入'!O7 -> 328000 | AN9: 100000 | AO9: 50000 | AP9: 100000 | AQ9: 50000 | AR9: 100000 | AS9: 50000 | AT9: 100000 | AU9: 50000 | AV9: 100000 | AW9: 50000 | AX9: 100000 | AY9: 50000 | AZ9: 100000 | BA9: 50000 | BB9: 100000 | BC9: 50000 | BD9: 100000 | BE9: 50000 | BF9: 100000 | BG9: 50000 | BH9: 100000 | BI9: 50000 | BJ9: 100000 | BK9: 50000 | BL9: =SUM(E9:O9) -> 7540 | BM9: - | BN9: =SUM(P9:AA9) -> 704810 | BO9: =BN9/BL9 -> 93.476127 | BP9: =SUM(AB9:AM9) -> 3422964 | BQ9: =BP9/BN9 -> 4.8565769 | BR9: =SUM(AN9:AY9) -> 900000 | BS9: =BR9/BP9 -> 0.26293002 | BT9: =SUM(AZ9:BK9) -> 900000 | BU9: =BT9/BR9 -> 1
D10: ポイント収入 | E10: ='FY-1(月次)収入予実'!F6 -> 2000 | F10: ='FY-1(月次)収入予実'!G6 -> 0 | G10: ='FY-1(月次)収入予実'!H6 -> 2000 | H10: ='FY-1(月次)収入予実'!I6 -> 2000 | I10: ='FY-1(月次)収入予実'!J6 -> 2000 | J10: ='FY-1(月次)収入予実'!K6 -> 4000 | K10: ='FY-1(月次)収入予実'!L6 -> 2000 | L10: ='FY-1(月次)収入予実'!M6 -> 2000 | ... O10: ='FY-1(月次)収入予実'!P6 -> 0 | P10: ='FY-2(月次)収入'!D8 -> 3985 | Q10: ='FY-2(月次)収入'!E8 -> 3280 | R10: ='FY-2(月次)収入'!F8 -> 30383 | S10: ='FY-2(月次)収入'!G8 -> 3158 | T10: ='FY-2(月次)収入'!H8 -> 2090 | U10: ='FY-2(月次)収入'!I8 -> 7250 | V10: ='FY-2(月次)収入'!J8 -> 6752 | W10: ='FY-2(月次)収入'!K8 -> 3949 | ... AA10: ='FY-2(月次)収入'!O8 -> 10429 | AB10: ='FY-3(月次)収入'!D8 -> 0 | AC10: ='FY-3(月次)収入'!E8 -> 4297 | AD10: ='FY-3(月次)収入'!F8 -> 46735 | AE10: ='FY-3(月次)収入'!G8 -> 3158 | AF10: ='FY-3(月次)収入'!H8 -> 2090 | AG10: ='FY-3(月次)収入'!I8 -> 7250 | AH10: ='FY-3(月次)収入'!J8 -> 6752 | AI10: ='FY-3(月次)収入'!K8 -> 3949 | ... AM10: ='FY-3(月次)収入'!O8 -> 3000 | AN10: 3000 | AO10: 0 | AP10: 0 | AQ10: 3000 | AR10: 0 | AS10: 0 | AT10: 3000 | AU10: 0 | AV10: 0 | AW10: 3000 | AX10: 0 | AY10: 0 | AZ10: 3000 | BA10: 0 | BB10: 0 | BC10: 3000 | BD10: 0 | BE10: 0 | BF10: 3000 | BG10: 0 | BH10: 0 | BI10: 3000 | BJ10: 0 | BK10: 0 | BL10: =SUM(E10:O10) -> 17800 | BM10: - | BN10: =SUM(P10:AA10) -> 97605 | BO10: =BN10/BL10 -> 5.483427 | BP10: =SUM(AB10:AM10) -> 103560 | BQ10: =BP10/BN10 -> 1.0610112 | BR10: =SUM(AN10:AY10) -> 12000 | BS10: =BR10/BP10 -> 0.11587486 | BT10: =SUM(AZ10:BK10) -> 12000 | BU10: =BT10/BR10 -> 1
D11: （合計額に対するポイントの割合） | E11: =E10/E5 -> 0.0054654814 | F11: =F10/F5 -> 0 | G11: =G10/G5 -> 0.0048543689 | H11: =H10/H5 -> 0.0047169811 | I11: =I10/I5 -> 0.0049751244 | J11: =J10/J5 -> 0.008849166 | K11: =K10/K5 -> 0.0043859649 | L11: =L10/L5 -> 0.0049751244 | ... BL11: =BL10/BL5 -> 0.0037882585 | BN11: =BN10/BN5 -> 0.012951209 | BP11: =BP10/BP5 -> 0.0094141458 | BR11: =BR10/BR5 -> 0.0012155592 | BT11: =BT10/BT5 -> 0.0014684288
C12: 控除額内訳 | D12: 合計 | E12: =SUM(E13:E21) -> 61448 | F12: =SUM(F13:F21) -> 53679 | G12: =SUM(G13:G21) -> 72704 | H12: =SUM(H13:H21) -> 85236 | I12: =SUM(I13:I21) -> 83804 | J12: =SUM(J13:J21) -> 90612 | K12: =SUM(K13:K21) -> 95118 | L12: =SUM(L13:L21) -> 69214 | ... BK12: =SUM(BK13:BK21) -> 141470 | BL12: =SUM(E12:P12) -> 978734 | BM12: - | BN12: =SUM(P12:AA12) -> 1343774.3 | BO12: =BN12/BL12 -> 1.3729719 | BP12: =SUM(AB12:AM12) -> 1708908 | BQ12: =BP12/BN12 -> 1.2717225 | BR12: =SUM(AN12:AY12) -> 1588840 | BS12: =BR12/BP12 -> 0.92973993 | BT12: =SUM(AZ12:BK12) -> 1708840 | BU12: =BT12/BR12 -> 1.0755268
D13: 住民税 | E13: ='FY-1(月次)収入予実'!F11 -> 0 | F13: ='FY-1(月次)収入予実'!G11 -> 0 | G13: ='FY-1(月次)収入予実'!H11 -> 19400 | H13: ='FY-1(月次)収入予実'!I11 -> 18400 | I13: ='FY-1(月次)収入予実'!J11 -> 18400 | J13: ='FY-1(月次)収入予実'!K11 -> 18400 | K13: ='FY-1(月次)収入予実'!L11 -> 18400 | L13: ='FY-1(月次)収入予実'!M11 -> 18400 | ... O13: ='FY-1(月次)収入予実'!P11 -> 18400 | P13: ='FY-2(月次)収入'!D13 -> 18400 | Q13: ='FY-2(月次)収入'!E13 -> 18400 | R13: ='FY-2(月次)収入'!F13 -> 0 | S13: ='FY-2(月次)収入'!G13 -> 21100 | T13: ='FY-2(月次)収入'!H13 -> 20200 | U13: ='FY-2(月次)収入'!I13 -> 20200 | V13: ='FY-2(月次)収入'!J13 -> 20200 | W13: ='FY-2(月次)収入'!K13 -> 20200 | ... AA13: ='FY-2(月次)収入'!O13 -> 20200 | AB13: ='FY-3(月次)収入'!D13 -> 20200 | AC13: ='FY-3(月次)収入'!E13 -> 20200 | AD13: ='FY-3(月次)収入'!F13 -> 25100 | AE13: ='FY-3(月次)収入'!G13 -> 25200 | AF13: ='FY-3(月次)収入'!H13 -> 25200 | AG13: ='FY-3(月次)収入'!I13 -> 25200 | AH13: ='FY-3(月次)収入'!J13 -> 25200 | AI13: ='FY-3(月次)収入'!K13 -> 25200 | ... AM13: ='FY-3(月次)収入'!O13 -> 25200 | AN13: 30000 | AO13: 30000 | AP13: 30000 | AQ13: 30000 | AR13: 30000 | AS13: 30000 | AT13: 30000 | AU13: 30000 | AV13: 30000 | AW13: 30000 | AX13: 30000 | AY13: 30000 | AZ13: 40000 | BA13: 40000 | BB13: 40000 | BC13: 40000 | BD13: 40000 | BE13: 40000 | BF13: 40000 | BG13: 40000 | BH13: 40000 | BI13: 40000 | BJ13: 40000 | BK13: 40000 | BL13: =SUM(E13:O13) -> 166600 | BM13: - | BN13: =SUM(P13:AA13) -> 219500 | BO13: =BN13/BL13 -> 1.317527 | BP13: =SUM(AB13:AM13) -> 292300 | BQ13: =BP13/BN13 -> 1.3316629 | BR13: =SUM(AN13:AY13) -> 360000 | BS13: =BR13/BP13 -> 1.2316114 | BT13: =SUM(AZ13:BK13) -> 480000 | BU13: =BT13/BR13 -> 1.3333333
D14: 所得税 | E14: ='FY-1(月次)収入予実'!F12 -> 8420 | F14: ='FY-1(月次)収入予実'!G12 -> 17240 | G14: ='FY-1(月次)収入予実'!H12 -> 12100 | H14: ='FY-1(月次)収入予実'!I12 -> 14060 | I14: ='FY-1(月次)収入予実'!J12 -> 12100 | J14: ='FY-1(月次)収入予実'!K12 -> 11610 | K14: ='FY-1(月次)収入予実'!L12 -> 16020 | L14: ='FY-1(月次)収入予実'!M12 -> 11610 | ... O14: ='FY-1(月次)収入予実'!P12 -> 11610 | P14: ='FY-2(月次)収入'!D14 -> 11610 | Q14: ='FY-2(月次)収入'!E14 -> 8670 | R14: ='FY-2(月次)収入'!F14 -> 0 | S14: ='FY-2(月次)収入'!G14 -> 21070 | T14: ='FY-2(月次)収入'!H14 -> 28420 | U14: ='FY-2(月次)収入'!I14 -> 45440 | V14: ='FY-2(月次)収入'!J14 -> 38280 | W14: ='FY-2(月次)収入'!K14 -> 42140 | ... AA14: ='FY-2(月次)収入'!O14 -> 20840 | AB14: ='FY-3(月次)収入'!D14 -> 42640 | AC14: ='FY-3(月次)収入'!E14 -> 21330 | AD14: ='FY-3(月次)収入'!F14 -> 21330 | AE14: ='FY-3(月次)収入'!G14 -> 42000 | AF14: ='FY-3(月次)収入'!H14 -> 30000 | AG14: ='FY-3(月次)収入'!I14 -> 30000 | AH14: ='FY-3(月次)収入'!J14 -> 30000 | AI14: ='FY-3(月次)収入'!K14 -> 30000 | ... AM14: ='FY-3(月次)収入'!O14 -> 30000 | AN14: 25000 | AO14: 25000 | AP14: 25000 | AQ14: 25000 | AR14: 25000 | AS14: 25000 | AT14: 25000 | AU14: 25000 | AV14: 25000 | AW14: 25000 | AX14: 25000 | AY14: 25000 | AZ14: 25000 | BA14: 25000 | BB14: 25000 | BC14: 25000 | BD14: 25000 | BE14: 25000 | BF14: 25000 | BG14: 25000 | BH14: 25000 | BI14: 25000 | BJ14: 25000 | BK14: 25000 | BL14: =SUM(E14:O14) -> 143130 | BM14: - | BN14: =SUM(P14:AA14) -> 316930 | BO14: =BN14/BL14 -> 2.2142807 | BP14: =SUM(AB14:AM14) -> 367300 | BQ14: =BP14/BN14 -> 1.158931 | BR14: =SUM(AN14:AY14) -> 300000 | BS14: =BR14/BP14 -> 0.81677103 | BT14: =SUM(AZ14:BK14) -> 300000 | BU14: =BT14/BR14 -> 1
D15: 健康保険料 | E15: ='FY-1(月次)収入予実'!F13 -> 17964 | F15: ='FY-1(月次)収入予実'!G13 -> 17964 | G15: ='FY-1(月次)収入予実'!H13 -> 17964 | H15: ='FY-1(月次)収入予実'!I13 -> 17964 | I15: ='FY-1(月次)収入予実'!J13 -> 17964 | J15: ='FY-1(月次)収入予実'!K13 -> 20459 | K15: ='FY-1(月次)収入予実'!L13 -> 20459 | L15: ='FY-1(月次)収入予実'!M13 -> 20459 | ... O15: ='FY-1(月次)収入予実'!P13 -> 20459 | P15: ='FY-2(月次)収入'!D15 -> 20315 | Q15: ='FY-2(月次)収入'!E15 -> 40630 | R15: ='FY-2(月次)収入'!F15 -> 0 | S15: ='FY-2(月次)収入'!G15 -> 23585 | T15: ='FY-2(月次)収入'!H15 -> 23585 | U15: ='FY-2(月次)収入'!I15 -> 23585 | V15: ='FY-2(月次)収入'!J15 -> 23585 | W15: ='FY-2(月次)収入'!K15 -> 23585 | ... AA15: ='FY-2(月次)収入'!O15 -> 30260 | AB15: ='FY-3(月次)収入'!D15 -> 29140 | AC15: ='FY-3(月次)収入'!E15 -> 29140 | AD15: ='FY-3(月次)収入'!F15 -> 29140 | AE15: ='FY-3(月次)収入'!G15 -> 29140 | AF15: ='FY-3(月次)収入'!H15 -> 29140 | AG15: ='FY-3(月次)収入'!I15 -> 29140 | AH15: ='FY-3(月次)収入'!J15 -> 29140 | AI15: ='FY-3(月次)収入'!K15 -> 29140 | ... AM15: ='FY-3(月次)収入'!O15 -> 29140 | AN15: 20315 | AO15: 40630 | AP15: 23585 | AQ15: 23585 | AR15: 23585 | AS15: 24775 | AT15: 24775 | AU15: 24775 | AV15: 24775 | AW15: 24775 | AX15: 24775 | AY15: 24775 | AZ15: 20315 | BA15: 40630 | BB15: 23585 | BC15: 23585 | BD15: 23585 | BE15: 24775 | BF15: 24775 | BG15: 24775 | BH15: 24775 | BI15: 24775 | BJ15: 24775 | BK15: 24775 | BL15: =SUM(E15:O15) -> 212574 | BM15: - | BN15: =SUM(P15:AA15) -> 293235 | BO15: =BN15/BL15 -> 1.379449 | BP15: =SUM(AB15:AM15) -> 349680 | BQ15: =BP15/BN15 -> 1.1924907 | BR15: =SUM(AN15:AY15) -> 305125 | BS15: =BR15/BP15 -> 0.8725835 | BT15: =SUM(AZ15:BK15) -> 305125 | BU15: =BT15/BR15 -> 1
D16: 雇用保険料 | E16: ='FY-1(月次)収入予実'!F14 -> 2124 | F16: ='FY-1(月次)収入予実'!G14 -> 2775 | G16: ='FY-1(月次)収入予実'!H14 -> 2400 | H16: ='FY-1(月次)収入予実'!I14 -> 2532 | I16: ='FY-1(月次)収入予実'!J14 -> 2400 | J16: ='FY-1(月次)収入予実'!K14 -> 2628 | K16: ='FY-1(月次)収入予実'!L14 -> 2724 | L16: ='FY-1(月次)収入予実'!M14 -> 2400 | ... O16: ='FY-1(月次)収入予実'!P14 -> 2400 | P16: ='FY-2(月次)収入'!D16 -> 2409 | Q16: ='FY-2(月次)収入'!E16 -> 2182 | R16: ='FY-2(月次)収入'!F16 -> 0 | S16: ='FY-2(月次)収入'!G16 -> 2997 | T16: ='FY-2(月次)収入'!H16 -> 3235 | U16: ='FY-2(月次)収入'!I16 -> 3780 | V16: ='FY-2(月次)収入'!J16 -> 3567 | W16: ='FY-2(月次)収入'!K16 -> 3677.817 | ... AA16: ='FY-2(月次)収入'!O16 -> 3096.753 | AB16: ='FY-3(月次)収入'!D16 -> 3783.043 | AC16: ='FY-3(月次)収入'!E16 -> 2810.925 | AD16: ='FY-3(月次)収入'!F16 -> 2813.255 | AE16: ='FY-3(月次)収入'!G16 -> 3320.15 | AF16: ='FY-3(月次)収入'!H16 -> 2795.895 | AG16: ='FY-3(月次)収入'!I16 -> 3356.93 | AH16: ='FY-3(月次)収入'!J16 -> 2834.575 | AI16: ='FY-3(月次)収入'!K16 -> 3373.23 | ... AM16: ='FY-3(月次)収入'!O16 -> 2805.15 | AN16: 2409 | AO16: 2182 | AP16: 2997 | AQ16: 2997 | AR16: 3235 | AS16: 3200 | AT16: 3200 | AU16: 3200 | AV16: 3200 | AW16: 3200 | AX16: 3200 | AY16: 3200 | AZ16: 2409 | BA16: 2182 | BB16: 2997 | BC16: 2997 | BD16: 3235 | BE16: 3200 | BF16: 3200 | BG16: 3200 | BH16: 3200 | BI16: 3200 | BJ16: 3200 | BK16: 3200 | BL16: =SUM(E16:O16) -> 27561 | BM16: - | BN16: =SUM(P16:AA16) -> 35299.277 | BO16: =BN16/BL16 -> 1.2807691 | BP16: =SUM(AB16:AM16) -> 37387.998 | BQ16: =BP16/BN16 -> 1.0591718 | BR16: =SUM(AN16:AY16) -> 36220 | BS16: =BR16/BP16 -> 0.96876008 | BT16: =SUM(AZ16:BK16) -> 36220 | BU16: =BT16/BR16 -> 1
D17: 厚生年金保険料 | E17: ='FY-1(月次)収入予実'!F15 -> 32940 | F17: ='FY-1(月次)収入予実'!G15 -> 32940 | G17: ='FY-1(月次)収入予実'!H15 -> 32940 | H17: ='FY-1(月次)収入予実'!I15 -> 32940 | I17: ='FY-1(月次)収入予実'!J15 -> 32940 | J17: ='FY-1(月次)収入予実'!K15 -> 37515 | K17: ='FY-1(月次)収入予実'!L15 -> 37515 | L17: ='FY-1(月次)収入予実'!M15 -> 37515 | ... O17: ='FY-1(月次)収入予実'!P15 -> 37515 | P17: ='FY-2(月次)収入'!D17 -> 37515 | Q17: ='FY-2(月次)収入'!E17 -> 75030 | R17: ='FY-2(月次)収入'!F17 -> 0 | S17: ='FY-2(月次)収入'!G17 -> 48495 | T17: ='FY-2(月次)収入'!H17 -> 48495 | U17: ='FY-2(月次)収入'!I17 -> 48495 | V17: ='FY-2(月次)収入'!J17 -> 48495 | W17: ='FY-2(月次)収入'!K17 -> 48495 | ... AA17: ='FY-2(月次)収入'!O17 -> 59475 | AB17: ='FY-3(月次)収入'!D17 -> 56730 | AC17: ='FY-3(月次)収入'!E17 -> 56730 | AD17: ='FY-3(月次)収入'!F17 -> 56730 | AE17: ='FY-3(月次)収入'!G17 -> 56730 | AF17: ='FY-3(月次)収入'!H17 -> 56730 | AG17: ='FY-3(月次)収入'!I17 -> 56730 | AH17: ='FY-3(月次)収入'!J17 -> 56730 | AI17: ='FY-3(月次)収入'!K17 -> 56730 | ... AM17: ='FY-3(月次)収入'!O17 -> 56730 | AN17: 37515 | AO17: 75030 | AP17: 48495 | AQ17: 48495 | AR17: 48495 | AS17: 48495 | AT17: 48495 | AU17: 48495 | AV17: 48495 | AW17: 48495 | AX17: 48495 | AY17: 48495 | AZ17: 37515 | BA17: 75030 | BB17: 48495 | BC17: 48495 | BD17: 48495 | BE17: 48495 | BF17: 48495 | BG17: 48495 | BH17: 48495 | BI17: 48495 | BJ17: 48495 | BK17: 48495 | BL17: =SUM(E17:O17) -> 389790 | BM17: - | BN17: =SUM(P17:AA17) -> 581940 | BO17: =BN17/BL17 -> 1.4929577 | BP17: =SUM(AB17:AM17) -> 680760 | BQ17: =BP17/BN17 -> 1.1698113 | BR17: =SUM(AN17:AY17) -> 597495 | BS17: =BR17/BP17 -> 0.87768817 | BT17: =SUM(AZ17:BK17) -> 597495 | BU17: =BT17/BR17 -> 1
D18: 定額減税・確定申告還付 | E18: ='FY-1(月次)収入予実'!F16 -> 0 | F18: ='FY-1(月次)収入予実'!G16 -> -17240 | G18: ='FY-1(月次)収入予実'!H16 -> -12100 | H18: ='FY-1(月次)収入予実'!I16 -> -660 | I18: ='FY-1(月次)収入予実'!J16 -> 0 | J18: ='FY-1(月次)収入予実'!K16 -> 0 | K18: ='FY-1(月次)収入予実'!L16 -> 0 | L18: ='FY-1(月次)収入予実'!M16 -> 0 | ... O18: ='FY-1(月次)収入予実'!P16 -> 0 | P18: ='FY-2(月次)収入'!D18 -> 0 | Q18: ='FY-2(月次)収入'!E18 -> 0 | R18: ='FY-2(月次)収入'!F18 -> 0 | S18: ='FY-2(月次)収入'!G18 -> 0 | T18: ='FY-2(月次)収入'!H18 -> 0 | U18: ='FY-2(月次)収入'!I18 -> 0 | V18: ='FY-2(月次)収入'!J18 -> 0 | W18: ='FY-2(月次)収入'!K18 -> 0 | ... AA18: ='FY-2(月次)収入'!O18 -> 0 | AB18: ='FY-3(月次)収入'!D18 -> -6363 | AC18: ='FY-3(月次)収入'!E18 -> 0 | AD18: ='FY-3(月次)収入'!F18 -> 0 | AE18: ='FY-3(月次)収入'!G18 -> 0 | AF18: ='FY-3(月次)収入'!H18 -> 0 | AG18: ='FY-3(月次)収入'!I18 -> 0 | AH18: ='FY-3(月次)収入'!J18 -> 0 | AI18: ='FY-3(月次)収入'!K18 -> 0 | ... AM18: ='FY-3(月次)収入'!O18 -> 0 | AN18: 0 | AO18: 0 | AP18: 0 | AQ18: 0 | AR18: 0 | AS18: 0 | AT18: 0 | AU18: 0 | AV18: 0 | AW18: 0 | AX18: 0 | AY18: 0 | AZ18: 0 | BA18: 0 | BB18: 0 | BC18: 0 | BD18: 0 | BE18: 0 | BF18: 0 | BG18: 0 | BH18: 0 | BI18: 0 | BJ18: 0 | BK18: 0 | BL18: =SUM(E18:O18) -> -30000 | BM18: - | BN18: =SUM(P18:AA18) -> 0 | BO18: =BN18/BL18 -> 0 | BP18: =SUM(AB18:AM18) -> -6363 | BQ18: =BP18/BN18 -> #DIV/0! | BR18: =SUM(AN18:AY18) -> 0 | BS18: =BR18/BP18 -> 0 | BT18: =SUM(AZ18:BK18) -> 0 | BU18: =BT18/BR18 -> #DIV/0!
D19: 年末調整精算額 | E19: ='FY-1(月次)収入予実'!F17 -> 0 | F19: ='FY-1(月次)収入予実'!G17 -> 0 | G19: ='FY-1(月次)収入予実'!H17 -> 0 | H19: ='FY-1(月次)収入予実'!I17 -> 0 | I19: ='FY-1(月次)収入予実'!J17 -> 0 | J19: ='FY-1(月次)収入予実'!K17 -> 0 | K19: ='FY-1(月次)収入予実'!L17 -> 0 | L19: ='FY-1(月次)収入予実'!M17 -> -21170 | ... O19: ='FY-1(月次)収入予実'!P17 -> 0 | P19: ='FY-2(月次)収入'!D19 -> 0 | Q19: ='FY-2(月次)収入'!E19 -> 0 | R19: ='FY-2(月次)収入'!F19 -> 0 | S19: ='FY-2(月次)収入'!G19 -> 0 | T19: ='FY-2(月次)収入'!H19 -> 0 | U19: ='FY-2(月次)収入'!I19 -> 0 | V19: ='FY-2(月次)収入'!J19 -> 0 | W19: ='FY-2(月次)収入'!K19 -> 0 | ... AA19: ='FY-2(月次)収入'!O19 -> 0 | AB19: ='FY-3(月次)収入'!D19 -> 0 | AC19: ='FY-3(月次)収入'!E19 -> 0 | AD19: ='FY-3(月次)収入'!F19 -> 0 | AE19: ='FY-3(月次)収入'!G19 -> 0 | AF19: ='FY-3(月次)収入'!H19 -> 0 | AG19: ='FY-3(月次)収入'!I19 -> 0 | AH19: ='FY-3(月次)収入'!J19 -> 0 | AI19: ='FY-3(月次)収入'!K19 -> 0 | ... AM19: ='FY-3(月次)収入'!O19 -> 0 | AN19: 0 | AO19: 0 | AP19: 0 | AQ19: 0 | AR19: 0 | AS19: 0 | AT19: 0 | AU19: 0 | AV19: -10000 | AW19: 0 | AX19: 0 | AY19: 0 | AZ19: 0 | BA19: 0 | BB19: 0 | BC19: 0 | BD19: 0 | BE19: 0 | BF19: 0 | BG19: 0 | BH19: -10000 | BI19: 0 | BJ19: 0 | BK19: 0 | BL19: =SUM(E19:O19) -> -21170 | BM19: - | BN19: =SUM(P19:AA19) -> -103130 | BO19: =BN19/BL19 -> 4.8715163 | BP19: =SUM(AB19:AM19) -> -20000 | BQ19: =BP19/BN19 -> 0.19392999 | BR19: =SUM(AN19:AY19) -> -10000 | BS19: =BR19/BP19 -> 0.5 | BT19: =SUM(AZ19:BK19) -> -10000 | BU19: =BT19/BR19 -> 1
D20: 子ども・子育て支援金 | E20: 0 | F20: 0 | G20: 0 | H20: 0 | I20: 0 | J20: 0 | K20: 0 | L20: 0 | M20: 0 | N20: 0 | O20: 0 | P20: 0 | Q20: 0 | R20: 0 | S20: 0 | T20: 0 | U20: 0 | V20: 0 | W20: 0 | X20: 0 | Y20: 0 | Z20: 0 | AA20: 0 | AB20: ='FY-3(月次)収入'!D20 -> 0 | AC20: ='FY-3(月次)収入'!E20 -> 713 | AD20: ='FY-3(月次)収入'!F20 -> 713 | AE20: ='FY-3(月次)収入'!G20 -> 713 | AF20: ='FY-3(月次)収入'!H20 -> 713 | AG20: ='FY-3(月次)収入'!I20 -> 713 | AH20: ='FY-3(月次)収入'!J20 -> 713 | AI20: ='FY-3(月次)収入'!K20 -> 713 | ... AM20: ='FY-3(月次)収入'!O20 -> 713 | AN20: 0 | AO20: 0 | AP20: 0 | AQ20: 0 | AR20: 0 | AS20: 0 | AT20: 0 | AU20: 0 | AV20: 0 | AW20: 0 | AX20: 0 | AY20: 0 | AZ20: 0 | BA20: 0 | BB20: 0 | BC20: 0 | BD20: 0 | BE20: 0 | BF20: 0 | BG20: 0 | BH20: 0 | BI20: 0 | BJ20: 0 | BK20: 0 | BL20: =SUM(E20:O20) -> 0 | BM20: - | BN20: =SUM(P20:AA20) -> 0 | BO20: =BN20/BL20 -> #DIV/0! | BP20: =SUM(AB20:AM20) -> 7843 | BQ20: =BP20/BN20 -> #DIV/0! | BR20: =SUM(AN20:AY20) -> 0 | BS20: =BR20/BP20 -> 0 | BT20: =SUM(AZ20:BK20) -> 0 | BU20: =BT20/BR20 -> #DIV/0!
D21: ふるさと納税返金額 | E21: ='FY-1(月次)収入予実'!F18 -> 0 | F21: ='FY-1(月次)収入予実'!G18 -> 0 | G21: ='FY-1(月次)収入予実'!H18 -> 0 | H21: ='FY-1(月次)収入予実'!I18 -> 0 | I21: ='FY-1(月次)収入予実'!J18 -> 0 | J21: ='FY-1(月次)収入予実'!K18 -> 0 | K21: ='FY-1(月次)収入予実'!L18 -> 0 | L21: ='FY-1(月次)収入予実'!M18 -> 0 | ... O21: ='FY-1(月次)収入予実'!P18 -> 0 | P21: ='FY-2(月次)収入'!D20 -> 0 | Q21: ='FY-2(月次)収入'!E20 -> 0 | R21: ='FY-2(月次)収入'!F20 -> 0 | S21: ='FY-2(月次)収入'!G20 -> 0 | T21: ='FY-2(月次)収入'!H20 -> 0 | U21: ='FY-2(月次)収入'!I20 -> 0 | V21: ='FY-2(月次)収入'!J20 -> 0 | W21: ='FY-2(月次)収入'!K20 -> 0 | ... AA21: ='FY-2(月次)収入'!O20 -> 0 | AB21: ='FY-3(月次)収入'!D21 -> 0 | AC21: ='FY-3(月次)収入'!E21 -> 0 | AD21: ='FY-3(月次)収入'!F21 -> 0 | AE21: ='FY-3(月次)収入'!G21 -> 0 | AF21: ='FY-3(月次)収入'!H21 -> 0 | AG21: ='FY-3(月次)収入'!I21 -> 0 | AH21: ='FY-3(月次)収入'!J21 -> 0 | AI21: ='FY-3(月次)収入'!K21 -> 0 | ... AM21: ='FY-3(月次)収入'!O21 -> 0 | AN21: 0 | AO21: 0 | AP21: 0 | AQ21: 0 | AR21: 0 | AS21: 0 | AT21: 0 | AU21: 0 | AV21: 0 | AW21: 0 | AX21: 0 | AY21: 0 | AZ21: 0 | BA21: 0 | BB21: 0 | BC21: 0 | BD21: 0 | BE21: 0 | BF21: 0 | BG21: 0 | BH21: 0 | BI21: 0 | BJ21: 0 | BK21: 0 | BL21: =SUM(E21:O21) -> 0 | BM21: - | BN21: =SUM(P21:AA21) -> 0 | BO21: =BN21/BL21 -> #DIV/0! | BP21: =SUM(AB21:AM21) -> 0 | BQ21: =BP21/BN21 -> #DIV/0! | BR21: =SUM(AN21:AY21) -> 0 | BS21: =BR21/BP21 -> #DIV/0! | BT21: =SUM(AZ21:BK21) -> 0 | BU21: =BT21/BR21 -> #DIV/0!
D22: （総支給額に対する控除額の割合） | E22: =E12/E6 -> 0.17361478 | F22: =F12/F6 -> 0.11607877 | G22: =G12/G6 -> 0.18176 | H22: =H12/H6 -> 0.20198104 | I22: =I12/I6 -> 0.20951 | J22: =J12/J6 -> 0.20686727 | K22: =K12/K6 -> 0.20951101 | L22: =L12/L6 -> 0.173035 | ... BL22: =BL12/BL6 -> 0.21307449 | BM22: - | BN22: =IFERROR((BN12-BN9)/(BN5-BN9),"0%") -> 0.093531349 | BO22: =BN22-BL22 -> -0.11954314 | BP22: =IFERROR((BP12-BP9)/(BP5-BP9),"0%") -> -0.22620328 | BQ22: =BP22-BN22 -> -0.31973463 | BR22: =IFERROR((BR12-BR9)/(BR5-BR9),"0%") -> 0.076776638 | BS22: =BR22-BP22 -> 0.30297991 | BT22: =IFERROR((BT12-BT9)/(BT5-BT9),"0%") -> 0.11122662 | BU22: =BT22-BR22 -> 0.034449984
C23: 可処分所得 | D23: 合計 | E23: =E5-E12 -> 304485 | F23: =F5-F12 -> 408757 | G23: =G5-G12 -> 339296 | H23: =H5-H12 -> 338764 | I23: =I5-I12 -> 318196 | J23: =J5-J12 -> 361408 | K23: =K5-K12 -> 360882 | L23: =L5-L12 -> 332786 | ... BL23: =BL5-BL12 -> 3719995 | BM23: - | BN23: =BN5-BN12 -> 6192587.7 | BO23: =BN23/BL23 -> 1.6646764 | BP23: =BP5-BP12 -> 9291559 | BQ23: =BP23/BN23 -> 1.5004324 | BR23: =BR5-BR12 -> 8283160 | BS23: =BR23/BP23 -> 0.8914715 | BT23: =BT5-BT12 -> 6463160 | BU23: =BT23/BR23 -> 0.78027709
D24: 収入合計－控除額合計 | E24: =E5-E12 -> 304485 | F24: =F5-F12 -> 408757 | G24: =G5-G12 -> 339296 | H24: =H5-H12 -> 338764 | I24: =I5-I12 -> 318196 | J24: =J5-J12 -> 361408 | K24: =K5-K12 -> 360882 | L24: =L5-L12 -> 332786 | ... BL24: =BL5-BL12 -> 3719995 | BM24: - | BN24: =BN5-BN12 -> 6192587.7 | BO24: =BN24-BL24 -> 2472592.7 | BP24: =BP5-BP12 -> 9291559 | BQ24: =BP24-BN24 -> 3098971.3 | BR24: =BR5-BR12 -> 8283160 | BS24: =BR24-BP24 -> -1008399 | BT24: =BT5-BT12 -> 6463160 | BU24: =BT24-BR24 -> -1820000
D25: （収入合計に対する可処分所得の割合） | E25: =E23/E5 -> 0.83207855 | F25: =F23/F5 -> 0.88392123 | G25: =G23/G5 -> 0.82353398 | H25: =H23/H5 -> 0.7989717 | I25: =I23/I5 -> 0.79153234 | J25: =J23/J5 -> 0.79953984 | K25: =K23/K5 -> 0.79140789 | L25: =L23/L5 -> 0.82782587 | ... BL25: =BL23/BL5 -> 0.79170239 | BM25: - | BN25: =BN23/BN5 -> 0.82169457 | BO25: =BN25-BL25 -> 0.029992174 | BP25: =BP23/BP5 -> 0.84465132 | BQ25: =BP25-BN25 -> 0.022956754 | BR25: =BR23/BR5 -> 0.83905592 | BS25: =BR25-BP25 -> -0.005595407 | BT25: =BT23/BT5 -> 0.79089085 | BU25: =BT25-BR25 -> -0.048165069
C27: 支出管理 | E27: FY-1（2024年5月～2025年3月） | P27: FY-2（2025年4月～2026年3月） | AB27: FY-3（2026年4月～2027年3月） | AN27: FY-4（2027年4月～2028年3月） | AZ27: FY-5（2028年4月～2029年3月） | BL27: FY-1 | BN27: FY-2 | BP27: FY-3 | BR27: FY-4 | BT27: FY-5
C28: 氏名 | D28: 雇用形態 | E28: 5月 | F28: 6月 | G28: 7月 | H28: 8月 | I28: 9月 | J28: 10月 | K28: 11月 | L28: 12月 | M28: 1月 | N28: 2月 | O28: 3月 | P28: 4月 | Q28: 5月 | R28: 6月 | S28: 7月 | T28: 8月 | U28: 9月 | V28: 10月 | W28: 11月 | X28: 12月 | Y28: 1月 | Z28: 2月 | AA28: 3月 | AB28: 4月 | AC28: 5月 | AD28: 6月 | AE28: 7月 | AF28: 8月 | AG28: 9月 | AH28: 10月 | AI28: 11月 | AJ28: 12月 | AK28: 1月 | AL28: 2月 | AM28: 3月 | AN28: 4月 | AO28: 5月 | AP28: 6月 | AQ28: 7月 | AR28: 8月 | AS28: 9月 | AT28: 10月 | AU28: 11月 | AV28: 12月 | AW28: 1月 | AX28: 2月 | AY28: 3月 | AZ28: 4月 | BA28: 5月 | BB28: 6月 | BC28: 7月 | BD28: 8月 | BE28: 9月 | BF28: 10月 | BG28: 11月 | BH28: 12月 | BI28: 1月 | BJ28: 2月 | BK28: 3月 | BL28: 通期 | BM28: (昨対比) | BN28: 通期 | BO28: (昨対比) | BP28: 通期 | BQ28: (昨対比) | BR28: 通期 | BS28: (昨対比) | BT28: 通期 | BU28: (昨対比)
C29: 固定費・サブスク | D29: 合計 | E29: =SUM(E30:E46) -> 118303 | F29: =SUM(F30:F46) -> 119837 | G29: =SUM(G30:G46) -> 119841 | H29: =SUM(H30:H46) -> 119187 | I29: =SUM(I30:I46) -> 118877 | J29: =SUM(J30:J46) -> 121239 | K29: =SUM(K30:K46) -> 121417 | L29: =SUM(L30:L46) -> 123063 | ... BK29: =SUM(BK30:BK46) -> 174834 | BL29: =SUM(E29:O29) -> 1332533 | BM29: - | BN29: =SUM(P29:AA29) -> 1935350 | BO29: =BN29/BL29 -> 1.4523843 | BP29: =SUM(AB29:AM29) -> 1899955 | BQ29: =BP29/BN29 -> 0.98171132 | BR29: =SUM(AN29:AY29) -> 2098008 | BS29: =BR29/BP29 -> 1.1042409 | BT29: =SUM(AZ29:BK29) -> 2098008 | BU29: =BT29/BR29 -> 1
D30: 家賃※水道光熱費込み | E30: ='FY-1(月次)支出予実'!C8 -> 60682 | F30: ='FY-1(月次)支出予実'!D8 -> 62216 | G30: ='FY-1(月次)支出予実'!E8 -> 62216 | H30: ='FY-1(月次)支出予実'!F8 -> 62216 | I30: ='FY-1(月次)支出予実'!G8 -> 62216 | J30: ='FY-1(月次)支出予実'!H8 -> 62216 | K30: ='FY-1(月次)支出予実'!I8 -> 62216 | L30: ='FY-1(月次)支出予実'!J8 -> 65516 | ... O30: ='FY-1(月次)支出予実'!M8 -> 62216 | P30: ='FY-2(月次)支出'!D7 -> 59149 | Q30: ='FY-2(月次)支出'!E7 -> 88700 | R30: ='FY-2(月次)支出'!F7 -> 89587 | S30: ='FY-2(月次)支出'!G7 -> 89587 | T30: ='FY-2(月次)支出'!H7 -> 89587 | U30: ='FY-2(月次)支出'!I7 -> 89587 | V30: ='FY-2(月次)支出'!J7 -> 89587 | W30: ='FY-2(月次)支出'!K7 -> 129987 | ... AA30: ='FY-2(月次)支出'!O7 -> 129987 | AB30: ='FY-3(月次)支出 '!D7 -> 129987 | AC30: ='FY-3(月次)支出 '!E7 -> 129987 | AD30: ='FY-3(月次)支出 '!F7 -> 129987 | AE30: ='FY-3(月次)支出 '!G7 -> 129987 | AF30: ='FY-3(月次)支出 '!H7 -> 129987 | AG30: ='FY-3(月次)支出 '!I7 -> 129987 | AH30: ='FY-3(月次)支出 '!J7 -> 129987 | AI30: ='FY-3(月次)支出 '!K7 -> 129987 | ... AM30: ='FY-3(月次)支出 '!O7 -> 129987 | AN30: 129987 | AO30: 129987 | AP30: 129987 | AQ30: 129987 | AR30: 129987 | AS30: 129987 | AT30: 129987 | AU30: 129987 | AV30: 129987 | AW30: 129987 | AX30: 129987 | AY30: 129987 | AZ30: 129987 | BA30: 129987 | BB30: 129987 | BC30: 129987 | BD30: 129987 | BE30: 129987 | BF30: 129987 | BG30: 129987 | BH30: 129987 | BI30: 129987 | BJ30: 129987 | BK30: 129987 | BL30: =SUM(E30:O30) -> 686142 | BM30: - | BN30: =SUM(P30:AA30) -> 1245687 | BO30: =BN30/BL30 -> 1.8154945 | BP30: =SUM(AB30:AM30) -> 1559812 | BQ30: =BP30/BN30 -> 1.2521701 | BR30: =SUM(AN30:AY30) -> 1559844 | BS30: =BR30/BP30 -> 1.0000205 | BT30: =SUM(AZ30:BK30) -> 1559844 | BU30: =BT30/BR30 -> 1
D31: 生命保険料 | E31: ='FY-1(月次)支出予実'!C6 -> 9307 | F31: ='FY-1(月次)支出予実'!D6 -> 9307 | G31: ='FY-1(月次)支出予実'!E6 -> 9307 | H31: ='FY-1(月次)支出予実'!F6 -> 9307 | I31: ='FY-1(月次)支出予実'!G6 -> 9307 | J31: ='FY-1(月次)支出予実'!H6 -> 9307 | K31: ='FY-1(月次)支出予実'!I6 -> 9307 | L31: ='FY-1(月次)支出予実'!J6 -> 9307 | ... O31: ='FY-1(月次)支出予実'!M6 -> 9307 | P31: ='FY-2(月次)支出'!D9 -> 9307 | Q31: ='FY-2(月次)支出'!E9 -> 9307 | R31: ='FY-2(月次)支出'!F9 -> 9307 | S31: ='FY-2(月次)支出'!G9 -> 9307 | T31: ='FY-2(月次)支出'!H9 -> 9307 | U31: ='FY-2(月次)支出'!I9 -> 9307 | V31: ='FY-2(月次)支出'!J9 -> 9307 | W31: ='FY-2(月次)支出'!K9 -> 9307 | ... AA31: ='FY-2(月次)支出'!O9 -> 9307 | AB31: ='FY-3(月次)支出 '!D9 -> 9307 | AC31: ='FY-3(月次)支出 '!E9 -> 0 | AD31: ='FY-3(月次)支出 '!F9 -> 0 | AE31: ='FY-3(月次)支出 '!G9 -> 0 | AF31: ='FY-3(月次)支出 '!H9 -> 0 | AG31: ='FY-3(月次)支出 '!I9 -> 0 | AH31: ='FY-3(月次)支出 '!J9 -> 0 | AI31: ='FY-3(月次)支出 '!K9 -> 0 | ... AM31: ='FY-3(月次)支出 '!O9 -> 0 | AN31: 9307 | AO31: 9307 | AP31: 9307 | AQ31: 9307 | AR31: 9307 | AS31: 9307 | AT31: 9307 | AU31: 9307 | AV31: 9307 | AW31: 9307 | AX31: 9307 | AY31: 9307 | AZ31: 9307 | BA31: 9307 | BB31: 9307 | BC31: 9307 | BD31: 9307 | BE31: 9307 | BF31: 9307 | BG31: 9307 | BH31: 9307 | BI31: 9307 | BJ31: 9307 | BK31: 9307 | BL31: =SUM(E31:O31) -> 102377 | BM31: - | BN31: =SUM(P31:AA31) -> 111684 | BO31: =BN31/BL31 -> 1.0909091 | BP31: =SUM(AB31:AM31) -> 9307 | BQ31: =BP31/BN31 -> 0.083333333 | BR31: =SUM(AN31:AY31) -> 111684 | BS31: =BR31/BP31 -> 12 | BT31: =SUM(AZ31:BK31) -> 111684 | BU31: =BT31/BR31 -> 1
D32: ジム | E32: ='FY-1(月次)支出予実'!C7 -> 9680 | F32: ='FY-1(月次)支出予実'!D7 -> 9680 | G32: ='FY-1(月次)支出予実'!E7 -> 9680 | H32: ='FY-1(月次)支出予実'!F7 -> 9680 | I32: ='FY-1(月次)支出予実'!G7 -> 9680 | J32: ='FY-1(月次)支出予実'!H7 -> 9680 | K32: ='FY-1(月次)支出予実'!I7 -> 9680 | L32: ='FY-1(月次)支出予実'!J7 -> 9680 | ... O32: ='FY-1(月次)支出予実'!M7 -> 12980 | P32: ='FY-2(月次)支出'!D8 -> 0 | Q32: ='FY-2(月次)支出'!E8 -> 13232 | R32: ='FY-2(月次)支出'!F8 -> 11000 | S32: ='FY-2(月次)支出'!G8 -> 11000 | T32: ='FY-2(月次)支出'!H8 -> 11000 | U32: ='FY-2(月次)支出'!I8 -> 11000 | V32: ='FY-2(月次)支出'!J8 -> 11000 | W32: ='FY-2(月次)支出'!K8 -> 9167 | ... AA32: ='FY-2(月次)支出'!O8 -> 8000 | AB32: ='FY-3(月次)支出 '!D8 -> 8000 | AC32: ='FY-3(月次)支出 '!E8 -> 8000 | AD32: ='FY-3(月次)支出 '!F8 -> 0 | AE32: ='FY-3(月次)支出 '!G8 -> 0 | AF32: ='FY-3(月次)支出 '!H8 -> 0 | AG32: ='FY-3(月次)支出 '!I8 -> 0 | AH32: ='FY-3(月次)支出 '!J8 -> 0 | AI32: ='FY-3(月次)支出 '!K8 -> 0 | ... AM32: ='FY-3(月次)支出 '!O8 -> 0 | AN32: 9000 | AO32: 9000 | AP32: 9000 | AQ32: 9000 | AR32: 9000 | AS32: 9000 | AT32: 9000 | AU32: 9000 | AV32: 9000 | AW32: 9000 | AX32: 9000 | AY32: 9000 | AZ32: 9000 | BA32: 9000 | BB32: 9000 | BC32: 9000 | BD32: 9000 | BE32: 9000 | BF32: 9000 | BG32: 9000 | BH32: 9000 | BI32: 9000 | BJ32: 9000 | BK32: 9000 | BL32: =SUM(E32:O32) -> 113080 | BM32: - | BN32: =SUM(P32:AA32) -> 101399 | BO32: =BN32/BL32 -> 0.89670145 | BP32: =SUM(AB32:AM32) -> 16000 | BQ32: =BP32/BN32 -> 0.15779248 | BR32: =SUM(AN32:AY32) -> 108000 | BS32: =BR32/BP32 -> 6.75 | BT32: =SUM(AZ32:BK32) -> 108000 | BU32: =BT32/BR32 -> 1
D33: 携帯料金(SB) | E33: ='FY-1(月次)支出予実'!C11 -> 11554 | F33: ='FY-1(月次)支出予実'!D11 -> 11554 | G33: ='FY-1(月次)支出予実'!E11 -> 11558 | H33: ='FY-1(月次)支出予実'!F11 -> 10904 | I33: ='FY-1(月次)支出予実'!G11 -> 11554 | J33: ='FY-1(月次)支出予実'!H11 -> 11576 | K33: ='FY-1(月次)支出予実'!I11 -> 11554 | L33: ='FY-1(月次)支出予実'!J11 -> 11580 | ... O33: ='FY-1(月次)支出予実'!M11 -> 12533 | P33: ='FY-2(月次)支出'!D10 -> 12753 | Q33: ='FY-2(月次)支出'!E10 -> 12621 | R33: ='FY-2(月次)支出'!F10 -> 12907 | S33: ='FY-2(月次)支出'!G10 -> 12906 | T33: ='FY-2(月次)支出'!H10 -> 15784 | U33: ='FY-2(月次)支出'!I10 -> 9028 | V33: ='FY-2(月次)支出'!J10 -> 9160 | W33: ='FY-2(月次)支出'!K10 -> 9402 | ... AA33: ='FY-2(月次)支出'!O10 -> 9214 | AB33: ='FY-3(月次)支出 '!D10 -> 12218 | AC33: ='FY-3(月次)支出 '!E10 -> 9093 | AD33: ='FY-3(月次)支出 '!F10 -> 9137 | AE33: ='FY-3(月次)支出 '!G10 -> 9200 | AF33: ='FY-3(月次)支出 '!H10 -> 9200 | AG33: ='FY-3(月次)支出 '!I10 -> 9200 | AH33: ='FY-3(月次)支出 '!J10 -> 9200 | AI33: ='FY-3(月次)支出 '!K10 -> 9200 | ... AM33: ='FY-3(月次)支出 '!O10 -> 9200 | AN33: 9500 | AO33: 9500 | AP33: 9500 | AQ33: 9500 | AR33: 9500 | AS33: 9500 | AT33: 9500 | AU33: 9500 | AV33: 9500 | AW33: 9500 | AX33: 9500 | AY33: 9500 | AZ33: 9500 | BA33: 9500 | BB33: 9500 | BC33: 9500 | BD33: 9500 | BE33: 9500 | BF33: 9500 | BG33: 9500 | BH33: 9500 | BI33: 9500 | BJ33: 9500 | BK33: 9500 | BL33: =SUM(E33:O33) -> 128454 | BM33: - | BN33: =SUM(P33:AA33) -> 131249 | BO33: =BN33/BL33 -> 1.0217588 | BP33: =SUM(AB33:AM33) -> 113248 | BQ33: =BP33/BN33 -> 0.86284848 | BR33: =SUM(AN33:AY33) -> 114000 | BS33: =BR33/BP33 -> 1.0066403 | BT33: =SUM(AZ33:BK33) -> 114000 | BU33: =BT33/BR33 -> 1
D34: 定期券代 | E34: ='FY-1(月次)支出予実'!C16 -> 8830 | F34: ='FY-1(月次)支出予実'!D16 -> 8830 | G34: ='FY-1(月次)支出予実'!E16 -> 8830 | H34: ='FY-1(月次)支出予実'!F16 -> 8830 | I34: ='FY-1(月次)支出予実'!G16 -> 8830 | J34: ='FY-1(月次)支出予実'!H16 -> 8830 | K34: ='FY-1(月次)支出予実'!I16 -> 8830 | L34: ='FY-1(月次)支出予実'!J16 -> 8830 | ... O34: ='FY-1(月次)支出予実'!M16 -> 8830 | P34: ='FY-2(月次)支出'!D11 -> 8830 | Q34: ='FY-2(月次)支出'!E11 -> 0 | R34: ='FY-2(月次)支出'!F11 -> 22591 | S34: ='FY-2(月次)支出'!G11 -> 20340 | T34: ='FY-2(月次)支出'!H11 -> 20510 | U34: ='FY-2(月次)支出'!I11 -> 20510 | V34: ='FY-2(月次)支出'!J11 -> 20510 | W34: ='FY-2(月次)支出'!K11 -> 11590 | ... AA34: ='FY-2(月次)支出'!O11 -> 12420 | AB34: ='FY-3(月次)支出 '!D11 -> 13030 | AC34: ='FY-3(月次)支出 '!E11 -> 13030 | AD34: ='FY-3(月次)支出 '!F11 -> 12380 | AE34: ='FY-3(月次)支出 '!G11 -> 12380 | AF34: ='FY-3(月次)支出 '!H11 -> 12380 | AG34: ='FY-3(月次)支出 '!I11 -> 13030 | AH34: ='FY-3(月次)支出 '!J11 -> 13030 | AI34: ='FY-3(月次)支出 '!K11 -> 13030 | ... AM34: ='FY-3(月次)支出 '!O11 -> 13030 | AN34: 11590 | AO34: 11590 | AP34: 11590 | AQ34: 11590 | AR34: 11590 | AS34: 11590 | AT34: 11590 | AU34: 11590 | AV34: 11590 | AW34: 11590 | AX34: 11590 | AY34: 11590 | AZ34: 11590 | BA34: 11590 | BB34: 11590 | BC34: 11590 | BD34: 11590 | BE34: 11590 | BF34: 11590 | BG34: 11590 | BH34: 11590 | BI34: 11590 | BJ34: 11590 | BK34: 11590 | BL34: =SUM(E34:O34) -> 97130 | BM34: - | BN34: =SUM(P34:AA34) -> 173731 | BO34: =BN34/BL34 -> 1.7886441 | BP34: =SUM(AB34:AM34) -> 154410 | BQ34: =BP34/BN34 -> 0.88878784 | BR34: =SUM(AN34:AY34) -> 139080 | BS34: =BR34/BP34 -> 0.90071887 | BT34: =SUM(AZ34:BK34) -> 139080 | BU34: =BT34/BR34 -> 1
D35: Kindleサブスク | E35: - | F35: - | G35: - | H35: - | I35: - | J35: - | K35: - | L35: - | M35: - | N35: - | O35: - | P35: - | Q35: - | R35: - | S35: - | T35: - | U35: - | V35: - | W35: - | X35: - | Y35: - | Z35: - | AA35: 0 | AB35: ='FY-3(月次)支出 '!D14 -> 980 | AC35: ='FY-3(月次)支出 '!E14 -> 980 | AD35: ='FY-3(月次)支出 '!F14 -> 0 | AE35: ='FY-3(月次)支出 '!G14 -> 0 | AF35: ='FY-3(月次)支出 '!H14 -> 0 | AG35: ='FY-3(月次)支出 '!I14 -> 0 | AH35: ='FY-3(月次)支出 '!J14 -> 0 | AI35: ='FY-3(月次)支出 '!K14 -> 0 | ... AM35: ='FY-3(月次)支出 '!O14 -> 0
D36: 脱毛支払い(プラム) | E36: ='FY-1(月次)支出予実'!C9 -> 11400 | F36: ='FY-1(月次)支出予実'!D9 -> 11400 | G36: ='FY-1(月次)支出予実'!E9 -> 11400 | H36: ='FY-1(月次)支出予実'!F9 -> 11400 | I36: ='FY-1(月次)支出予実'!G9 -> 11400 | J36: ='FY-1(月次)支出予実'!H9 -> 11400 | K36: ='FY-1(月次)支出予実'!I9 -> 11400 | L36: ='FY-1(月次)支出予実'!J9 -> 11400 | ... O36: ='FY-1(月次)支出予実'!M9 -> 11400 | P36: ='FY-2(月次)支出'!D12 -> 11400 | Q36: ='FY-2(月次)支出'!E12 -> 11400 | R36: ='FY-2(月次)支出'!F12 -> 11400 | S36: ='FY-2(月次)支出'!G12 -> 11400 | T36: ='FY-2(月次)支出'!H12 -> 11400 | U36: ='FY-2(月次)支出'!I12 -> 11400 | V36: ='FY-2(月次)支出'!J12 -> 11400 | W36: ='FY-2(月次)支出'!K12 -> 11400 | ... AA36: ='FY-2(月次)支出'!O12 -> 0 | AB36: 0 | AC36: 0 | AD36: 0 | AE36: 0 | AF36: 0 | AG36: 0 | AH36: 0 | AI36: 0 | AJ36: 0 | AK36: 0 | AL36: 0 | AM36: 0 | AN36: 0 | AO36: 0 | AP36: 0 | AQ36: 0 | AR36: 0 | AS36: 0 | AT36: 0 | AU36: 0 | AV36: 0 | AW36: 0 | AX36: 0 | AY36: 0 | AZ36: 0 | BA36: 0 | BB36: 0 | BC36: 0 | BD36: 0 | BE36: 0 | BF36: 0 | BG36: 0 | BH36: 0 | BI36: 0 | BJ36: 0 | BK36: 0 | BL36: =SUM(E36:O36) -> 125400 | BM36: - | BN36: =SUM(P36:AA36) -> 114000 | BO36: =BN36/BL36 -> 0.90909091 | BP36: =SUM(AB36:AM36) -> 0 | BQ36: =BP36/BN36 -> 0 | BR36: =SUM(AN36:AY36) -> 0 | BS36: =BR36/BP36 -> #DIV/0! | BT36: =SUM(AZ36:BK36) -> 0 | BU36: =BT36/BR36 -> #DIV/0!
D37: iCloud拡張会費 | E37: ='FY-1(月次)支出予実'!C12 -> 450 | F37: ='FY-1(月次)支出予実'!D12 -> 450 | G37: ='FY-1(月次)支出予実'!E12 -> 450 | H37: ='FY-1(月次)支出予実'!F12 -> 450 | I37: ='FY-1(月次)支出予実'!G12 -> 450 | J37: ='FY-1(月次)支出予実'!H12 -> 450 | K37: ='FY-1(月次)支出予実'!I12 -> 450 | L37: ='FY-1(月次)支出予実'!J12 -> 450 | ... O37: ='FY-1(月次)支出予実'!M12 -> 450 | P37: ='FY-2(月次)支出'!D13 -> 450 | Q37: ='FY-2(月次)支出'!E13 -> 450 | R37: ='FY-2(月次)支出'!F13 -> 450 | S37: ='FY-2(月次)支出'!G13 -> 450 | T37: ='FY-2(月次)支出'!H13 -> 450 | U37: ='FY-2(月次)支出'!I13 -> 450 | V37: ='FY-2(月次)支出'!J13 -> 450 | W37: ='FY-2(月次)支出'!K13 -> 450 | ... AA37: ='FY-2(月次)支出'!O13 -> 150 | AB37: ='FY-3(月次)支出 '!D12 -> 150 | AC37: ='FY-3(月次)支出 '!E12 -> 150 | AD37: ='FY-3(月次)支出 '!F12 -> 150 | AE37: ='FY-3(月次)支出 '!G12 -> 150 | AF37: ='FY-3(月次)支出 '!H12 -> 150 | AG37: ='FY-3(月次)支出 '!I12 -> 150 | AH37: ='FY-3(月次)支出 '!J12 -> 150 | AI37: ='FY-3(月次)支出 '!K12 -> 150 | ... AM37: ='FY-3(月次)支出 '!O12 -> 150 | AN37: 450 | AO37: 450 | AP37: 450 | AQ37: 450 | AR37: 450 | AS37: 450 | AT37: 450 | AU37: 450 | AV37: 450 | AW37: 450 | AX37: 450 | AY37: 450 | AZ37: 450 | BA37: 450 | BB37: 450 | BC37: 450 | BD37: 450 | BE37: 450 | BF37: 450 | BG37: 450 | BH37: 450 | BI37: 450 | BJ37: 450 | BK37: 450 | BL37: =SUM(E37:O37) -> 4950 | BM37: - | BN37: =SUM(P37:AA37) -> 4800 | BO37: =BN37/BL37 -> 0.96969697 | BP37: =SUM(AB37:AM37) -> 1800 | BQ37: =BP37/BN37 -> 0.375 | BR37: =SUM(AN37:AY37) -> 5400 | BS37: =BR37/BP37 -> 3 | BT37: =SUM(AZ37:BK37) -> 5400 | BU37: =BT37/BR37 -> 1
C38: ★(2025年6月8日~1年)支払い済。減価償却の形で計上※2026年5月頃確認 | D38: あすけんプレミアム | E38: - | F38: - | G38: - | H38: - | I38: - | J38: - | K38: - | L38: - | M38: - | N38: - | O38: - | P38: 0 | Q38: 0 | R38: 0 | S38: 0 | T38: 0 | U38: 0 | V38: 0 | W38: 0 | X38: 0 | Y38: 0 | Z38: 0 | AA38: 0 | AB38: 0 | AC38: 0 | AD38: 0 | AE38: 0 | AF38: 0 | AG38: 0 | AH38: 0 | AI38: 0 | AJ38: 0 | AK38: 0 | AL38: 0 | AM38: 0 | AN38: 0 | AO38: 0 | AP38: 0 | AQ38: 0 | AR38: 0 | AS38: 0 | AT38: 0 | AU38: 0 | AV38: 0 | AW38: 0 | AX38: 0 | AY38: 0 | AZ38: 0 | BA38: 0 | BB38: 0 | BC38: 0 | BD38: 0 | BE38: 0 | BF38: 0 | BG38: 0 | BH38: 0 | BI38: 0 | BJ38: 0 | BK38: 0 | BL38: =SUM(E38:O38) -> 0 | BM38: - | BN38: =SUM(P38:AA38) -> 0 | BO38: =BN38/BL38 -> #DIV/0! | BP38: =SUM(AB38:AM38) -> 0 | BQ38: =BP38/BN38 -> #DIV/0! | BR38: =SUM(AN38:AY38) -> 0 | BS38: =BR38/BP38 -> #DIV/0! | BT38: =SUM(AZ38:BK38) -> 0 | BU38: =BT38/BR38 -> #DIV/0!
C39: ★2025年7月30日～年間プランに変更 7月~減価償却で計上※2026年6月頃要確認 | D39: Amazon Prime | E39: ='FY-1(月次)支出予実'!C14 -> 600 | F39: ='FY-1(月次)支出予実'!D14 -> 600 | G39: ='FY-1(月次)支出予実'!E14 -> 600 | H39: ='FY-1(月次)支出予実'!F14 -> 600 | I39: ='FY-1(月次)支出予実'!G14 -> 600 | J39: ='FY-1(月次)支出予実'!H14 -> 600 | K39: ='FY-1(月次)支出予実'!I14 -> 600 | L39: ='FY-1(月次)支出予実'!J14 -> 600 | ... O39: ='FY-1(月次)支出予実'!M14 -> 600 | P39: 0 | Q39: 0 | R39: 0 | S39: 0 | T39: 0 | U39: 0 | V39: 0 | W39: 0 | X39: 0 | Y39: 0 | Z39: 0 | AA39: 0 | AB39: 0 | AC39: 0 | AD39: 0 | AE39: 0 | AF39: 0 | AG39: 0 | AH39: 0 | AI39: 0 | AJ39: 0 | AK39: 0 | AL39: 0 | AM39: 0 | AN39: 0 | AO39: 0 | AP39: 0 | AQ39: 0 | AR39: 0 | AS39: 0 | AT39: 0 | AU39: 0 | AV39: 0 | AW39: 0 | AX39: 0 | AY39: 0 | AZ39: 0 | BA39: 0 | BB39: 0 | BC39: 0 | BD39: 0 | BE39: 0 | BF39: 0 | BG39: 0 | BH39: 0 | BI39: 0 | BJ39: 0 | BK39: 0 | BL39: =SUM(E39:O39) -> 6600 | BM39: - | BN39: =SUM(P39:AA39) -> 0 | BO39: =BN39/BL39 -> 0 | BP39: =SUM(AB39:AM39) -> 0 | BQ39: =BP39/BN39 -> #DIV/0! | BR39: =SUM(AN39:AY39) -> 0 | BS39: =BR39/BP39 -> #DIV/0! | BT39: =SUM(AZ39:BK39) -> 0 | BU39: =BT39/BR39 -> #DIV/0!
C40: ★2025年8月28日～年間プランに変更予定 9月~減価償却で計上※2026年7月頃要確認 | D40: テレ東BIZ | E40: ='FY-1(月次)支出予実'!C15 -> 550 | F40: ='FY-1(月次)支出予実'!D15 -> 550 | G40: ='FY-1(月次)支出予実'!E15 -> 550 | H40: ='FY-1(月次)支出予実'!F15 -> 550 | I40: ='FY-1(月次)支出予実'!G15 -> 550 | J40: ='FY-1(月次)支出予実'!H15 -> 1210 | K40: ='FY-1(月次)支出予実'!I15 -> 1210 | L40: ='FY-1(月次)支出予実'!J15 -> 1210 | ... O40: ='FY-1(月次)支出予実'!M15 -> 1210 | P40: 0 | Q40: 0 | R40: 0 | S40: 0 | T40: 0 | U40: 0 | V40: 0 | W40: 0 | X40: 0 | Y40: 0 | Z40: 0 | AA40: 0 | AB40: 0 | AC40: 0 | AD40: 0 | AE40: 0 | AF40: 0 | AG40: 0 | AH40: 0 | AI40: 0 | AJ40: 0 | AK40: 0 | AL40: 0 | AM40: 0 | AN40: 0 | AO40: 0 | AP40: 0 | AQ40: 0 | AR40: 0 | AS40: 0 | AT40: 0 | AU40: 0 | AV40: 0 | AW40: 0 | AX40: 0 | AY40: 0 | AZ40: 0 | BA40: 0 | BB40: 0 | BC40: 0 | BD40: 0 | BE40: 0 | BF40: 0 | BG40: 0 | BH40: 0 | BI40: 0 | BJ40: 0 | BK40: 0 | BL40: =SUM(E40:O40) -> 10010 | BM40: - | BN40: =SUM(P40:AA40) -> 0 | BO40: =BN40/BL40 -> 0 | BP40: =SUM(AB40:AM40) -> 0 | BQ40: =BP40/BN40 -> #DIV/0! | BR40: =SUM(AN40:AY40) -> 0 | BS40: =BR40/BP40 -> #DIV/0! | BT40: =SUM(AZ40:BK40) -> 0 | BU40: =BT40/BR40 -> #DIV/0!
D41: BASE FOOD/ナッシュ | E41: - | F41: - | G41: - | H41: - | I41: - | J41: - | K41: - | L41: - | M41: - | N41: - | O41: - | P41: ='FY-2(月次)支出'!D14 -> 0 | Q41: ='FY-2(月次)支出'!E14 -> 0 | R41: ='FY-2(月次)支出'!F14 -> 0 | S41: ='FY-2(月次)支出'!G14 -> 7324 | T41: ='FY-2(月次)支出'!H14 -> 3714 | U41: ='FY-2(月次)支出'!I14 -> 5182 | V41: ='FY-2(月次)支出'!J14 -> 5038 | W41: ='FY-2(月次)支出'!K14 -> 4920 | ... AA41: ='FY-2(月次)支出'!O14 -> 4036 | AB41: ='FY-3(月次)支出 '!D13 -> 4036 | AC41: ='FY-3(月次)支出 '!E13 -> 4036 | AD41: ='FY-3(月次)支出 '!F13 -> 3058 | AE41: ='FY-3(月次)支出 '!G13 -> 0 | AF41: ='FY-3(月次)支出 '!H13 -> 4036 | AG41: ='FY-3(月次)支出 '!I13 -> 4036 | AH41: ='FY-3(月次)支出 '!J13 -> 4036 | AI41: ='FY-3(月次)支出 '!K13 -> 4036 | ... AM41: ='FY-3(月次)支出 '!O13 -> 4036 | AN41: 5000 | AO41: 5000 | AP41: 5000 | AQ41: 5000 | AR41: 5000 | AS41: 5000 | AT41: 5000 | AU41: 5000 | AV41: 5000 | AW41: 5000 | AX41: 5000 | AY41: 5000 | AZ41: 5000 | BA41: 5000 | BB41: 5000 | BC41: 5000 | BD41: 5000 | BE41: 5000 | BF41: 5000 | BG41: 5000 | BH41: 5000 | BI41: 5000 | BJ41: 5000 | BK41: 5000 | BL41: =SUM(E41:O41) -> 0 | BM41: - | BN41: =SUM(P41:AA41) -> 44090 | BO41: =BN41/BL41 -> #DIV/0! | BP41: =SUM(AB41:AM41) -> 43418 | BQ41: =BP41/BN41 -> 0.98475845 | BR41: =SUM(AN41:AY41) -> 60000 | BS41: =BR41/BP41 -> 1.3819153 | BT41: =SUM(AZ41:BK41) -> 60000 | BU41: =BT41/BR41 -> 1
D42: chat gptプラス | E42: - | F42: - | G42: - | H42: - | I42: - | J42: - | K42: - | L42: - | M42: - | N42: - | O42: ='FY-1(月次)支出予実'!M17 -> 3000 | P42: ='FY-2(月次)支出'!D15 -> 3000 | Q42: ='FY-2(月次)支出'!E15 -> 3000 | R42: ='FY-2(月次)支出'!F15 -> 0 | S42: ='FY-2(月次)支出'!G15 -> 0 | T42: ='FY-2(月次)支出'!H15 -> 0 | U42: ='FY-2(月次)支出'!I15 -> 0 | V42: ='FY-2(月次)支出'!J15 -> 0 | W42: ='FY-2(月次)支出'!K15 -> 0 | ... AA42: ='FY-2(月次)支出'!O15 -> 0 | AB42: 0 | AC42: 0 | AD42: 0 | AE42: 0 | AF42: 0 | AG42: 0 | AH42: 0 | AI42: 0 | AJ42: 0 | AK42: 0 | AL42: 0 | AM42: 0 | AN42: 0 | AO42: 0 | AP42: 0 | AQ42: 0 | AR42: 0 | AS42: 0 | AT42: 0 | AU42: 0 | AV42: 0 | AW42: 0 | AX42: 0 | AY42: 0 | AZ42: 0 | BA42: 0 | BB42: 0 | BC42: 0 | BD42: 0 | BE42: 0 | BF42: 0 | BG42: 0 | BH42: 0 | BI42: 0 | BJ42: 0 | BK42: 0 | BL42: =SUM(E42:O42) -> 3000 | BM42: - | BN42: =SUM(P42:AA42) -> 6000 | BO42: =BN42/BL42 -> 2 | BP42: =SUM(AB42:AM42) -> 0 | BQ42: =BP42/BN42 -> 0 | BR42: =SUM(AN42:AY42) -> 0 | BS42: =BR42/BP42 -> #DIV/0! | BT42: =SUM(AZ42:BK42) -> 0 | BU42: =BT42/BR42 -> #DIV/0!
D43: Netflix | E43: ='FY-1(月次)支出予実'!C13 -> 990 | F43: ='FY-1(月次)支出予実'!D13 -> 990 | G43: ='FY-1(月次)支出予実'!E13 -> 990 | H43: ='FY-1(月次)支出予実'!F13 -> 990 | I43: ='FY-1(月次)支出予実'!G13 -> 990 | J43: ='FY-1(月次)支出予実'!H13 -> 990 | K43: ='FY-1(月次)支出予実'!I13 -> 1190 | L43: ='FY-1(月次)支出予実'!J13 -> 1190 | ... O43: ='FY-1(月次)支出予実'!M13 -> 1190 | P43: ='FY-2(月次)支出'!D16 -> 1190 | Q43: ='FY-2(月次)支出'!E16 -> 1190 | R43: ='FY-2(月次)支出'!F16 -> 0 | S43: ='FY-2(月次)支出'!G16 -> 0 | T43: ='FY-2(月次)支出'!H16 -> 0 | U43: ='FY-2(月次)支出'!I16 -> 0 | V43: ='FY-2(月次)支出'!J16 -> 0 | W43: ='FY-2(月次)支出'!K16 -> 0 | ... AA43: ='FY-2(月次)支出'!O16 -> 0 | AB43: 0 | AC43: 0 | AD43: 0 | AE43: 0 | AF43: 0 | AG43: 0 | AH43: 0 | AI43: 0 | AJ43: 0 | AK43: 0 | AL43: 0 | AM43: 0 | AN43: 0 | AO43: 0 | AP43: 0 | AQ43: 0 | AR43: 0 | AS43: 0 | AT43: 0 | AU43: 0 | AV43: 0 | AW43: 0 | AX43: 0 | AY43: 0 | AZ43: 0 | BA43: 0 | BB43: 0 | BC43: 0 | BD43: 0 | BE43: 0 | BF43: 0 | BG43: 0 | BH43: 0 | BI43: 0 | BJ43: 0 | BK43: 0 | BL43: =SUM(E43:O43) -> 11890 | BM43: - | BN43: =SUM(P43:AA43) -> 2380 | BO43: =BN43/BL43 -> 0.20016821 | BP43: =SUM(AB43:AM43) -> 0 | BQ43: =BP43/BN43 -> 0 | BR43: =SUM(AN43:AY43) -> 0 | BS43: =BR43/BP43 -> #DIV/0! | BT43: =SUM(AZ43:BK43) -> 0 | BU43: =BT43/BR43 -> #DIV/0!
D44: しがく会費 | E44: ='FY-1(月次)支出予実'!C10 -> 3300 | F44: ='FY-1(月次)支出予実'!D10 -> 3300 | G44: ='FY-1(月次)支出予実'!E10 -> 3300 | H44: ='FY-1(月次)支出予実'!F10 -> 3300 | I44: ='FY-1(月次)支出予実'!G10 -> 3300 | J44: ='FY-1(月次)支出予実'!H10 -> 3300 | K44: ='FY-1(月次)支出予実'!I10 -> 3300 | L44: ='FY-1(月次)支出予実'!J10 -> 3300 | ... O44: ='FY-1(月次)支出予実'!M10 -> 3300 | P44: ='FY-2(月次)支出'!D17 -> 330 | Q44: ='FY-2(月次)支出'!E17 -> 0 | R44: ='FY-2(月次)支出'!F17 -> 0 | S44: ='FY-2(月次)支出'!G17 -> 0 | T44: ='FY-2(月次)支出'!H17 -> 0 | U44: ='FY-2(月次)支出'!I17 -> 0 | V44: ='FY-2(月次)支出'!J17 -> 0 | W44: ='FY-2(月次)支出'!K17 -> 0 | ... AA44: ='FY-2(月次)支出'!O17 -> 0 | AB44: 0 | AC44: 0 | AD44: 0 | AE44: 0 | AF44: 0 | AG44: 0 | AH44: 0 | AI44: 0 | AJ44: 0 | AK44: 0 | AL44: 0 | AM44: 0 | AN44: 0 | AO44: 0 | AP44: 0 | AQ44: 0 | AR44: 0 | AS44: 0 | AT44: 0 | AU44: 0 | AV44: 0 | AW44: 0 | AX44: 0 | AY44: 0 | AZ44: 0 | BA44: 0 | BB44: 0 | BC44: 0 | BD44: 0 | BE44: 0 | BF44: 0 | BG44: 0 | BH44: 0 | BI44: 0 | BJ44: 0 | BK44: 0 | BL44: =SUM(E44:O44) -> 36300 | BM44: - | BN44: =SUM(P44:AA44) -> 330 | BO44: =BN44/BL44 -> 0.0090909091 | BP44: =SUM(AB44:AM44) -> 0 | BQ44: =BP44/BN44 -> 0 | BR44: =SUM(AN44:AY44) -> 0 | BS44: =BR44/BP44 -> #DIV/0! | BT44: =SUM(AZ44:BK44) -> 0 | BU44: =BT44/BR44 -> #DIV/0!
D45: YouTubeプレミアム | E45: ='FY-1(月次)支出予実'!C19 -> 0 | F45: ='FY-1(月次)支出予実'!D19 -> 0 | G45: ='FY-1(月次)支出予実'!E19 -> 0 | H45: ='FY-1(月次)支出予実'!F19 -> 0 | I45: ='FY-1(月次)支出予実'!G19 -> 0 | J45: ='FY-1(月次)支出予実'!H19 -> 1680 | K45: ='FY-1(月次)支出予実'!I19 -> 1680 | L45: ='FY-1(月次)支出予実'!J19 -> 0 | ... O45: ='FY-1(月次)支出予実'!M19 -> 0 | P45: 0 | Q45: 0 | R45: 0 | S45: 0 | T45: 0 | U45: 0 | V45: 0 | W45: 0 | X45: 0 | Y45: 0 | Z45: 0 | AA45: 0 | AB45: 0 | AC45: 0 | AD45: 0 | AE45: 0 | AF45: 0 | AG45: 0 | AH45: 0 | AI45: 0 | AJ45: 0 | AK45: 0 | AL45: 0 | AM45: 0 | AN45: 0 | AO45: 0 | AP45: 0 | AQ45: 0 | AR45: 0 | AS45: 0 | AT45: 0 | AU45: 0 | AV45: 0 | AW45: 0 | AX45: 0 | AY45: 0 | AZ45: 0 | BA45: 0 | BB45: 0 | BC45: 0 | BD45: 0 | BE45: 0 | BF45: 0 | BG45: 0 | BH45: 0 | BI45: 0 | BJ45: 0 | BK45: 0 | BL45: =SUM(E45:O45) -> 3360 | BM45: - | BN45: =SUM(P45:AA45) -> 0 | BO45: =BN45/BL45 -> 0 | BP45: =SUM(AB45:AM45) -> 0 | BQ45: =BP45/BN45 -> #DIV/0! | BR45: =SUM(AN45:AY45) -> 0 | BS45: =BR45/BP45 -> #DIV/0! | BT45: =SUM(AZ45:BK45) -> 0 | BU45: =BT45/BR45 -> #DIV/0!
D46: Abemaプレミアム | E46: ='FY-1(月次)支出予実'!C18 -> 960 | F46: ='FY-1(月次)支出予実'!D18 -> 960 | G46: ='FY-1(月次)支出予実'!E18 -> 960 | H46: ='FY-1(月次)支出予実'!F18 -> 960 | I46: ='FY-1(月次)支出予実'!G18 -> 0 | J46: ='FY-1(月次)支出予実'!H18 -> 0 | K46: ='FY-1(月次)支出予実'!I18 -> 0 | L46: ='FY-1(月次)支出予実'!J18 -> 0 | ... O46: ='FY-1(月次)支出予実'!M18 -> 0 | P46: ='FY-2(月次)支出'!D18 -> 0 | Q46: ='FY-2(月次)支出'!E18 -> 0 | R46: ='FY-2(月次)支出'!F18 -> 0 | S46: ='FY-2(月次)支出'!G18 -> 0 | T46: ='FY-2(月次)支出'!H18 -> 0 | U46: ='FY-2(月次)支出'!I18 -> 0 | V46: ='FY-2(月次)支出'!J18 -> 0 | W46: ='FY-2(月次)支出'!K18 -> 0 | ... AA46: ='FY-2(月次)支出'!O18 -> 0 | AB46: 0 | AC46: 0 | AD46: 0 | AE46: 0 | AF46: 0 | AG46: 0 | AH46: 0 | AI46: 0 | AJ46: 0 | AK46: 0 | AL46: 0 | AM46: 0 | AN46: 0 | AO46: 0 | AP46: 0 | AQ46: 0 | AR46: 0 | AS46: 0 | AT46: 0 | AU46: 0 | AV46: 0 | AW46: 0 | AX46: 0 | AY46: 0 | AZ46: 0 | BA46: 0 | BB46: 0 | BC46: 0 | BD46: 0 | BE46: 0 | BF46: 0 | BG46: 0 | BH46: 0 | BI46: 0 | BJ46: 0 | BK46: 0 | BL46: =SUM(E46:O46) -> 3840 | BM46: - | BN46: =SUM(P46:AA46) -> 0 | BO46: =BN46/BL46 -> 0 | BP46: =SUM(AB46:AM46) -> 0 | BQ46: =BP46/BN46 -> #DIV/0! | BR46: =SUM(AN46:AY46) -> 0 | BS46: =BR46/BP46 -> #DIV/0! | BT46: =SUM(AZ46:BK46) -> 0 | BU46: =BT46/BR46 -> #DIV/0!
D47: （可処分所得に対する固定費の割合） | E47: =E29/E23 -> 0.38853474 | F47: =F29/F23 -> 0.29317418 | G47: =G29/G23 -> 0.35320487 | H47: =H29/H23 -> 0.351829 | I47: =I29/I23 -> 0.37359678 | J47: =J29/J23 -> 0.33546297 | K47: =K29/K23 -> 0.33644515 | L47: =L29/L23 -> 0.36979621 | ... BK47: =BK29/BK23 -> 0.34380273 | BL47: =SUM(E47:O47) -> 3.8745943 | BM47: - | BN47: =SUM(P47:AA47) -> 5.6437752 | BO47: =BN47/BL47 -> 1.4566106 | BP47: =SUM(AB47:AM47) -> 2.6421647 | BQ47: =BP47/BN47 -> 0.46815555 | BR47: =SUM(AN47:AY47) -> 3.0539837 | BS47: =BR47/BP47 -> 1.1558643 | BT47: =SUM(AZ47:BK47) -> 3.9159432 | BU47: =BT47/BR47 -> 1.282241
C48: 食費（会食以外） | D48: 合計 | E48: =SUM(E49:E52) -> 64000 | F48: =SUM(F49:F52) -> 64000 | G48: =SUM(G49:G52) -> 64000 | H48: =SUM(H49:H52) -> 68000 | I48: =SUM(I49:I52) -> 63112 | J48: =SUM(J49:J52) -> 90169 | K48: =SUM(K49:K52) -> 122189 | L48: =SUM(L49:L52) -> 170806 | ... BK48: =SUM(BK49:BK52) -> 100000 | BL48: =SUM(E48:O48) -> 989371 | BM48: - | BN48: =SUM(P48:AA48) -> 1521059 | BO48: =BN48/BL48 -> 1.5374 | BP48: =SUM(AB48:AM48) -> 2167354 | BQ48: =BP48/BN48 -> 1.424898 | BR48: =SUM(AN48:AY48) -> 1200000 | BS48: =BR48/BP48 -> 0.55367051 | BT48: =SUM(AZ48:BK48) -> 1200000 | BU48: =BT48/BR48 -> 1
D49: 食費（1人） | E49: ='FY-1(月次)支出予実'!C22 -> 30000 | F49: ='FY-1(月次)支出予実'!D22 -> 30000 | G49: ='FY-1(月次)支出予実'!E22 -> 30000 | H49: ='FY-1(月次)支出予実'!F22 -> 30000 | I49: ='FY-1(月次)支出予実'!G22 -> 21794 | J49: ='FY-1(月次)支出予実'!H22 -> 35277 | K49: ='FY-1(月次)支出予実'!I22 -> 34563 | L49: ='FY-1(月次)支出予実'!J22 -> 40123 | ... O49: ='FY-1(月次)支出予実'!M22 -> 32269 | P49: ='FY-2(月次)支出'!D22 -> 36623 | Q49: ='FY-2(月次)支出'!E22 -> 44495 | R49: ='FY-2(月次)支出'!F22 -> 28774 | S49: ='FY-2(月次)支出'!G22 -> 27303 | T49: ='FY-2(月次)支出'!H22 -> 27961 | U49: ='FY-2(月次)支出'!I22 -> 27170 | V49: ='FY-2(月次)支出'!J22 -> 48661 | W49: ='FY-2(月次)支出'!K22 -> 36375 | ... AA49: ='FY-2(月次)支出'!O22 -> 38188 | AB49: ='FY-3(月次)支出 '!D20 -> 39230 | AC49: ='FY-3(月次)支出 '!E20 -> 13368 | AD49: ='FY-3(月次)支出 '!F20 -> 12414 | AE49: ='FY-3(月次)支出 '!G20 -> 30000 | AF49: ='FY-3(月次)支出 '!H20 -> 30000 | AG49: ='FY-3(月次)支出 '!I20 -> 30000 | AH49: ='FY-3(月次)支出 '!J20 -> 30000 | AI49: ='FY-3(月次)支出 '!K20 -> 30000 | ... AM49: ='FY-3(月次)支出 '!O20 -> 30000 | AN49: 30000 | AO49: 30000 | AP49: 30000 | AQ49: 30000 | AR49: 30000 | AS49: 30000 | AT49: 30000 | AU49: 30000 | AV49: 30000 | AW49: 30000 | AX49: 30000 | AY49: 30000 | AZ49: 30000 | BA49: 30000 | BB49: 30000 | BC49: 30000 | BD49: 30000 | BE49: 30000 | BF49: 30000 | BG49: 30000 | BH49: 30000 | BI49: 30000 | BJ49: 30000 | BK49: 30000 | BL49: =SUM(E49:O49) -> 366198 | BM49: - | BN49: =SUM(P49:AA49) -> 422422 | BO49: =BN49/BL49 -> 1.1535344 | BP49: =SUM(AB49:AM49) -> 335012 | BQ49: =BP49/BN49 -> 0.79307422 | BR49: =SUM(AN49:AY49) -> 360000 | BS49: =BR49/BP49 -> 1.0745884 | BT49: =SUM(AZ49:BK49) -> 360000 | BU49: =BT49/BR49 -> 1
D50: 交際費 | E50: ='FY-1(月次)支出予実'!C27 -> 30000 | F50: ='FY-1(月次)支出予実'!D27 -> 30000 | G50: ='FY-1(月次)支出予実'!E27 -> 30000 | H50: ='FY-1(月次)支出予実'!F27 -> 30000 | I50: ='FY-1(月次)支出予実'!G27 -> 30060 | J50: ='FY-1(月次)支出予実'!H27 -> 41848 | K50: ='FY-1(月次)支出予実'!I27 -> 71562 | L50: ='FY-1(月次)支出予実'!J27 -> 100887 | ... O50: ='FY-1(月次)支出予実'!M27 -> 29262 | P50: ='FY-2(月次)支出'!D23 -> 44765 | Q50: ='FY-2(月次)支出'!E23 -> 57343 | R50: ='FY-2(月次)支出'!F23 -> 4150 | S50: ='FY-2(月次)支出'!G23 -> 37069 | T50: ='FY-2(月次)支出'!H23 -> 64576 | U50: ='FY-2(月次)支出'!I23 -> 40401 | V50: ='FY-2(月次)支出'!J23 -> 40652 | W50: ='FY-2(月次)支出'!K23 -> 62264 | ... AA50: ='FY-2(月次)支出'!O23 -> 165996 | AB50: ='FY-3(月次)支出 '!D21 -> 83941 | AC50: ='FY-3(月次)支出 '!E21 -> 86657 | AD50: ='FY-3(月次)支出 '!F21 -> 86516 | AE50: ='FY-3(月次)支出 '!G21 -> 150000 | AF50: ='FY-3(月次)支出 '!H21 -> 250000 | AG50: ='FY-3(月次)支出 '!I21 -> 250000 | AH50: ='FY-3(月次)支出 '!J21 -> 100000 | AI50: ='FY-3(月次)支出 '!K21 -> 100000 | ... AM50: ='FY-3(月次)支出 '!O21 -> 100000 | AN50: 50000 | AO50: 50000 | AP50: 50000 | AQ50: 50000 | AR50: 50000 | AS50: 50000 | AT50: 50000 | AU50: 50000 | AV50: 50000 | AW50: 50000 | AX50: 50000 | AY50: 50000 | AZ50: 50000 | BA50: 50000 | BB50: 50000 | BC50: 50000 | BD50: 50000 | BE50: 50000 | BF50: 50000 | BG50: 50000 | BH50: 50000 | BI50: 50000 | BJ50: 50000 | BK50: 50000 | BL50: =SUM(E50:O50) -> 456900 | BM50: - | BN50: =SUM(P50:AA50) -> 800224 | BO50: =BN50/BL50 -> 1.7514204 | BP50: =SUM(AB50:AM50) -> 1507114 | BQ50: =BP50/BN50 -> 1.8833652 | BR50: =SUM(AN50:AY50) -> 600000 | BS50: =BR50/BP50 -> 0.39811189 | BT50: =SUM(AZ50:BK50) -> 600000 | BU50: =BT50/BR50 -> 1
D51: プレゼント・奢り等 | E51: ='FY-1(月次)支出予実'!C34 -> 0 | F51: ='FY-1(月次)支出予実'!D34 -> 0 | G51: ='FY-1(月次)支出予実'!E34 -> 0 | H51: ='FY-1(月次)支出予実'!F34 -> 4000 | I51: ='FY-1(月次)支出予実'!G34 -> 2146 | J51: ='FY-1(月次)支出予実'!H34 -> 2171 | K51: ='FY-1(月次)支出予実'!I34 -> 5771 | L51: ='FY-1(月次)支出予実'!J34 -> 20134 | ... O51: ='FY-1(月次)支出予実'!M34 -> 8574 | P51: ='FY-2(月次)支出'!D24 -> 4397 | Q51: ='FY-2(月次)支出'!E24 -> 22831 | R51: ='FY-2(月次)支出'!F24 -> 1704 | S51: ='FY-2(月次)支出'!G24 -> 1170 | T51: ='FY-2(月次)支出'!H24 -> 10772 | U51: ='FY-2(月次)支出'!I24 -> 12707 | V51: ='FY-2(月次)支出'!J24 -> 15486 | W51: ='FY-2(月次)支出'!K24 -> 18665 | ... AA51: ='FY-2(月次)支出'!O24 -> 19864 | AB51: ='FY-3(月次)支出 '!D22 -> 19397 | AC51: ='FY-3(月次)支出 '!E22 -> 21331 | AD51: ='FY-3(月次)支出 '!F22 -> 2570 | AE51: ='FY-3(月次)支出 '!G22 -> 10000 | AF51: ='FY-3(月次)支出 '!H22 -> 10000 | AG51: ='FY-3(月次)支出 '!I22 -> 10000 | AH51: ='FY-3(月次)支出 '!J22 -> 10000 | AI51: ='FY-3(月次)支出 '!K22 -> 10000 | ... AM51: ='FY-3(月次)支出 '!O22 -> 10000 | AN51: 10000 | AO51: 10000 | AP51: 10000 | AQ51: 10000 | AR51: 10000 | AS51: 10000 | AT51: 10000 | AU51: 10000 | AV51: 10000 | AW51: 10000 | AX51: 10000 | AY51: 10000 | AZ51: 10000 | BA51: 10000 | BB51: 10000 | BC51: 10000 | BD51: 10000 | BE51: 10000 | BF51: 10000 | BG51: 10000 | BH51: 10000 | BI51: 10000 | BJ51: 10000 | BK51: 10000 | BL51: =SUM(E51:O51) -> 86033 | BM51: - | BN51: =SUM(P51:AA51) -> 165081 | BO51: =BN51/BL51 -> 1.9188102 | BP51: =SUM(AB51:AM51) -> 133298 | BQ51: =BP51/BN51 -> 0.80747027 | BR51: =SUM(AN51:AY51) -> 120000 | BS51: =BR51/BP51 -> 0.90023856 | BT51: =SUM(AZ51:BK51) -> 120000 | BU51: =BT51/BR51 -> 1
D52: スーパー(まとめ買い) | E52: ='FY-1(月次)支出予実'!C26 -> 4000 | F52: ='FY-1(月次)支出予実'!D26 -> 4000 | G52: ='FY-1(月次)支出予実'!E26 -> 4000 | H52: ='FY-1(月次)支出予実'!F26 -> 4000 | I52: ='FY-1(月次)支出予実'!G26 -> 9112 | J52: ='FY-1(月次)支出予実'!H26 -> 10873 | K52: ='FY-1(月次)支出予実'!I26 -> 10293 | L52: ='FY-1(月次)支出予実'!J26 -> 9662 | ... O52: ='FY-1(月次)支出予実'!M26 -> 11106 | P52: ='FY-2(月次)支出'!D25 -> 0 | Q52: ='FY-2(月次)支出'!E25 -> 0 | R52: ='FY-2(月次)支出'!F25 -> 21399 | S52: ='FY-2(月次)支出'!G25 -> 11477 | T52: ='FY-2(月次)支出'!H25 -> 16697 | U52: ='FY-2(月次)支出'!I25 -> 8476 | V52: ='FY-2(月次)支出'!J25 -> 7903 | W52: ='FY-2(月次)支出'!K25 -> 14360 | ... AA52: ='FY-2(月次)支出'!O25 -> 17489 | AB52: ='FY-3(月次)支出 '!D23 -> 15288 | AC52: ='FY-3(月次)支出 '!E23 -> 23644 | AD52: ='FY-3(月次)支出 '!F23 -> 17998 | AE52: ='FY-3(月次)支出 '!G23 -> 15000 | AF52: ='FY-3(月次)支出 '!H23 -> 15000 | AG52: ='FY-3(月次)支出 '!I23 -> 15000 | AH52: ='FY-3(月次)支出 '!J23 -> 15000 | AI52: ='FY-3(月次)支出 '!K23 -> 15000 | ... AM52: ='FY-3(月次)支出 '!O23 -> 15000 | AN52: 10000 | AO52: 10000 | AP52: 10000 | AQ52: 10000 | AR52: 10000 | AS52: 10000 | AT52: 10000 | AU52: 10000 | AV52: 10000 | AW52: 10000 | AX52: 10000 | AY52: 10000 | AZ52: 10000 | BA52: 10000 | BB52: 10000 | BC52: 10000 | BD52: 10000 | BE52: 10000 | BF52: 10000 | BG52: 10000 | BH52: 10000 | BI52: 10000 | BJ52: 10000 | BK52: 10000 | BL52: =SUM(E52:O52) -> 80240 | BM52: - | BN52: =SUM(P52:AA52) -> 133332 | BO52: =BN52/BL52 -> 1.661665 | BP52: =SUM(AB52:AM52) -> 191930 | BQ52: =BP52/BN52 -> 1.4394894 | BR52: =SUM(AN52:AY52) -> 120000 | BS52: =BR52/BP52 -> 0.62522795 | BT52: =SUM(AZ52:BK52) -> 120000 | BU52: =BT52/BR52 -> 1
D53: （可処分所得に対する食費の割合） | E53: =E48/E$23 -> 0.21019098 | F53: =F48/F$23 -> 0.15657224 | G53: =G48/G$23 -> 0.18862586 | H53: =H48/H$23 -> 0.20072971 | I53: =I48/I$23 -> 0.19834316 | J53: =J48/J$23 -> 0.24949365 | K53: =K48/K$23 -> 0.33858436 | L53: =L48/L$23 -> 0.51326077 | ... BK53: =BK48/BK$23 -> 0.19664523 | BL53: =SUM(E53:O53) -> 2.868738 | BM53: - | BN53: =SUM(P53:AA53) -> 3.5106479 | BO53: =BN53/BL53 -> 1.2237604 | BP53: =SUM(AB53:AM53) -> 2.9665205 | BQ53: =BP53/BN53 -> 0.84500656 | BR53: =SUM(AN53:AY53) -> 1.7467905 | BS53: =BR53/BP53 -> 0.5888348 | BT53: =SUM(AZ53:BK53) -> 2.2398065 | BU53: =BT53/BR53 -> 1.282241
C54: 自己投資・1人体験 | D54: 合計 | E54: =SUM(E55:E56) -> 8000 | F54: =SUM(F55:F56) -> 9800 | G54: =SUM(G55:G56) -> 11000 | H54: =SUM(H55:H56) -> 8100 | I54: =SUM(I55:I56) -> 8073 | J54: =SUM(J55:J56) -> 28860 | K54: =SUM(K55:K56) -> 12688 | L54: =SUM(L55:L56) -> 11652 | ... BK54: =SUM(BK55:BK56) -> 5000 | BL54: =SUM(E54:O54) -> 145456 | BM54: - | BN54: =SUM(P54:AA54) -> 313897 | BO54: =BN54/BL54 -> 2.1580203 | BP54: =SUM(AB54:AM54) -> 868970 | BQ54: =BP54/BN54 -> 2.7683285 | BR54: =SUM(AN54:AY54) -> 220000 | BS54: =BR54/BP54 -> 0.2531733 | BT54: =SUM(AZ54:BK54) -> 260000 | BU54: =BT54/BR54 -> 1.1818182
D55: 1人体験(運動,散髪等) | E55: ='FY-1(月次)支出予実'!C36 -> 8000 | F55: ='FY-1(月次)支出予実'!D36 -> 9800 | G55: ='FY-1(月次)支出予実'!E36 -> 11000 | H55: ='FY-1(月次)支出予実'!F36 -> 8100 | I55: ='FY-1(月次)支出予実'!G36 -> 8073 | J55: ='FY-1(月次)支出予実'!H36 -> 28860 | K55: ='FY-1(月次)支出予実'!I36 -> 12688 | L55: ='FY-1(月次)支出予実'!J36 -> 11652 | ... O55: ='FY-1(月次)支出予実'!M36 -> 17426 | P55: ='FY-2(月次)支出'!D28 -> 4400 | Q55: ='FY-2(月次)支出'!E28 -> 7370 | R55: ='FY-2(月次)支出'!F28 -> 4111 | S55: ='FY-2(月次)支出'!G28 -> 9650 | T55: ='FY-2(月次)支出'!H28 -> 4128 | U55: ='FY-2(月次)支出'!I28 -> 1950 | V55: ='FY-2(月次)支出'!J28 -> 9020 | W55: ='FY-2(月次)支出'!K28 -> 8300 | ... AA55: ='FY-2(月次)支出'!O28 -> 22540 | AB55: ='FY-3(月次)支出 '!D26 -> 36690 | AC55: ='FY-3(月次)支出 '!E26 -> 89500 | AD55: ='FY-3(月次)支出 '!F26 -> 82780 | AE55: ='FY-3(月次)支出 '!G26 -> 60000 | AF55: ='FY-3(月次)支出 '!H26 -> 60000 | AG55: ='FY-3(月次)支出 '!I26 -> 60000 | AH55: ='FY-3(月次)支出 '!J26 -> 60000 | AI55: ='FY-3(月次)支出 '!K26 -> 60000 | ... AM55: ='FY-3(月次)支出 '!O26 -> 60000 | AN55: 5000 | AO55: 5000 | AP55: 5000 | AQ55: 5000 | AR55: 5000 | AS55: 5000 | AT55: 5000 | AU55: 5000 | AV55: 5000 | AW55: 5000 | AX55: 5000 | AY55: 5000 | AZ55: 5000 | BA55: 5000 | BB55: 5000 | BC55: 5000 | BD55: 5000 | BE55: 5000 | BF55: 5000 | BG55: 5000 | BH55: 5000 | BI55: 5000 | BJ55: 5000 | BK55: 5000 | BL55: =SUM(E55:O55) -> 145456 | BM55: - | BN55: =SUM(P55:AA55) -> 180332 | BO55: =BN55/BL55 -> 1.2397701 | BP55: =SUM(AB55:AM55) -> 748970 | BQ55: =BP55/BN55 -> 4.1532839 | BR55: =SUM(AN55:AY55) -> 60000 | BS55: =BR55/BP55 -> 0.080110018 | BT55: =SUM(AZ55:BK55) -> 60000 | BU55: =BT55/BR55 -> 1
D56: 結婚式 | E56: ='FY-1(月次)支出予実'!C35 -> 0 | F56: ='FY-1(月次)支出予実'!D35 -> 0 | G56: ='FY-1(月次)支出予実'!E35 -> 0 | H56: ='FY-1(月次)支出予実'!F35 -> 0 | I56: ='FY-1(月次)支出予実'!G35 -> 0 | J56: ='FY-1(月次)支出予実'!H35 -> 0 | K56: ='FY-1(月次)支出予実'!I35 -> 0 | L56: ='FY-1(月次)支出予実'!J35 -> 0 | ... O56: ='FY-1(月次)支出予実'!M35 -> 0 | P56: ='FY-2(月次)支出'!D29 -> 43560 | Q56: ='FY-2(月次)支出'!E29 -> 0 | R56: ='FY-2(月次)支出'!F29 -> 0 | S56: ='FY-2(月次)支出'!G29 -> 0 | T56: ='FY-2(月次)支出'!H29 -> 0 | U56: ='FY-2(月次)支出'!I29 -> 52005 | V56: ='FY-2(月次)支出'!J29 -> 8000 | W56: ='FY-2(月次)支出'!K29 -> 0 | ... AA56: ='FY-2(月次)支出'!O29 -> 0 | AB56: ='FY-3(月次)支出 '!D27 -> 0 | AC56: ='FY-3(月次)支出 '!E27 -> 0 | AD56: ='FY-3(月次)支出 '!F27 -> 0 | AE56: ='FY-3(月次)支出 '!G27 -> 30000 | AF56: ='FY-3(月次)支出 '!H27 -> 30000 | AG56: ='FY-3(月次)支出 '!I27 -> 0 | AH56: ='FY-3(月次)支出 '!J27 -> 30000 | AI56: ='FY-3(月次)支出 '!K27 -> 30000 | ... AM56: ='FY-3(月次)支出 '!O27 -> 0 | AN56: 0 | AO56: 0 | AP56: 40000 | AQ56: 0 | AR56: 0 | AS56: 40000 | AT56: 0 | AU56: 0 | AV56: 40000 | AW56: 0 | AX56: 40000 | AY56: 0 | AZ56: 0 | BA56: 40000 | BB56: 0 | BC56: 40000 | BD56: 0 | BE56: 40000 | BF56: 0 | BG56: 0 | BH56: 40000 | BI56: 0 | BJ56: 40000 | BK56: 0 | BL56: =SUM(E56:O56) -> 0 | BM56: - | BN56: =SUM(P56:AA56) -> 133565 | BO56: =BN56/BL56 -> #DIV/0! | BP56: =SUM(AB56:AM56) -> 120000 | BQ56: =BP56/BN56 -> 0.89843896 | BR56: =SUM(AN56:AY56) -> 160000 | BS56: =BR56/BP56 -> 1.3333333 | BT56: =SUM(AZ56:BK56) -> 200000 | BU56: =BT56/BR56 -> 1.25
D57: （可処分所得に対する自己投資・1人体験費の割合） | E57: =E54/E$23 -> 0.026273872 | F57: =F54/F$23 -> 0.023975125 | G57: =G54/G$23 -> 0.03242007 | H57: =H54/H$23 -> 0.023910451 | I57: =I54/I$23 -> 0.025371155 | J57: =J54/J$23 -> 0.079854347 | K57: =K54/K$23 -> 0.035158307 | L57: =L54/L$23 -> 0.035013492 | ... BK57: =BK54/BK$23 -> 0.0098322616 | BL57: =SUM(E57:O57) -> 0.41925841 | BM57: - | BN57: =SUM(P57:AA57) -> 0.61552092 | BO57: =BN57/BL57 -> 1.4681182 | BP57: =SUM(AB57:AM57) -> 1.2168881 | BQ57: =BP57/BN57 -> 1.9770053 | BR57: =SUM(AN57:AY57) -> 0.30890008 | BS57: =BR57/BP57 -> 0.25384428 | BT57: =SUM(AZ57:BK57) -> 0.48902605 | BU57: =BT57/BR57 -> 1.5831205
C58: 諸経費・備品購入費 | D58: 合計 | E58: =SUM(E59:E62) -> 11000 | F58: =SUM(F59:F62) -> 11000 | G58: =SUM(G59:G62) -> 11200 | H58: =SUM(H59:H62) -> 34339 | I58: =SUM(I59:I62) -> 20831 | J58: =SUM(J59:J62) -> 30439 | K58: =SUM(K59:K62) -> 25479 | L58: =SUM(L59:L62) -> 36358 | ... BK58: =SUM(BK59:BK62) -> 20000 | BL58: =SUM(E58:P58) -> 336576 | BM58: - | BN58: =SUM(P58:AA58) -> 1741882 | BO58: =BN58/BL58 -> 5.1753007 | BP58: =SUM(AB58:AM58) -> 1153273 | BQ58: =BP58/BN58 -> 0.66208446 | BR58: =SUM(AN58:AY58) -> 200000 | BS58: =BR58/BP58 -> 0.17341948 | BT58: =SUM(AZ58:BK58) -> 200000 | BU58: =BT58/BR58 -> 1
D59: 旅費・交通費 | E59: ='FY-1(月次)支出予実'!C44 -> 1000 | F59: ='FY-1(月次)支出予実'!D44 -> 1000 | G59: ='FY-1(月次)支出予実'!E44 -> 1000 | H59: ='FY-1(月次)支出予実'!F44 -> 1000 | I59: ='FY-1(月次)支出予実'!G44 -> 1000 | J59: ='FY-1(月次)支出予実'!H44 -> 1000 | K59: ='FY-1(月次)支出予実'!I44 -> 1000 | L59: ='FY-1(月次)支出予実'!J44 -> 1000 | ... O59: ='FY-1(月次)支出予実'!M44 -> 1000 | P59: ='FY-2(月次)支出'!D32 -> 29173 | Q59: ='FY-2(月次)支出'!E32 -> 28969 | R59: ='FY-2(月次)支出'!F32 -> 3296 | S59: ='FY-2(月次)支出'!G32 -> 13594 | T59: ='FY-2(月次)支出'!H32 -> 20598 | U59: ='FY-2(月次)支出'!I32 -> 18940 | V59: ='FY-2(月次)支出'!J32 -> 47043 | W59: ='FY-2(月次)支出'!K32 -> 11966 | ... AA59: ='FY-2(月次)支出'!O32 -> 74334 | AB59: ='FY-3(月次)支出 '!D30 -> 49681 | AC59: ='FY-3(月次)支出 '!E30 -> 33168 | AD59: ='FY-3(月次)支出 '!F30 -> 12548 | AE59: ='FY-3(月次)支出 '!G30 -> 15000 | AF59: ='FY-3(月次)支出 '!H30 -> 15000 | AG59: ='FY-3(月次)支出 '!I30 -> 15000 | AH59: ='FY-3(月次)支出 '!J30 -> 15000 | AI59: ='FY-3(月次)支出 '!K30 -> 15000 | ... AM59: ='FY-3(月次)支出 '!O30 -> 15000 | AN59: 5000 | AO59: 5000 | AP59: 5000 | AQ59: 5000 | AR59: 5000 | AS59: 5000 | AT59: 5000 | AU59: 5000 | AV59: 5000 | AW59: 5000 | AX59: 5000 | AY59: 5000 | AZ59: 5000 | BA59: 5000 | BB59: 5000 | BC59: 5000 | BD59: 5000 | BE59: 5000 | BF59: 5000 | BG59: 5000 | BH59: 5000 | BI59: 5000 | BJ59: 5000 | BK59: 5000 | BL59: =SUM(E59:P59) -> 40173 | BM59: - | BN59: =SUM(P59:AA59) -> 401405 | BO59: =BN59/BL59 -> 9.99191 | BP59: =SUM(AB59:AM59) -> 230397 | BQ59: =BP59/BN59 -> 0.57397641 | BR59: =SUM(AN59:AY59) -> 60000 | BS59: =BR59/BP59 -> 0.26042006 | BT59: =SUM(AZ59:BK59) -> 60000 | BU59: =BT59/BR59 -> 1
D60: 物品購入費(生活用品全般) | E60: ='FY-1(月次)支出予実'!C47 -> 5000 | F60: ='FY-1(月次)支出予実'!D47 -> 5000 | G60: ='FY-1(月次)支出予実'!E47 -> 5200 | H60: ='FY-1(月次)支出予実'!F47 -> 21339 | I60: ='FY-1(月次)支出予実'!G47 -> 12351 | J60: ='FY-1(月次)支出予実'!H47 -> 22119 | K60: ='FY-1(月次)支出予実'!I47 -> 17569 | L60: ='FY-1(月次)支出予実'!J47 -> 28268 | ... O60: ='FY-1(月次)支出予実'!M47 -> 26615 | P60: ='FY-2(月次)支出'!D33 -> 49492 | Q60: ='FY-2(月次)支出'!E33 -> 4418 | R60: ='FY-2(月次)支出'!F33 -> 76924 | S60: ='FY-2(月次)支出'!G33 -> 43022 | T60: ='FY-2(月次)支出'!H33 -> 21970 | U60: ='FY-2(月次)支出'!I33 -> 15079 | V60: ='FY-2(月次)支出'!J33 -> 41297 | W60: ='FY-2(月次)支出'!K33 -> 47119 | ... AA60: ='FY-2(月次)支出'!O33 -> 39229 | AB60: ='FY-3(月次)支出 '!D31 -> 7451 | AC60: ='FY-3(月次)支出 '!E31 -> 5834 | AD60: ='FY-3(月次)支出 '!F31 -> 8428 | AE60: ='FY-3(月次)支出 '!G31 -> 20000 | AF60: ='FY-3(月次)支出 '!H31 -> 10000 | AG60: ='FY-3(月次)支出 '!I31 -> 300000 | AH60: ='FY-3(月次)支出 '!J31 -> 100000 | AI60: ='FY-3(月次)支出 '!K31 -> 100000 | ... AM60: ='FY-3(月次)支出 '!O31 -> 100000 | AN60: 5000 | AO60: 5000 | AP60: 5000 | AQ60: 5000 | AR60: 5000 | AS60: 5000 | AT60: 5000 | AU60: 5000 | AV60: 5000 | AW60: 5000 | AX60: 5000 | AY60: 5000 | AZ60: 5000 | BA60: 5000 | BB60: 5000 | BC60: 5000 | BD60: 5000 | BE60: 5000 | BF60: 5000 | BG60: 5000 | BH60: 5000 | BI60: 5000 | BJ60: 5000 | BK60: 5000 | BL60: =SUM(E60:P60) -> 206186 | BM60: - | BN60: =SUM(P60:AA60) -> 737137 | BO60: =BN60/BL60 -> 3.5751069 | BP60: =SUM(AB60:AM60) -> 771713 | BQ60: =BP60/BN60 -> 1.0469058 | BR60: =SUM(AN60:AY60) -> 60000 | BS60: =BR60/BP60 -> 0.077749111 | BT60: =SUM(AZ60:BK60) -> 60000 | BU60: =BT60/BR60 -> 1
D61: その他諸経費 | E61: ='FY-1(月次)支出予実'!C46 -> 0 | F61: ='FY-1(月次)支出予実'!D46 -> 0 | G61: ='FY-1(月次)支出予実'!E46 -> 0 | H61: ='FY-1(月次)支出予実'!F46 -> 7000 | I61: ='FY-1(月次)支出予実'!G46 -> 0 | J61: ='FY-1(月次)支出予実'!H46 -> 0 | K61: ='FY-1(月次)支出予実'!I46 -> 0 | L61: ='FY-1(月次)支出予実'!J46 -> 0 | ... O61: ='FY-1(月次)支出予実'!M46 -> 2560 | P61: ='FY-2(月次)支出'!D34 -> 0 | Q61: ='FY-2(月次)支出'!E34 -> 147777 | R61: ='FY-2(月次)支出'!F34 -> 22175 | S61: ='FY-2(月次)支出'!G34 -> 3894 | T61: ='FY-2(月次)支出'!H34 -> 430 | U61: ='FY-2(月次)支出'!I34 -> 775 | V61: ='FY-2(月次)支出'!J34 -> 132955 | W61: ='FY-2(月次)支出'!K34 -> 169190 | ... AA61: ='FY-2(月次)支出'!O34 -> 11709 | AB61: ='FY-3(月次)支出 '!D32 -> 1308 | AC61: ='FY-3(月次)支出 '!E32 -> 475 | AD61: ='FY-3(月次)支出 '!F32 -> 6010 | AE61: ='FY-3(月次)支出 '!G32 -> 5000 | AF61: ='FY-3(月次)支出 '!H32 -> 5000 | AG61: ='FY-3(月次)支出 '!I32 -> 5000 | AH61: ='FY-3(月次)支出 '!J32 -> 5000 | AI61: ='FY-3(月次)支出 '!K32 -> 5000 | ... AM61: ='FY-3(月次)支出 '!O32 -> 5000 | AN61: 5000 | AO61: 0 | AP61: 0 | AQ61: 0 | AR61: 5000 | AS61: 0 | AT61: 0 | AU61: 5000 | AV61: 0 | AW61: 0 | AX61: 0 | AY61: 5000 | AZ61: 5000 | BA61: 0 | BB61: 0 | BC61: 0 | BD61: 5000 | BE61: 0 | BF61: 0 | BG61: 5000 | BH61: 0 | BI61: 0 | BJ61: 0 | BK61: 5000 | BL61: =SUM(E61:P61) -> 9560 | BM61: - | BN61: =SUM(P61:AA61) -> 518590 | BO61: =BN61/BL61 -> 54.245816 | BP61: =SUM(AB61:AM61) -> 52793 | BQ61: =BP61/BN61 -> 0.10180104 | BR61: =SUM(AN61:AY61) -> 20000 | BS61: =BR61/BP61 -> 0.3788381 | BT61: =SUM(AZ61:BK61) -> 20000 | BU61: =BT61/BR61 -> 1
D62: 嗜好品(TBC) | E62: ='FY-1(月次)支出予実'!C25 -> 5000 | F62: ='FY-1(月次)支出予実'!D25 -> 5000 | G62: ='FY-1(月次)支出予実'!E25 -> 5000 | H62: ='FY-1(月次)支出予実'!F25 -> 5000 | I62: ='FY-1(月次)支出予実'!G25 -> 7480 | J62: ='FY-1(月次)支出予実'!H25 -> 7320 | K62: ='FY-1(月次)支出予実'!I25 -> 6910 | L62: ='FY-1(月次)支出予実'!J25 -> 7090 | ... O62: ='FY-1(月次)支出予実'!M25 -> 7730 | P62: ='FY-2(月次)支出'!D35 -> 9760 | Q62: ='FY-2(月次)支出'!E35 -> 4940 | R62: ='FY-2(月次)支出'!F35 -> 1000 | S62: ='FY-2(月次)支出'!G35 -> 5500 | T62: ='FY-2(月次)支出'!H35 -> 6650 | U62: ='FY-2(月次)支出'!I35 -> 6510 | V62: ='FY-2(月次)支出'!J35 -> 7440 | W62: ='FY-2(月次)支出'!K35 -> 12040 | ... AA62: ='FY-2(月次)支出'!O35 -> 8400 | AB62: ='FY-3(月次)支出 '!D33 -> 9650 | AC62: ='FY-3(月次)支出 '!E33 -> 8080 | AD62: ='FY-3(月次)支出 '!F33 -> 8640 | AE62: ='FY-3(月次)支出 '!G33 -> 8000 | AF62: ='FY-3(月次)支出 '!H33 -> 8000 | AG62: ='FY-3(月次)支出 '!I33 -> 8000 | AH62: ='FY-3(月次)支出 '!J33 -> 8000 | AI62: ='FY-3(月次)支出 '!K33 -> 8000 | ... AM62: ='FY-3(月次)支出 '!O33 -> 8000 | AN62: 5000 | AO62: 5000 | AP62: 5000 | AQ62: 5000 | AR62: 5000 | AS62: 5000 | AT62: 5000 | AU62: 5000 | AV62: 5000 | AW62: 5000 | AX62: 5000 | AY62: 5000 | AZ62: 5000 | BA62: 5000 | BB62: 5000 | BC62: 5000 | BD62: 5000 | BE62: 5000 | BF62: 5000 | BG62: 5000 | BH62: 5000 | BI62: 5000 | BJ62: 5000 | BK62: 5000 | BL62: =SUM(E62:P62) -> 80657 | BM62: - | BN62: =SUM(P62:AA62) -> 84750 | BO62: =BN62/BL62 -> 1.0507458 | BP62: =SUM(AB62:AM62) -> 98370 | BQ62: =BP62/BN62 -> 1.160708 | BR62: =SUM(AN62:AY62) -> 60000 | BS62: =BR62/BP62 -> 0.60994206 | BT62: =SUM(AZ62:BK62) -> 60000 | BU62: =BT62/BR62 -> 1
D63: （可処分所得に対する諸経費・備品購入費の割合） | E63: =E58/E$23 -> 0.036126574 | F63: =F58/F$23 -> 0.026910854 | G63: =G58/G$23 -> 0.033009526 | H63: =H58/H$23 -> 0.10136555 | I63: =I58/I$23 -> 0.065465939 | J63: =J58/J$23 -> 0.084223371 | K63: =K58/K$23 -> 0.070602025 | L63: =L58/L$23 -> 0.10925339 | ... BK63: =BK58/BK$23 -> 0.039329046 | BL63: =SUM(E63:P63) -> 0.97356478 | BM63: - | BN63: =SUM(P63:AA63) -> 4.5731527 | BO63: =BN63/BL63 -> 4.6973276 | BP63: =SUM(AB63:AM63) -> 1.4859439 | BQ63: =BP63/BN63 -> 0.32492767 | BR63: =SUM(AN63:AY63) -> 0.29119422 | BS63: =BR63/BP63 -> 0.19596583 | BT63: =SUM(AZ63:BK63) -> 0.37322319 | BU63: =BT63/BR63 -> 1.2816985
C64: 支払い利息 | D64: 合計 | E64: =SUM(E65:E66) -> 0 | F64: =SUM(F65:F66) -> 0 | G64: =SUM(G65:G66) -> 110000 | H64: =SUM(H65:H66) -> 110000 | I64: =SUM(I65:I66) -> 110000 | J64: =SUM(J65:J66) -> 110000 | K64: =SUM(K65:K66) -> 110000 | L64: =SUM(L65:L66) -> 110000 | ... BK64: =SUM(BK65:BK66) -> 0 | BL64: =SUM(E64:P64) -> 997219 | BM64: - | BN64: =SUM(P64:AA64) -> 899819 | BO64: =BN64/BL64 -> 0.90232838 | BP64: =SUM(AB64:AM64) -> 0 | BQ64: =BP64/BN64 -> 0 | BR64: =SUM(AN64:AY64) -> 0 | BS64: =BR64/BP64 -> #DIV/0! | BT64: =SUM(AZ64:BK64) -> 0 | BU64: =BT64/BR64 -> #DIV/0!
D65: ①元金返済金額 | E65: ='FY-1(月次)支出予実'!C50 -> 0 | F65: ='FY-1(月次)支出予実'!D50 -> 0 | G65: ='FY-1(月次)支出予実'!E50 -> 100000 | H65: ='FY-1(月次)支出予実'!F50 -> 100000 | I65: ='FY-1(月次)支出予実'!G50 -> 100000 | J65: ='FY-1(月次)支出予実'!H50 -> 100000 | K65: ='FY-1(月次)支出予実'!I50 -> 100000 | L65: ='FY-1(月次)支出予実'!J50 -> 100000 | ... O65: ='FY-1(月次)支出予実'!M50 -> 100000 | P65: ='FY-2(月次)支出'!D37 -> 0 | Q65: ='FY-2(月次)支出'!E37 -> 0 | R65: ='FY-2(月次)支出'!F37 -> 10762 | S65: ='FY-2(月次)支出'!G37 -> 179852 | T65: ='FY-2(月次)支出'!H37 -> 167170 | U65: ='FY-2(月次)支出'!I37 -> 182978 | V65: ='FY-2(月次)支出'!J37 -> 10000 | W65: ='FY-2(月次)支出'!K37 -> 0 | ... AA65: ='FY-2(月次)支出'!O37 -> 0 | AB65: ='FY-3(月次)支出 '!D35 -> 0 | AC65: ='FY-3(月次)支出 '!E35 -> 0 | AD65: ='FY-3(月次)支出 '!F35 -> 0 | AE65: ='FY-3(月次)支出 '!G35 -> 0 | AF65: ='FY-3(月次)支出 '!H35 -> 0 | AG65: ='FY-3(月次)支出 '!I35 -> 0 | AH65: ='FY-3(月次)支出 '!J35 -> 0 | AI65: ='FY-3(月次)支出 '!K35 -> 0 | ... AM65: ='FY-3(月次)支出 '!O35 -> 0 | AN65: 0 | AO65: 0 | AP65: 0 | AQ65: 0 | AR65: 0 | AS65: 0 | AT65: 0 | AU65: 0 | AV65: 0 | AW65: 0 | AX65: 0 | AY65: 0 | AZ65: 0 | BA65: 0 | BB65: 0 | BC65: 0 | BD65: 0 | BE65: 0 | BF65: 0 | BG65: 0 | BH65: 0 | BI65: 0 | BJ65: 0 | BK65: 0 | BL65: =SUM(E65:P65) -> 900000 | BM65: - | BN65: =SUM(P65:AA65) -> 830762 | BO65: =BN65/BL65 -> 0.92306889 | BP65: =SUM(AB65:AM65) -> 0 | BQ65: =BP65/BN65 -> 0 | BR65: =SUM(AN65:AY65) -> 0 | BS65: =BR65/BP65 -> #DIV/0! | BT65: =SUM(AZ65:BK65) -> 0 | BU65: =BT65/BR65 -> #DIV/0!
D66: ②返済利子 | E66: ='FY-1(月次)支出予実'!C51 -> 0 | F66: ='FY-1(月次)支出予実'!D51 -> 0 | G66: ='FY-1(月次)支出予実'!E51 -> 10000 | H66: ='FY-1(月次)支出予実'!F51 -> 10000 | I66: ='FY-1(月次)支出予実'!G51 -> 10000 | J66: ='FY-1(月次)支出予実'!H51 -> 10000 | K66: ='FY-1(月次)支出予実'!I51 -> 10000 | L66: ='FY-1(月次)支出予実'!J51 -> 10000 | ... O66: ='FY-1(月次)支出予実'!M51 -> 10000 | P66: ='FY-2(月次)支出'!D38 -> 7219 | Q66: ='FY-2(月次)支出'!E38 -> 5148 | R66: ='FY-2(月次)支出'!F38 -> 14675 | S66: ='FY-2(月次)支出'!G38 -> 15761 | T66: ='FY-2(月次)支出'!H38 -> 7317 | U66: ='FY-2(月次)支出'!I38 -> 5727 | V66: ='FY-2(月次)支出'!J38 -> 4433 | W66: ='FY-2(月次)支出'!K38 -> 4142 | ... AA66: ='FY-2(月次)支出'!O38 -> 0 | AB66: ='FY-3(月次)支出 '!D36 -> 0 | AC66: ='FY-3(月次)支出 '!E36 -> 0 | AD66: ='FY-3(月次)支出 '!F36 -> 0 | AE66: ='FY-3(月次)支出 '!G36 -> 0 | AF66: ='FY-3(月次)支出 '!H36 -> 0 | AG66: ='FY-3(月次)支出 '!I36 -> 0 | AH66: ='FY-3(月次)支出 '!J36 -> 0 | AI66: ='FY-3(月次)支出 '!K36 -> 0 | ... AM66: ='FY-3(月次)支出 '!O36 -> 0 | AN66: 0 | AO66: 0 | AP66: 0 | AQ66: 0 | AR66: 0 | AS66: 0 | AT66: 0 | AU66: 0 | AV66: 0 | AW66: 0 | AX66: 0 | AY66: 0 | AZ66: 0 | BA66: 0 | BB66: 0 | BC66: 0 | BD66: 0 | BE66: 0 | BF66: 0 | BG66: 0 | BH66: 0 | BI66: 0 | BJ66: 0 | BK66: 0 | BL66: =SUM(E66:P66) -> 97219 | BM66: - | BN66: =SUM(P66:AA66) -> 69057 | BO66: =BN66/BL66 -> 0.71032411 | BP66: =SUM(AB66:AM66) -> 0 | BQ66: =BP66/BN66 -> 0 | BR66: =SUM(AN66:AY66) -> 0 | BS66: =BR66/BP66 -> #DIV/0! | BT66: =SUM(AZ66:BK66) -> 0 | BU66: =BT66/BR66 -> #DIV/0!
D67: （可処分所得に対する支払利息の割合） | E67: =E64/E$23 -> 0 | F67: =F64/F$23 -> 0 | G67: =G64/G$23 -> 0.3242007 | H67: =H64/H$23 -> 0.32470983 | I67: =I64/I$23 -> 0.34569888 | J67: =J64/J$23 -> 0.30436515 | K67: =K64/K$23 -> 0.30480877 | L67: =L64/L$23 -> 0.33054275 | ... BK67: =BK64/BK$23 -> 0 | BL67: =SUM(E67:P67) -> 2.9074524 | BM67: - | BN67: =SUM(P67:AA67) -> 1.9302492 | BO67: =BN67/BL67 -> 0.66389708 | BP67: =SUM(AB67:AM67) -> 0 | BQ67: =BP67/BN67 -> 0 | BR67: =SUM(AN67:AY67) -> 0 | BS67: =BR67/BP67 -> #DIV/0! | BT67: =SUM(AZ67:BK67) -> 0 | BU67: =BT67/BR67 -> #DIV/0!
C68: 固定費：合計支出額 | E68: =SUM(E30:E46) -> 118303 | F68: =SUM(F30:F46) -> 119837 | G68: =SUM(G30:G46) -> 119841 | H68: =SUM(H30:H46) -> 119187 | I68: =SUM(I30:I46) -> 118877 | J68: =SUM(J30:J46) -> 121239 | K68: =SUM(K30:K46) -> 121417 | L68: =SUM(L30:L46) -> 123063 | ... BK68: =SUM(BK30:BK46) -> 174834 | BL68: =SUM(E68:P68) -> 1438942 | BM68: - | BN68: =SUM(P68:AA68) -> 1935350 | BO68: =BN68/BL68 -> 1.3449812 | BP68: =SUM(AB68:AM68) -> 1899955 | BQ68: =BP68/BN68 -> 0.98171132 | BR68: =SUM(AN68:AY68) -> 2098008 | BS68: =BR68/BP68 -> 1.1042409 | BT68: =SUM(AZ68:BK68) -> 2098008 | BU68: =BT68/BR68 -> 1
C69: 変動費：合計支出額 | E69: =E48+E54+E58 -> 83000 | F69: =F48+F54+F58 -> 84800 | G69: =G48+G54+G58 -> 86200 | H69: =H48+H54+H58 -> 110439 | I69: =I48+I54+I58 -> 92016 | J69: =J48+J54+J58 -> 149468 | K69: =K48+K54+K58 -> 160356 | L69: =L48+L54+L58 -> 218816 | ... BK69: =BK48+BK54+BK58 -> 125000 | BL69: =SUM(E69:P69) -> 1605148 | BM69: - | BN69: =SUM(P69:AA69) -> 3576838 | BO69: =BN69/BL69 -> 2.228354 | BP69: =SUM(AB69:AM69) -> 4189597 | BQ69: =BP69/BN69 -> 1.171313 | BR69: =SUM(AN69:AY69) -> 1620000 | BS69: =BR69/BP69 -> 0.38667204 | BT69: =SUM(AZ69:BK69) -> 1660000 | BU69: =BT69/BR69 -> 1.0246914
C70: 〔 固定費及び変動費 〕総合計支出額 | E70: =E68+E69 -> 201303 | F70: =F68+F69 -> 204637 | G70: =G68+G69 -> 206041 | H70: =H68+H69 -> 229626 | I70: =I68+I69 -> 210893 | J70: =J68+J69 -> 270707 | K70: =K68+K69 -> 281773 | L70: =L68+L69 -> 341879 | ... BK70: =BK68+BK69 -> 299834 | BL70: =SUM(E70:P70) -> 3044090 | BM70: - | BN70: =SUM(P70:AA70) -> 5512188 | BO70: =BN70/BL70 -> 1.8107835 | BP70: =SUM(AB70:AM70) -> 6089552 | BQ70: =BP70/BN70 -> 1.1047432 | BR70: =SUM(AN70:AY70) -> 3718008 | BS70: =BR70/BP70 -> 0.61055526 | BT70: =SUM(AZ70:BK70) -> 3758008 | BU70: =BT70/BR70 -> 1.0107584
C71: 営業利益 | E71: =E23-E70 -> 103182 | F71: =F23-F70 -> 204120 | G71: =G23-G70 -> 133255 | H71: =H23-H70 -> 109138 | I71: =I23-I70 -> 107303 | J71: =J23-J70 -> 90701 | K71: =K23-K70 -> 79109 | L71: =L23-L70 -> -9093 | ... BK71: =BK23-BK70 -> 208696 | BL71: =SUM(E71:P71) -> 1128910 | BM71: - | BN71: =SUM(P71:AA71) -> 680399.72 | BO71: =BN71/BL71 -> 0.60270502 | BP71: =SUM(AB71:AM71) -> 3202007 | BQ71: =BP71/BN71 -> 4.7060675 | BR71: =SUM(AN71:AY71) -> 4565152 | BS71: =BR71/BP71 -> 1.4257158 | BT71: =SUM(AZ71:BK71) -> 2705152 | BU71: =BT71/BR71 -> 0.59256559
C72: 累積損失 | E72: 0 | F72: =E72+E71 -> 103182 | G72: =F72+F71 -> 307302 | H72: =G72+G71 -> 440557 | I72: =H72+H71 -> 549695 | J72: =I72+I71 -> 656998 | K72: =J72+J71 -> 747699 | L72: =K72+K71 -> 826808 | M72: =L72+L71 -> 817715 | ... BK72: =BJ72+BJ71 -> 12038748 | BL72: =SUM(E72:P72) -> 7503159 | BM72: - | BN72: =SUM(P72:AA72) -> 13985808 | BO72: =BN72/BL72 -> 1.8639893 | BP72: =SUM(AB72:AM72) -> 32868903 | BQ72: =BP72/BN72 -> 2.3501611 | BR72: =SUM(AN72:AY72) -> 84384200 | BS72: =BR72/BP72 -> 2.5672959 | BT72: =SUM(AZ72:BK72) -> 1.2929602e+08 | BU72: =BT72/BR72 -> 1.5322303
C74: 【キャッシュフロー】*銀行上での数字のうごき？ | E74: FY-1（2024年5月～2025年3月） | P74: FY-2（2025年4月～2026年3月） | AB74: FY-3（2026年4月～2027年3月） | AN74: FY-4（2027年4月～2028年3月） | AZ74: FY-5（2028年4月～2029年3月）
C75: 小項目 | D75: メモ | E75: 5月 | F75: 6月 | G75: 7月 | H75: 8月 | I75: 9月 | J75: 10月 | K75: 11月 | L75: 12月 | M75: 1月 | N75: 2月 | O75: 3月 | P75: 4月 | Q75: 5月 | R75: 6月 | S75: 7月 | T75: 8月 | U75: 9月 | V75: 10月 | W75: 11月 | X75: 12月 | Y75: 1月 | Z75: 2月 | AA75: 3月 | AB75: 4月 | AC75: 5月 | AD75: 6月 | AE75: 7月 | AF75: 8月 | AG75: 9月 | AH75: 10月 | AI75: 11月 | AJ75: 12月 | AK75: 1月 | AL75: 2月 | AM75: 3月 | AN75: 4月 | AO75: 5月 | AP75: 6月 | AQ75: 7月 | AR75: 8月 | AS75: 9月 | AT75: 10月 | AU75: 11月 | AV75: 12月 | AW75: 1月 | AX75: 2月 | AY75: 3月 | AZ75: 4月 | BA75: 5月 | BB75: 6月 | BC75: 7月 | BD75: 8月 | BE75: 9月 | BF75: 10月 | BG75: 11月 | BH75: 12月 | BI75: 1月 | BJ75: 2月 | BK75: 3月
C76: 残高 | D76: 合計 | E76: - | F76: - | G76: - | H76: - | I76: - | J76: - | K76: - | L76: - | M76: - | N76: - | O76: - | P76: =SUM(P77:P80) -> 109418 | Q76: =SUM(Q77:Q80) -> 163655 | R76: =SUM(R77:R80) -> 48459 | S76: =SUM(S77:S80) -> 20957 | T76: =SUM(T77:T80) -> 21010 | U76: =SUM(U77:U80) -> 25539 | V76: =SUM(V77:V80) -> 48910 | W76: =SUM(W77:W80) -> 30359 | ... BK76: =SUM(BK77:BK80) -> #REF!
D77: ①みずほ銀行／浜松町支店 | E77: - | F77: - | G77: - | H77: - | I77: - | J77: - | K77: - | L77: - | M77: - | N77: - | O77: - | P77: ='(FY-2)資産管理'!C5 -> 101400 | Q77: ='(FY-2)資産管理'!D5 -> 110380 | R77: ='(FY-2)資産管理'!E5 -> 35621 | S77: ='(FY-2)資産管理'!F5 -> 14033 | T77: ='(FY-2)資産管理'!G5 -> 13905 | U77: ='(FY-2)資産管理'!H5 -> 13900 | V77: ='(FY-2)資産管理'!I5 -> 34634 | W77: ='(FY-2)資産管理'!J5 -> 22620 | ... AA77: ='(FY-2)資産管理'!N5 -> 30684 | AB77: ='(FY-3)資産管理'!C5 -> 8 | AC77: ='(FY-3)資産管理'!D5 -> 32259 | AD77: ='(FY-3)資産管理'!E5 -> 72765 | AE77: ='(FY-3)資産管理'!F5 -> 252668 | AF77: ='(FY-3)資産管理'!G5 -> 422571 | AG77: ='(FY-3)資産管理'!H5 -> 442474 | AH77: ='(FY-3)資産管理'!I5 -> 462377 | AI77: ='(FY-3)資産管理'!J5 -> 482280 | ... AM77: ='(FY-3)資産管理'!N5 -> 561892 | AN77: =#REF!*0.4*0.25 -> #REF! | AO77: =#REF!*0.4*0.25 -> #REF! | AP77: =#REF!*0.4*0.25 -> #REF! | AQ77: =#REF!*0.4*0.25 -> #REF! | AR77: =#REF!*0.4*0.25 -> #REF! | AS77: =#REF!*0.4*0.25 -> #REF! | AT77: =#REF!*0.4*0.25 -> #REF! | AU77: =#REF!*0.4*0.25 -> #REF! | ... BK77: =#REF!*0.4*0.25 -> #REF!
D78: ②三菱UFJ銀行／国立支店 | E78: - | F78: - | G78: - | H78: - | I78: - | J78: - | K78: - | L78: - | M78: - | N78: - | O78: - | P78: ='(FY-2)資産管理'!C6 -> 8018 | Q78: ='(FY-2)資産管理'!D6 -> 53275 | R78: ='(FY-2)資産管理'!E6 -> 12838 | S78: ='(FY-2)資産管理'!F6 -> 6924 | T78: ='(FY-2)資産管理'!G6 -> 325 | U78: ='(FY-2)資産管理'!H6 -> 325 | V78: ='(FY-2)資産管理'!I6 -> 325 | W78: ='(FY-2)資産管理'!J6 -> 325 | ... AA78: ='(FY-2)資産管理'!N6 -> 0 | AB78: ='(FY-3)資産管理'!C6 -> 0 | AC78: ='(FY-3)資産管理'!D6 -> 0 | AD78: ='(FY-3)資産管理'!E6 -> 0 | AE78: ='(FY-3)資産管理'!F6 -> 0 | AF78: ='(FY-3)資産管理'!G6 -> 0 | AG78: ='(FY-3)資産管理'!H6 -> 0 | AH78: ='(FY-3)資産管理'!I6 -> 0 | AI78: ='(FY-3)資産管理'!J6 -> 0 | ... AM78: ='(FY-3)資産管理'!N6 -> 0 | AN78: =#REF!*0.4*0.25 -> #REF! | AO78: =#REF!*0.4*0.25 -> #REF! | AP78: =#REF!*0.4*0.25 -> #REF! | AQ78: =#REF!*0.4*0.25 -> #REF! | AR78: =#REF!*0.4*0.25 -> #REF! | AS78: =#REF!*0.4*0.25 -> #REF! | AT78: =#REF!*0.4*0.25 -> #REF! | AU78: =#REF!*0.4*0.25 -> #REF! | ... BK78: =#REF!*0.4*0.25 -> #REF!
D79: ③三井住友銀行／オリーブECRU(871)支店 | E79: - | F79: - | G79: - | H79: - | I79: - | J79: - | K79: - | L79: - | M79: - | N79: - | O79: - | P79: - | Q79: - | R79: - | S79: ='(FY-2)資産管理'!F7 -> 0 | T79: ='(FY-2)資産管理'!G7 -> 6780 | U79: ='(FY-2)資産管理'!H7 -> 11314 | V79: ='(FY-2)資産管理'!I7 -> 13951 | W79: ='(FY-2)資産管理'!J7 -> 7414 | X79: ='(FY-2)資産管理'!K7 -> 27387 | Y79: ='(FY-2)資産管理'!L7 -> 172576 | Z79: ='(FY-2)資産管理'!M7 -> 78526 | AA79: ='(FY-2)資産管理'!N7 -> 110842 | AB79: ='(FY-3)資産管理'!C7 -> 909 | AC79: ='(FY-3)資産管理'!D7 -> 4210 | AD79: ='(FY-3)資産管理'!E7 -> 57550 | AE79: ='(FY-3)資産管理'!F7 -> 19550 | AF79: ='(FY-3)資産管理'!G7 -> 19550 | AG79: ='(FY-3)資産管理'!H7 -> 119550 | AH79: ='(FY-3)資産管理'!I7 -> 219550 | AI79: ='(FY-3)資産管理'!J7 -> 319550 | ... AM79: ='(FY-3)資産管理'!N7 -> 719550 | AN79: =#REF!*0.4*0.25 -> #REF! | AO79: =#REF!*0.4*0.25 -> #REF! | AP79: =#REF!*0.4*0.25 -> #REF! | AQ79: =#REF!*0.4*0.25 -> #REF! | AR79: =#REF!*0.4*0.25 -> #REF! | AS79: =#REF!*0.4*0.25 -> #REF! | AT79: =#REF!*0.4*0.25 -> #REF! | AU79: =#REF!*0.4*0.25 -> #REF! | ... BK79: =#REF!*0.4*0.25 -> #REF!
D80: ④楽天銀行／ベース支店 | E80: - | F80: - | G80: - | H80: - | I80: - | J80: - | K80: - | L80: - | M80: - | N80: - | O80: - | P80: - | Q80: - | R80: - | S80: - | T80: - | U80: - | V80: - | W80: - | X80: - | Y80: - | Z80: - | AA80: - | AB80: ='(FY-3)資産管理'!C8 -> 14 | AC80: ='(FY-3)資産管理'!D8 -> 17391 | AD80: ='(FY-3)資産管理'!E8 -> 20873 | AE80: ='(FY-3)資産管理'!F8 -> 20873 | AF80: ='(FY-3)資産管理'!G8 -> 20873 | AG80: ='(FY-3)資産管理'!H8 -> 20873 | AH80: ='(FY-3)資産管理'!I8 -> 20873 | AI80: ='(FY-3)資産管理'!J8 -> 20873 | ... AM80: ='(FY-3)資産管理'!N8 -> 20873 | AN80: / | AO80: / | AP80: / | AQ80: / | AR80: / | AS80: / | AT80: / | AU80: / | AV80: / | AW80: / | AX80: / | AY80: / | AZ80: / | BA80: / | BB80: / | BC80: / | BD80: / | BE80: / | BF80: / | BG80: / | BH80: / | BI80: / | BJ80: / | BK80: /
C81: 出金 | D81: 合計 | E81: - | F81: - | G81: - | H81: - | I81: - | J81: - | K81: - | L81: - | M81: - | N81: - | O81: - | P81: =SUM(P82:P84) -> 244149 | Q81: =SUM(Q82:Q84) -> 375700 | R81: =SUM(R82:R84) -> 319587 | S81: =SUM(S82:S84) -> 284587 | T81: =SUM(T82:T84) -> 294807 | U81: =SUM(U82:U84) -> 319049 | V81: =SUM(V82:V84) -> 300600 | W81: =SUM(W82:W84) -> 382816 | ... BK81: =SUM(BK82:BK84) -> 129987
D82: 家賃（27日にみずほ銀行から引落し） | E82: - | F82: - | G82: - | H82: - | I82: - | J82: - | K82: - | L82: - | M82: - | N82: - | O82: - | P82: 59149 | Q82: 88700 | R82: 89587 | S82: 89587 | T82: 89587 | U82: 89587 | V82: 89587 | W82: 129987 | X82: 129987 | Y82: 129987 | Z82: 129987 | AA82: 129987 | AB82: 129987 | AC82: 129987 | AD82: 129987 | AE82: 129987 | AF82: 129987 | AG82: 129987 | AH82: 129987 | AI82: 129987 | AJ82: 129987 | AK82: 129987 | AL82: 129987 | AM82: 129987 | AN82: 129987 | AO82: 129987 | AP82: 129987 | AQ82: 129987 | AR82: 129987 | AS82: 129987 | AT82: 129987 | AU82: 129987 | AV82: 129987 | AW82: 129987 | AX82: 129987 | AY82: 129987 | AZ82: 129987 | BA82: 129987 | BB82: 129987 | BC82: 129987 | BD82: 129987 | BE82: 129987 | BF82: 129987 | BG82: 129987 | BH82: 129987 | BI82: 129987 | BJ82: 129987 | BK82: 129987
D83: iDeCo（27日にみずほ銀行から引落し） | E83: - | F83: - | G83: - | H83: - | I83: - | J83: - | K83: - | L83: - | M83: - | N83: - | O83: -
D84: クレカ（27日に三井住友銀行から引落し） | E84: - | F84: - | G84: - | H84: - | I84: - | J84: - | K84: - | L84: - | M84: - | N84: - | O84: - | P84: ='クレカ '!C34 -> 185000 | Q84: ='クレカ '!C66 -> 287000 | R84: ='クレカ '!C97 -> 230000 | S84: ='クレカ '!C129 -> 195000 | T84: ='クレカ '!C160 -> 205220 | U84: ='クレカ '!C196 -> 229462 | V84: ='クレカ '!C227 -> 211013 | W84: ='クレカ '!C259 -> 252829 | X84: ='クレカ '!C290 -> 230469 | Y84: ='クレカ '!C322 -> 389835 | Z84: ='クレカ '!C354 -> 500600 | AA84: ='クレカ '!C383 -> 580495 | AB84: ='クレカ '!C415 -> 459296 | AC84: ='クレカ '!C446 -> 290883 | AD84: ='クレカ '!C478 -> 240000 | AE84: ='クレカ '!C509 -> 250000 | AF84: ='クレカ '!C541 -> 153484 | AG84: ='クレカ '!C573 -> 52895 | AH84: ='クレカ '!C604 -> 52895 | AI84: ='クレカ '!C636 -> 40700 | AJ84: ='クレカ '!C667 -> 40700 | AK84: ='クレカ '!C699 -> 40700 | AL84: ='クレカ '!C731 -> 40700 | AM84: ='クレカ '!C760 -> 0 | AN84: 0 | AO84: 0 | AP84: 0 | AQ84: 0 | AR84: 0 | AS84: 0 | AT84: 0 | AU84: 0 | AV84: 0 | AW84: 0 | AX84: 0 | AY84: 0 | AZ84: 0 | BA84: 0 | BB84: 0 | BC84: 0 | BD84: 0 | BE84: 0 | BF84: 0 | BG84: 0 | BH84: 0 | BI84: 0 | BJ84: 0 | BK84: 0
C85: 銀行借入れ | D85: 当月
D86: 借入元金 | U86: =T86+U85-T87 -> 0 | V86: =U86+V85-U87 -> 0 | W86: =V86+W85-V87 -> 0 | X86: =W86+X85-W87 -> 0 | Y86: =X86+Y85-X87 -> 0 | Z86: =Y86+Z85-Y87 -> 0 | AA86: =Z86+AA85-Z87 -> 0 | AB86: =AA86+AB85-AA87 -> 0 | ... BK86: =BJ86+BK85-BJ87 -> 0
C87: 返済金額 | D87: 5年借入 | U87: =U86/60 -> 0 | V87: =V86/60 -> 0 | W87: =W86/60 -> 0 | X87: =X86/60 -> 0 | Y87: =Y86/60 -> 0 | Z87: =Z86/60 -> 0 | AA87: =AA86/60 -> 0 | AB87: =AB86/60 -> 0 | ... BK87: =BK86/60 -> 0
C88: 返済利子 | D88: 0.03 | U88: =U86*3% -> 0 | V88: =V86*3% -> 0 | W88: =W86*3% -> 0 | X88: =X86*3% -> 0 | Y88: =Y86*3% -> 0 | Z88: =Z86*3% -> 0 | AA88: =AA86*3% -> 0 | AB88: =AB86*3% -> 0 | ... BK88: =BK86*3% -> 0
C89: 残高 | D89: 1ｗeek※未整備 | U89: =T92-U77 -> -13900 | V89: =U92-V77 -> #VALUE! | W89: =V92-W77 -> #VALUE! | X89: =W92-X77 -> #VALUE! | Y89: =X92-Y77 -> #VALUE! | Z89: =Y92-Z77 -> #VALUE! | AA89: =Z92-AA77 -> #VALUE! | AB89: =AA92-AB77 -> #VALUE! | ... BK89: =BJ92-BK77 -> #VALUE!
D90: 2ｗeek※未整備 | U90: =U89-U78 -> -14225 | V90: =V89-V78 -> #VALUE! | W90: =W89-W78 -> #VALUE! | X90: =X89-X78 -> #VALUE! | Y90: =Y89-Y78 -> #VALUE! | Z90: =Z89-Z78 -> #VALUE! | AA90: =AA89-AA78 -> #VALUE! | AB90: =AB89-AB78 -> #VALUE! | ... BK90: =BK89-BK78 -> #VALUE!
D91: 3ｗeek※未整備 | U91: =U90-U79-U84 -> -255001 | V91: =V90-V79-V84 -> #VALUE! | W91: =W90-W79-W84 -> #VALUE! | X91: =X90-X79-X84 -> #VALUE! | Y91: =Y90-Y79-Y84 -> #VALUE! | Z91: =Z90-Z79-Z84 -> #VALUE! | AA91: =AA90-AA79-AA84 -> #VALUE! | AB91: =AB90-AB79-AB84 -> #VALUE! | ... BK91: =BK90-BK79-BK84 -> #VALUE!
D92: 月末※未整備 | U92: =U91-U80-#REF!-#REF!+(U85-U87-U88)+T76 -> #VALUE! | V92: =V91-V80-#REF!-#REF!+(V85-V87-V88)+U76 -> #VALUE! | W92: =W91-W80-#REF!-#REF!+(W85-W87-W88)+V76 -> #VALUE! | X92: =X91-X80-#REF!-#REF!+(X85-X87-X88)+W76 -> #VALUE! | Y92: =Y91-Y80-#REF!-#REF!+(Y85-Y87-Y88)+X76 -> #VALUE! | Z92: =Z91-Z80-#REF!-#REF!+(Z85-Z87-Z88)+Y76 -> #VALUE! | AA92: =AA91-AA80-#REF!-#REF!+(AA85-AA87-AA88)+Z76 -> #VALUE! | AB92: =AB91-AB80-#REF!-#REF!+(AB85-AB87-AB88)+AA76 -> #VALUE! | ... BK92: =BK91-BK80-#REF!-#REF!+(BK85-BK87-BK88)+BJ76 -> #VALUE!

Sheet FY-1(月次)支出予実
C1: 予測 | D1: 予測 | E1: 予測 | F1: 予測 | G1: ※確定 | H1: ※確定 | I1: ※確定 | J1: ※確定 | K1: ※確定 | L1: ※確定 | M1: ※確定 | N1: ※確定
B2: 支出 | C2: 45413 | D2: 45444 | E2: 45474 | F2: 45505 | G2: 45536 | H2: 45566 | I2: 45597 | J2: 45627 | K2: 45658 | L2: 45689 | M2: 45717 | N2: 45748 | O2: 合計 | P2: 平均
A3: ALL | B3: 合算費用 | C3: =C4+C20+C28+C37+C42+C52 -> 201303 | D3: =D4+D20+D28+D37+D42+D52 -> 204637 | E3: =E4+E20+E28+E37+E42+E52 -> 206041 | F3: =F4+F20+F28+F37+F42+F52 -> 229626 | G3: =G4+G20+G28+G37+G42+G52 -> 210893 | H3: =H4+H20+H28+H37+H42+H52 -> 270707 | I3: =I4+I20+I28+I37+I42+I52 -> 281773 | J3: =J4+J20+J28+J37+J42+J52 -> 341879 | ... N3: =N4+N20+N28+N37+N42+N52 -> 330716 | O3: =SUM(C3:N3) -> 3046227 | P3: =IFERROR(AVERAGE(C3:N3),"") -> 253852.25
A4: 固定費 | B4: 【固定費】月次合計: | C4: =SUM(C6:C19) -> 118303 | D4: =SUM(D6:D19) -> 119837 | E4: =SUM(E6:E19) -> 119841 | F4: =SUM(F6:F19) -> 119187 | G4: =SUM(G6:G19) -> 118877 | H4: =SUM(H6:H19) -> 121239 | I4: =SUM(I6:I19) -> 121417 | J4: =SUM(J6:J19) -> 123063 | ... N4: =SUM(N6:N19) -> 108219 | O4: =SUM(C4:N4) -> 1440752 | P4: =IFERROR(AVERAGE(C4:N4),"") -> 120062.67
B5: 収入(手取り)に対する比率 | C5: #REF! | D5: #REF! | E5: #REF! | F5: #REF! | G5: #REF! | H5: #REF! | I5: #REF! | J5: #REF! | K5: #REF! | L5: #REF! | M5: #REF! | N5: #REF! | O5: #REF! | P5: #REF!
A6: ☑ | B6: 生命保険料(プルデンシャル) | C6: 9307 | D6: 9307 | E6: 9307 | F6: 9307 | G6: 9307 | H6: 9307 | I6: 9307 | J6: 9307 | K6: 9307 | L6: 9307 | M6: 9307 | N6: 9307 | O6: =SUM(C6:N6) -> 111684 | P6: =IFERROR(AVERAGE(C6:N6), "¥0") -> 9307
A7: ☑ | B7: ジム(東急スポーツオアシス) | C7: 9680 | D7: 9680 | E7: 9680 | F7: 9680 | G7: 9680 | H7: 9680 | I7: 9680 | J7: 9680 | K7: 9680 | L7: 12980 | M7: 12980 | N7: 0 | O7: =SUM(C7:N7) -> 113080 | P7: =IFERROR(AVERAGE(C7:N7), "¥0") -> 9423.3333
A8: ☑ | B8: 家賃(TERMINALS高槻)※水道光熱費込み | C8: 60682 | D8: 62216 | E8: 62216 | F8: 62216 | G8: 62216 | H8: 62216 | I8: 62216 | J8: 65516 | K8: 62216 | L8: 62216 | M8: 62216 | N8: 59149 | O8: =SUM(C8:N8) -> 745291 | P8: =IFERROR(AVERAGE(C8:N8), "¥0") -> 62107.583
A9: ☑ | B9: 脱毛支払い(プラム) | C9: 11400 | D9: 11400 | E9: 11400 | F9: 11400 | G9: 11400 | H9: 11400 | I9: 11400 | J9: 11400 | K9: 11400 | L9: 11400 | M9: 11400 | N9: 11400 | O9: =SUM(C9:N9) -> 136800 | P9: =IFERROR(AVERAGE(C9:N9), "¥0") -> 11400
A10: ☑ | B10: しがく会費 | C10: 3300 | D10: 3300 | E10: 3300 | F10: 3300 | G10: 3300 | H10: 3300 | I10: 3300 | J10: 3300 | K10: 3300 | L10: 3300 | M10: 3300 | N10: 330 | O10: =SUM(C10:N10) -> 36630 | P10: =IFERROR(AVERAGE(C10:N10), "¥0") -> 3052.5
A11: ☑ | B11: 携帯料金(SB)＋YouTubeプレミアム(￥870) | C11: 11554 | D11: 11554 | E11: 11558 | F11: 10904 | G11: 11554 | H11: 11576 | I11: 11554 | J11: 11580 | K11: 11554 | L11: 12533 | M11: 12533 | N11: 12753 | O11: =SUM(C11:N11) -> 141207 | P11: =IFERROR(AVERAGE(C11:N11), "¥0") -> 11767.25
A12: ☑ | B12: iCloud拡張会費 | C12: 450 | D12: 450 | E12: 450 | F12: 450 | G12: 450 | H12: 450 | I12: 450 | J12: 450 | K12: 450 | L12: 450 | M12: 450 | N12: 450 | O12: =SUM(C12:N12) -> 5400 | P12: =IFERROR(AVERAGE(C12:N12), "¥0") -> 450
A13: ☑ | B13: Netflix | C13: 990 | D13: 990 | E13: 990 | F13: 990 | G13: 990 | H13: 990 | I13: 1190 | J13: 1190 | K13: 1190 | L13: 1190 | M13: 1190 | N13: 1190 | O13: =SUM(C13:N13) -> 13080 | P13: =IFERROR(AVERAGE(C13:N13), "¥0") -> 1090
A14: ☑ | B14: Amazon Prime | C14: 600 | D14: 600 | E14: 600 | F14: 600 | G14: 600 | H14: 600 | I14: 600 | J14: 600 | K14: 600 | L14: 600 | M14: 600 | N14: 600 | O14: =SUM(C14:N14) -> 7200 | P14: =IFERROR(AVERAGE(C14:N14), "¥0") -> 600
A15: ☑ | B15: テレ東BIZ | C15: 550 | D15: 550 | E15: 550 | F15: 550 | G15: 550 | H15: 1210 | I15: 1210 | J15: 1210 | K15: 1210 | L15: 1210 | M15: 1210 | N15: 1210 | O15: =SUM(C15:N15) -> 11220 | P15: =IFERROR(AVERAGE(C15:N15), "¥0") -> 935
A16: ☑ | B16: 定期券代 | C16: 8830 | D16: 8830 | E16: 8830 | F16: 8830 | G16: 8830 | H16: 8830 | I16: 8830 | J16: 8830 | K16: 8830 | L16: 8830 | M16: 8830 | N16: 8830 | O16: =SUM(C16:N16) -> 105960 | P16: =IFERROR(AVERAGE(C16:N16), "¥0") -> 8830
A17: ☑ | B17: chat gptプラス | C17: 0 | D17: 0 | E17: 0 | F17: 0 | G17: 0 | H17: 0 | I17: 0 | J17: 0 | K17: 0 | L17: 0 | M17: 3000 | N17: 3000 | O17: =SUM(C17:N17) -> 6000
A18: ☑ | B18: Abemaプレミアム | C18: 960 | D18: 960 | E18: 960 | F18: 960 | G18: 0 | H18: 0 | I18: 0 | J18: 0 | K18: 0 | L18: 0 | M18: 0 | N18: 0 | O18: =SUM(C18:N18) -> 3840 | P18: =IFERROR(AVERAGE(C18:N18), "¥0") -> 320
A19: ☑ | B19: YouTubeプレミアム | C19: 0 | D19: 0 | E19: 0 | F19: 0 | G19: 0 | H19: 1680 | I19: 1680 | J19: 0 | K19: 0 | L19: 0 | M19: 0 | N19: 0 | O19: =SUM(C19:N19) -> 3360 | P19: =IFERROR(AVERAGE(C19:N19), "¥0") -> 280
A20: 食費（経費以外） | B20: 月次合計: | C20: =SUM(C22:C26) -> 72000 | D20: =SUM(D22:D26) -> 72000 | E20: =SUM(E22:E26) -> 72000 | F20: =SUM(F22:F26) -> 72000 | G20: =SUM(G22:G26) -> 69266 | H20: =SUM(H22:H26) -> 86352 | I20: =SUM(I22:I26) -> 126556 | J20: =SUM(J22:J26) -> 80424 | ... N20: =SUM(N22:N26) -> 91748 | O20: =SUM(C20:N20) -> 987954 | P20: =IFERROR(AVERAGE(C20:N20),"") -> 82329.5
B21: 収入(手取り)に対する比率 | C21: #REF! | D21: #REF! | E21: #REF! | F21: #REF! | G21: #REF! | H21: #REF! | I21: #REF! | J21: #REF! | K21: #REF! | L21: #REF! | M21: #REF! | N21: #REF! | O21: #REF! | P21: #REF!
A22: ☑ | B22: 食費（1人） | C22: 30000 | D22: 30000 | E22: 30000 | F22: 30000 | G22: 21794 | H22: 35277 | I22: 34563 | J22: 40123 | K22: 41837 | L22: 40335 | M22: 32269 | N22: 36623 | O22: =SUM(C22:N22) -> 402821 | P22: =IFERROR(AVERAGE(C22:N22), "¥0") -> 33568.417
A23: ☑ | B23: ①交際費（誰かと飲み・ごはん） | C23: 30000 | D23: 30000 | E23: 30000 | F23: 30000 | G23: 30060 | H23: 32882 | I23: 71562 | J23: 23549 | K23: 24103 | L23: 24208 | M23: 29262 | N23: 44765 | O23: =SUM(C23:N23) -> 400391 | P23: =IFERROR(AVERAGE(C23:N23), "¥0") -> 33365.917
A24: ☑ | B24: ③温泉費用（館内での飲食含む） | C24: 3000 | D24: 3000 | E24: 3000 | F24: 3000 | G24: 820 | H24: 0 | I24: 3228 | J24: 0 | K24: 2960 | L24: 4237 | M24: 0 | N24: 600 | O24: =SUM(C24:N24) -> 23845 | P24: =IFERROR(AVERAGE(C24:N24), "¥0") -> 1987.0833
A25: ☑ | B25: タバコ | C25: 5000 | D25: 5000 | E25: 5000 | F25: 5000 | G25: 7480 | H25: 7320 | I25: 6910 | J25: 7090 | K25: 6487 | L25: 7880 | M25: 7730 | N25: 9760 | O25: =SUM(C25:N25) -> 80657 | P25: =IFERROR(AVERAGE(C25:N25), "¥0") -> 6721.4167
A26: ☑ | B26: スーパー購入費 | C26: 4000 | D26: 4000 | E26: 4000 | F26: 4000 | G26: 9112 | H26: 10873 | I26: 10293 | J26: 9662 | K26: 4006 | L26: 9188 | M26: 11106 | N26: 0 | O26: =SUM(C26:N26) -> 80240 | P26: =IFERROR(AVERAGE(C26:N26), "¥0") -> 6686.6667
B27: ①交際費+②旅行費 | C27: =C23+C33 -> 30000 | D27: =D23+D33 -> 30000 | E27: =E23+E33 -> 30000 | F27: =F23+F33 -> 30000 | G27: =G23+G33 -> 30060 | H27: =H23+H33 -> 41848 | I27: =I23+I33 -> 71562 | J27: =J23+J33 -> 100887 | ... P27: =P23+P33 -> 41805.417
A28: 娯楽費 | B28: 月次合計: | C28: =SUM(C30:C35) -> 5000 | D28: =SUM(D30:D35) -> 6800 | E28: =SUM(E30:E35) -> 13200 | F28: =SUM(F30:F35) -> 14100 | G28: =SUM(G30:G35) -> 9399 | H28: =SUM(H30:H35) -> 36497 | I28: =SUM(I30:I35) -> 10281 | J28: =SUM(J30:J35) -> 99467 | ... N28: =SUM(N30:N35) -> 48284 | O28: =SUM(C28:N28) -> 327235 | P28: =IFERROR(AVERAGE(C28:N28),"") -> 27269.583
B29: 収入(手取り)に対する比率 | C29: #REF! | D29: #REF! | E29: #REF! | F29: #REF! | G29: #REF! | H29: #REF! | I29: #REF! | J29: #REF! | K29: #REF! | L29: #REF! | M29: #REF! | N29: #REF! | O29: #REF! | P29: #REF!
A30: ☑ | B30: ⑩映画・ドラマ（netflixの固定費以外） | C30: 0 | D30: 0 | E30: 200 | F30: 0 | G30: 0 | H30: 0 | I30: 0 | J30: 0 | K30: 0 | L30: 0 | M30: 0 | N30: 0 | O30: =SUM(C30:N30) -> 200 | P30: =IFERROR(AVERAGE(C30:N30), "¥0") -> 16.666667
A31: ☑ | B31: ⑨ライブ・スポーツ観戦など（ex,甲子園） | C31: 0 | D31: 1800 | E31: 8000 | F31: 5100 | G31: 7253 | H31: 25360 | I31: 0 | J31: 1995 | K31: 0 | L31: 0 | M31: 17426 | N31: 0 | O31: =SUM(C31:N31) -> 66934 | P31: =IFERROR(AVERAGE(C31:N31), "¥0") -> 5577.8333
A32: ☑ | B32: ⑦香水・フレグランス | C32: 5000 | D32: 5000 | E32: 5000 | F32: 5000 | G32: 0 | H32: 0 | I32: 4510 | J32: 0 | K32: 0 | L32: 0 | M32: 0 | N32: 0 | O32: =SUM(C32:N32) -> 24510 | P32: =IFERROR(AVERAGE(C32:N32), "¥0") -> 2042.5
A33: ☑ | B33: ②旅行費（名古屋・有馬・富士急など） | C33: 0 | D33: 0 | E33: 0 | F33: 0 | G33: 0 | H33: 8966 | I33: 0 | J33: 77338 | K33: 14970 | L33: 0 | M33: 0 | N33: 0 | O33: =SUM(C33:N33) -> 101274 | P33: =IFERROR(AVERAGE(C33:N33), "¥0") -> 8439.5
A34: ☑ | B34: プレゼント・おごりなど | C34: 0 | D34: 0 | E34: 0 | F34: 4000 | G34: 2146 | H34: 2171 | I34: 5771 | J34: 20134 | K34: 37436 | L34: 5801 | M34: 8574 | N34: 4397 | O34: =SUM(C34:N34) -> 90430 | P34: =IFERROR(AVERAGE(C34:N34), "¥0") -> 7535.8333
A35: ☑ | B35: 結婚式 | C35: 0 | D35: 0 | E35: 0 | F35: 0 | G35: 0 | H35: 0 | I35: 0 | J35: 0 | K35: 0 | L35: 0 | M35: 0 | N35: 43887 | O35: =SUM(C35:N35) -> 43887 | P35: =IFERROR(AVERAGE(C35:N35), "¥0") -> 3657.25
B36: 1人体験(運動,散髪,グリーン車,1人映画鑑賞) ③温泉費用+④体験+⑤散髪+⑨ライブ・スポーツ | C36: =C24+C40+C41+C31 -> 8000 | D36: =D24+D40+D41+D31 -> 9800 | E36: =E24+E40+E41+E31 -> 11000 | F36: =F24+F40+F41+F31 -> 8100 | G36: =G24+G40+G41+G31 -> 8073 | H36: =H24+H40+H41+H31 -> 28860 | I36: =I24+I40+I41+I31 -> 12688 | J36: =J24+J40+J41+J31 -> 11652 | ... P36: =P24+P40+P41+P31 -> 12488
A37: 自己投資 | B37: 月次合計: | C37: =SUM(C39:C41) -> 5000 | D37: =SUM(D39:D41) -> 5000 | E37: =SUM(E39:E41) -> 0 | F37: =SUM(F39:F41) -> 0 | G37: =SUM(G39:G41) -> 0 | H37: =SUM(H39:H41) -> 3500 | I37: =SUM(I39:I41) -> 10780 | J37: =SUM(J39:J41) -> 16477 | ... N37: =SUM(N39:N41) -> 3800 | O37: =SUM(C37:N37) -> 77777 | P37: =IFERROR(AVERAGE(C37:N37),"") -> 6481.4167
B38: 収入(手取り)に対する比率 | C38: #REF! | D38: #REF! | E38: #REF! | F38: #REF! | G38: #REF! | H38: #REF! | I38: #REF! | J38: #REF! | K38: #REF! | L38: #REF! | M38: #REF! | N38: #REF! | O38: #REF! | P38: #REF!
A39: ☑ | B39: ⑧本・セミナー・イベントなど | C39: 0 | D39: 0 | E39: 0 | F39: 0 | G39: 0 | H39: 0 | I39: 1320 | J39: 6820 | K39: 1650 | L39: 0 | M39: 8910 | N39: 0 | O39: =SUM(C39:N39) -> 18700 | P39: =IFERROR(AVERAGE(C39:N39), "¥0") -> 1558.3333
A40: ☑ | B40: ④体験(グリーン車やホテル,個サルや運動など) | C40: 0 | D40: 0 | E40: 0 | F40: 0 | G40: 0 | H40: 0 | I40: 5960 | J40: 8157 | K40: 7000 | L40: 8860 | M40: 0 | N40: 0 | O40: =SUM(C40:N40) -> 29977 | P40: =IFERROR(AVERAGE(C40:N40), "¥0") -> 2498.0833
A41: ☑ | B41: ⑤散髪 | C41: 5000 | D41: 5000 | E41: 0 | F41: 0 | G41: 0 | H41: 3500 | I41: 3500 | J41: 1500 | K41: 3300 | L41: 3500 | M41: 0 | N41: 3800 | O41: =SUM(C41:N41) -> 29100 | P41: =IFERROR(AVERAGE(C41:N41), "¥0") -> 2425
A42: 諸経費・備品 | B42: 月次合計: | C42: =SUM(C44:C46) -> 1000 | D42: =SUM(D44:D46) -> 1000 | E42: =SUM(E44:E46) -> 1000 | F42: =SUM(F44:F46) -> 24339 | G42: =SUM(G44:G46) -> 13351 | H42: =SUM(H44:H46) -> 23119 | I42: =SUM(I44:I46) -> 12739 | J42: =SUM(J44:J46) -> 22448 | ... N42: =SUM(N44:N46) -> 78665 | O42: =SUM(C42:N42) -> 212509 | P42: =IFERROR(AVERAGE(C42:N42),"") -> 17709.083
B43: 収入(手取り)に対する比率 | C43: #REF! | D43: #REF! | E43: #REF! | F43: #REF! | G43: #REF! | H43: #REF! | I43: #REF! | J43: #REF! | K43: #REF! | L43: #REF! | M43: #REF! | N43: #REF! | O43: #REF! | P43: #REF!
A44: ☑ | B44: 旅費・交通費(交通系ICと新幹線代)※経費以外 | C44: 1000 | D44: 1000 | E44: 1000 | F44: 1000 | G44: 1000 | H44: 1000 | I44: 1000 | J44: 1000 | K44: 1000 | L44: 1000 | M44: 1000 | N44: 29173 | O44: =SUM(C44:N44) -> 40173 | P44: =IFERROR(AVERAGE(C44:N44), "¥0") -> 3347.75
A45: ☑ | B45: ⑥物品購入費(衣類・家具・髭剃りなど生活用品) | C45: 0 | D45: 0 | E45: 0 | F45: 16339 | G45: 12351 | H45: 22119 | I45: 11739 | J45: 21448 | K45: 5350 | L45: 6233 | M45: 17705 | N45: 49492 | O45: =SUM(C45:N45) -> 162776 | P45: =IFERROR(AVERAGE(C45:N45), "¥0") -> 13564.667
A46: ☑ | B46: その他諸経費(処分費用・病院費用・荷造運賃) | C46: 0 | D46: 0 | E46: 0 | F46: 7000 | G46: 0 | H46: 0 | I46: 0 | J46: 0 | K46: 0 | L46: 0 | M46: 2560 | N46: 0 | O46: =SUM(C46:N46) -> 9560 | P46: =IFERROR(AVERAGE(C46:N46), "¥0") -> 796.66667
B47: 物品購入費 ⑥物品購入+⑦香水・フレグランス ⑧本・セミナー+⑩映画・ドラマ | C47: =C45+C32+C39+C30 -> 5000 | D47: =D45+D32+D39+D30 -> 5000 | E47: =E45+E32+E39+E30 -> 5200 | F47: =F45+F32+F39+F30 -> 21339 | G47: =G45+G32+G39+G30 -> 12351 | H47: =H45+H32+H39+H30 -> 22119 | I47: =I45+I32+I39+I30 -> 17569 | J47: =J45+J32+J39+J30 -> 28268 | ... P47: =P45+P32+P39+P30 -> 17182.167
A48: 利子(ALLの計算式からは抜いている) | B48: 月次合計: | C48: =SUM(C50:C51) -> 0 | D48: =SUM(D50:D51) -> 0 | E48: =SUM(E50:E51) -> 110000 | F48: =SUM(F50:F51) -> 110000 | G48: =SUM(G50:G51) -> 110000 | H48: =SUM(H50:H51) -> 110000 | I48: =SUM(I50:I51) -> 110000 | J48: =SUM(J50:J51) -> 110000 | ... N48: =SUM(N50:N51) -> 110000 | O48: =SUM(C48:N48) -> 1100000 | P48: =IFERROR(AVERAGE(C48:N48),"") -> 91666.667
B49: 収入(手取り)に対する比率 | C49: #REF! | D49: #REF! | E49: #REF! | F49: #REF! | G49: #REF! | H49: #REF! | I49: #REF! | J49: #REF! | K49: #REF! | L49: #REF! | M49: #REF! | N49: #REF! | O49: #REF! | P49: #REF!
A50: 実数値取れないので感覚☑ | B50: ①元金返済金額 | C50: 0 | D50: 0 | E50: 100000 | F50: 100000 | G50: 100000 | H50: 100000 | I50: 100000 | J50: 100000 | K50: 100000 | L50: 100000 | M50: 100000 | N50: 100000 | O50: =SUM(C50:N50) -> 1000000 | P50: =IFERROR(AVERAGE(C50:N50), "¥0") -> 83333.333
A51: ※100万払って利息12万☑ | B51: ②返済利子 | C51: 0 | D51: 0 | E51: 10000 | F51: 10000 | G51: 10000 | H51: 10000 | I51: 10000 | J51: 10000 | K51: 10000 | L51: 10000 | M51: 10000 | N51: 10000 | O51: =SUM(C51:N51) -> 100000 | P51: =IFERROR(AVERAGE(C51:N51), "¥0") -> 8333.3333
A52: 税金※月次収入タブ参照 | B52: 月次合計: | C52: =SUM(C54:C55) -> 0 | D52: =SUM(D54:D55) -> 0 | E52: =SUM(E54:E55) -> 0 | F52: =SUM(F54:F55) -> 0 | G52: =SUM(G54:G55) -> 0 | H52: =SUM(H54:H55) -> 0 | I52: =SUM(I54:I55) -> 0 | J52: =SUM(J54:J55) -> 0 | ... N52: =SUM(N54:N55) -> 0 | O52: =SUM(C52:N52) -> 0 | P52: =IFERROR(AVERAGE(C52:N52),"") -> 0
B53: 収入(手取り)に対する比率 | C53: #REF! | D53: #REF! | E53: #REF! | F53: #REF! | G53: #REF! | H53: #REF! | I53: #REF! | J53: #REF! | K53: #REF! | L53: #REF! | M53: #REF! | N53: #REF! | O53: #REF! | P53: #REF!
B54: 住民税(給与天引きに含む為計上なし) | C54: 0 | D54: 0 | E54: 0 | F54: 0 | G54: 0 | H54: 0 | I54: 0 | J54: 0 | K54: 0 | L54: 0 | M54: 0 | N54: 0 | O54: =SUM(C54:N54) -> 0 | P54: =IFERROR(AVERAGE(C54:N54), "¥0") -> 0
B55: 社会保険料(給与天引きに含む為計上なし) | C55: 0 | D55: 0 | E55: 0 | F55: 0 | G55: 0 | H55: 0 | I55: 0 | J55: 0 | K55: 0 | L55: 0 | M55: 0 | N55: 0 | O55: =SUM(C55:N55) -> 0 | P55: =IFERROR(AVERAGE(C55:N55), "¥0") -> 0

Sheet FY-1(月次)収入予実
F1: ※確定 | G1: ※確定 | H1: ※確定 | I1: ※確定 | J1: ※確定 | K1: ※確定 | L1: ※確定 | M1: ※確定 | N1: ※確定 | O1: ※確定 | P1: ※確定 | Q1: ※確定
E2: 収入 | F2: 45413 | G2: 45444 | H2: 45474 | I2: 45505 | J2: 45536 | K2: 45566 | L2: 45597 | M2: 45627 | N2: 45658 | O2: 45689 | P2: 45717 | Q2: 45748 | R2: 合計 | S2: 平均
B3: 収入 | E3: 月次合計: | F3: =SUM(F4:F8) -> 304485 | G3: =SUM(G4:G8) -> 408757 | H3: =SUM(H4:H8) -> 339296 | I3: =SUM(I4:I8) -> 338764 | J3: =SUM(J4:J8) -> 318196 | K3: =SUM(K4:K8) -> 361408 | L3: =SUM(L4:L8) -> 360882 | M3: =SUM(M4:M8) -> 332786 | ... Q3: =SUM(Q4:Q8) -> 362471 | R3: =SUM(F3:Q3) -> 4172715 | S3: =IFERROR(AVERAGE(F3:Q3),"") -> 347726.25
E4: 給与収入※控除後の手取り | F4: =F9-F10 -> 292485 | G4: =G9-G10 -> 408757 | H4: =H9-H10 -> 327296 | I4: =I9-I10 -> 336764 | J4: =J9-J10 -> 316196 | K4: =K9-K10 -> 347408 | L4: =L9-L10 -> 358882 | M4: =M9-M10 -> 330786 | ... Q4: =Q9-Q10 -> 347771 | R4: =SUM(F4:Q4) -> 4052675 | S4: =IFERROR(AVERAGE(F4:Q4), "¥0") -> 337722.92
B5: ☑ | E5: 経費精算➡支出にも入れていなかったので計上無し
B6: ☑ | E6: TikTokポイント収入 | F6: 2000 | G6: 0 | H6: 2000 | I6: 2000 | J6: 2000 | K6: 4000 | L6: 2000 | M6: 2000 | N6: 1800 | O6: 0 | P6: 0 | Q6: 2700 | R6: =SUM(F6:Q6) -> 20500 | S6: =IFERROR(AVERAGE(F6:Q6), "¥0") -> 1708.3333
B7: ☑ | E7: 家族収入 | F7: 10000 | G7: 0 | H7: 10000 | I7: 0 | J7: 0 | K7: 10000 | L7: 0 | M7: 0 | N7: 50000 | O7: 0 | P7: 0 | Q7: 0 | R7: =SUM(F7:Q7) -> 80000 | S7: =IFERROR(AVERAGE(F7:Q7), "¥0") -> 6666.6667
B8: ☑ | E8: その他収益 | F8: 0 | G8: 0 | H8: 0 | I8: 0 | J8: 0 | K8: 0 | L8: 0 | M8: 0 | N8: 500 | O8: 7040 | P8: 0 | Q8: 12000 | R8: =SUM(F8:Q8) -> 19540 | S8: =IFERROR(AVERAGE(F8:Q8), "¥0") -> 1628.3333
B9: ☑ | E9: 総支給額 | F9: 353933 | G9: 462436 | H9: 400000 | I9: 422000 | J9: 400000 | K9: 438020 | L9: 454000 | M9: 400000 | N9: 400000 | O9: 463000 | P9: 400000 | Q9: 438020 | R9: =SUM(F9:Q9) -> 5031409 | S9: =IFERROR(AVERAGE(F9:Q9), "¥0") -> 419284.08
B10: 控除額内訳 | E10: 月次合計: | F10: =SUM(F11:F18) -> 61448 | G10: =SUM(G11:G18) -> 53679 | H10: =SUM(H11:H18) -> 72704 | I10: =SUM(I11:I18) -> 85236 | J10: =SUM(J11:J18) -> 83804 | K10: =SUM(K11:K18) -> 90612 | L10: =SUM(L11:L18) -> 95118 | M10: =SUM(M11:M18) -> 69214 | ... Q10: =SUM(Q11:Q18) -> 90249 | R10: =SUM(F10:Q10) -> 978734 | S10: =IFERROR(AVERAGE(F10:Q10),"") -> 81561.167
B11: ☑ | E11: 住民税 | F11: 0 | G11: 0 | H11: 19400 | I11: 18400 | J11: 18400 | K11: 18400 | L11: 18400 | M11: 18400 | N11: 18400 | O11: 18400 | P11: 18400 | Q11: 18400 | R11: =SUM(F11:Q11) -> 185000 | S11: =IFERROR(AVERAGE(F11:Q11), "¥0") -> 15416.667
B12: ☑ | E12: 所得税給与所得の源泉徴収税額表（令和７年分）.xlsx | F12: 8420 | G12: 17240 | H12: 12100 | I12: 14060 | J12: 12100 | K12: 11610 | L12: 16020 | M12: 11610 | N12: 11610 | O12: 16750 | P12: 11610 | Q12: 11610 | R12: =SUM(F12:Q12) -> 154740 | S12: =IFERROR(AVERAGE(F12:Q12), "¥0") -> 12895
B13: ☑ | E13: 健康保険料令和7年度保険料額表（令和7年3月分から）.xlsx | F13: 17964 | G13: 17964 | H13: 17964 | I13: 17964 | J13: 17964 | K13: 20459 | L13: 20459 | M13: 20459 | N13: 20459 | O13: 20459 | P13: 20459 | Q13: 20315 | R13: =SUM(F13:Q13) -> 232889 | S13: =IFERROR(AVERAGE(F13:Q13), "¥0") -> 19407.417
B14: ☑ | E14: 雇用保険料 | F14: 2124 | G14: 2775 | H14: 2400 | I14: 2532 | J14: 2400 | K14: 2628 | L14: 2724 | M14: 2400 | N14: 2400 | O14: 2778 | P14: 2400 | Q14: 2409 | R14: =SUM(F14:Q14) -> 29970 | S14: =IFERROR(AVERAGE(F14:Q14), "¥0") -> 2497.5
B15: ☑ | E15: 厚生年金保険令和7年度保険料額表（令和7年3月分から）.xlsx | F15: 32940 | G15: 32940 | H15: 32940 | I15: 32940 | J15: 32940 | K15: 37515 | L15: 37515 | M15: 37515 | N15: 37515 | O15: 37515 | P15: 37515 | Q15: 37515 | R15: =SUM(F15:Q15) -> 427305 | S15: =IFERROR(AVERAGE(F15:Q15), "¥0") -> 35608.75
B16: ☑ | E16: 定額減税 | F16: 0 | G16: -17240 | H16: -12100 | I16: -660 | J16: 0 | K16: 0 | L16: 0 | M16: 0 | N16: 0 | O16: 0 | P16: 0 | Q16: 0 | R16: =SUM(F16:Q16) -> -30000 | S16: =IFERROR(AVERAGE(F16:Q16), "¥0") -> -2500
B17: ☑ | E17: 年末調整精算額 | F17: 0 | G17: 0 | H17: 0 | I17: 0 | J17: 0 | K17: 0 | L17: 0 | M17: -21170 | N17: 0 | O17: 0 | P17: 0 | Q17: 0 | R17: =SUM(F17:Q17) -> -21170 | S17: =IFERROR(AVERAGE(F17:Q17), "¥0") -> -1764.1667
B18: ☑ | E18: ふるさと納税返金額 | F18: 0 | G18: 0 | H18: 0 | I18: 0 | J18: 0 | K18: 0 | L18: 0 | M18: 0 | N18: 0 | O18: 0 | P18: 0 | Q18: 0 | R18: =SUM(F18:Q18) -> 0 | S18: =IFERROR(AVERAGE(F18:Q18), "¥0") -> 0

Sheet FY-2(日次)出費
C2: ※日付以外自動表示 触れない | D2: 手入力 | E2: 手入力 | F2: 手入力 | G2: ※自動表示 触れない | H2: 手入力 | I2: 手入力 | J2: 手入力 | K2: 手入力 | L2: 手入力 | M2: 手入力 | N2: 手入力 | O2: 手入力 | P2: ※切り出し特別管理用項目 →ほかにもあれば列追加
B3: 更新日時 | C3: 46137
B4: 【日付】 | C4: 合計 | D4: 朝飯 | E4: 昼飯 | F4: 晩飯 | G4: 食費合計 | H4: 交際費 | I4: プレゼント | J4: スーパー | K4: 体験 | L4: 結婚式 | M4: 旅費・交通費 | N4: 物品購入費 | O4: その他諸経費 | P4: 趣味・嗜好品(TBC等)
B5: 45748 | C5: =SUM(D5:P5) -> 3322 | D5: 0 | E5: 334 | F5: 698 | H5: 1610 | I5: 0 | J5: 0 | K5: 0 | L5: 0 | M5: 400 | N5: 280 | O5: 0 | P5: 0
B6: 45749 | C6: =SUM(D6:P6) -> 1280 | D6: 0 | E6: 850 | F6: 0 | H6: 0 | I6: 0 | J6: 0 | K6: 0 | L6: 0 | M6: 0 | N6: 0 | O6: 0 | P6: 430
B7: 45750 | C7: =SUM(D7:P7) -> 5585 | D7: 375 | E7: 410 | F7: 0 | H7: 1000 | I7: 0 | J7: 0 | K7: 3800 | L7: 0 | M7: 0 | N7: 0 | O7: 0 | P7: 0
B8: 45751 | C8: =SUM(D8:P8) -> 4099 | D8: 625 | E8: 0 | F8: 1044 | H8: 1570 | I8: 0 | J8: 0 | K8: 0 | L8: 0 | M8: 0 | N8: 0 | O8: 0 | P8: 860
B9: 45752 | C9: =SUM(D9:P9) -> 946 | D9: 0 | E9: 946 | F9: 0 | H9: 0 | I9: 0 | J9: 0 | K9: 0 | L9: 0 | M9: 0 | N9: 0 | O9: 0 | P9: 0
B10: 45753 | C10: =SUM(D10:P10) -> 2402 | D10: 0 | E10: 1200 | F10: 1202 | H10: 0 | I10: 0 | J10: 0 | K10: 0 | L10: 0 | M10: 0 | N10: 0 | O10: 0 | P10: 0
B11: 45754 | C11: =SUM(D11:P11) -> 0 | D11: 0 | E11: 0 | F11: 0 | H11: 0 | I11: 0 | J11: 0 | K11: 0 | L11: 0 | M11: 0 | N11: 0 | O11: 0 | P11: 0
B12: 45755 | C12: =SUM(D12:P12) -> 1277 | D12: 0 | E12: 417 | F12: 0 | H12: 0 | I12: 0 | J12: 0 | K12: 0 | L12: 0 | M12: 0 | N12: 0 | O12: 0 | P12: 860
B13: 45756 | C13: =SUM(D13:P13) -> 1000 | D13: 0 | E13: 0 | F13: 0 | H13: 1000 | I13: 0 | J13: 0 | K13: 0 | L13: 0 | M13: 0 | N13: 0 | O13: 0 | P13: 0
B14: 45757 | C14: =SUM(D14:P14) -> 2774 | D14: 0 | E14: 562 | F14: 1282 | H14: 0 | I14: 0 | J14: 0 | K14: 0 | L14: 0 | M14: 0 | N14: 0 | O14: 0 | P14: 930
B15: 45758 | C15: =SUM(D15:P15) -> 163 | D15: 0 | E15: 0 | F15: 0 | H15: 163 | I15: 0 | J15: 0 | K15: 0 | L15: 0 | M15: 0 | N15: 0 | O15: 0 | P15: 0
B16: 45759 | C16: =SUM(D16:P16) -> 5659 | D16: 0 | E16: 0 | F16: 938 | H16: 4721 | I16: 0 | J16: 0 | K16: 0 | L16: 0 | M16: 0 | N16: 0 | O16: 0 | P16: 0
... B34: 45777 | C34: =SUM(D34:P34) -> 2040 | D34: 0 | E34: 0 | F34: 465 | H34: 980 | I34: 0 | J34: 0 | K34: 0 | L34: 0 | M34: 0 | N34: 595 | O34: 0 | P34: 0
B35: 合計式 | C35: =SUM(D35:P35) -> 221470 | D35: =SUM(D5:D34) -> 6960 | E35: =SUM(E5:E34) -> 13780 | F35: =SUM(F5:F34) -> 15883 | H35: =SUM(H5:H34) -> 44065 | I35: =SUM(I5:I34) -> 4397 | J35: =SUM(J5:J34) -> 0 | K35: =SUM(K5:K34) -> 4400 | L35: =SUM(L5:L34) -> 43560 | M35: =SUM(M5:M34) -> 29173 | N35: =SUM(N5:N34) -> 49492 | O35: =SUM(O5:O34) -> 0 | P35: =SUM(P5:P34) -> 9760
B36: 45778 | C36: =SUM(D36:P36) -> 2743 | D36: 773 | E36: 440 | F36: 1530 | H36: 0 | I36: 0 | J36: 0 | K36: 0 | L36: 0 | M36: 0 | N36: 0 | O36: 0 | P36: 0
B37: 45779 | C37: =SUM(D37:P37) -> 6924 | D37: 554 | E37: 885 | F37: 985 | H37: 955 | I37: 470 | J37: 0 | K37: 0 | L37: 0 | M37: 0 | N37: 2215 | O37: 0 | P37: 860
B38: 45780 | C38: =SUM(D38:P38) -> 12949 | D38: 0 | E38: 0 | F38: 805 | H38: 11084 | I38: 0 | J38: 0 | K38: 0 | L38: 0 | M38: 560 | N38: 0 | O38: 0 | P38: 500
B39: 45781 | C39: =SUM(D39:P39) -> 8713 | D39: 0 | E39: 483 | F39: 829 | H39: 5445 | I39: 806 | J39: 0 | K39: 0 | L39: 0 | M39: 1150 | N39: 0 | O39: 0 | P39: 0
B40: 45782 | C40: =SUM(D40:P40) -> 4410 | D40: 0 | E40: 0 | F40: 1630 | H40: 2780 | I40: 0 | J40: 0 | K40: 0 | L40: 0 | M40: 0 | N40: 0 | O40: 0 | P40: 0
B41: 45783 | C41: =SUM(D41:P41) -> 3979 | D41: 0 | E41: 2156 | F41: 760 | H41: 0 | I41: 0 | J41: 0 | K41: 0 | L41: 0 | M41: 0 | N41: 633 | O41: 0 | P41: 430
B42: 45784 | C42: =SUM(D42:P42) -> 2316 | D42: 0 | E42: 760 | F42: 1556 | H42: 0 | I42: 0 | J42: 0 | K42: 0 | L42: 0 | M42: 0 | N42: 0 | O42: 0 | P42: 0
B43: 45785 | C43: =SUM(D43:P43) -> 1336 | D43: 0 | E43: 700 | F43: 186 | H43: 0 | I43: 450 | J43: 0 | K43: 0 | L43: 0 | M43: 0 | N43: 0 | O43: 0 | P43: 0
B44: 45786 | C44: =SUM(D44:P44) -> 3441 | D44: 0 | E44: 319 | F44: 1762 | H44: 0 | I44: 0 | J44: 0 | K44: 0 | L44: 0 | M44: 0 | N44: 0 | O44: 0 | P44: 1360
B45: 45787 | C45: =SUM(D45:P45) -> 3569 | D45: 0 | E45: 0 | F45: 1519 | H45: 0 | I45: 1000 | J45: 0 | K45: 0 | L45: 0 | M45: 1050 | N45: 0 | O45: 0 | P45: 0
B46: 45788 | C46: =SUM(D46:P46) -> 6099 | D46: 0 | E46: 1149 | F46: 0 | H46: 3700 | I46: 0 | J46: 0 | K46: 0 | L46: 0 | M46: 820 | N46: 0 | O46: 0 | P46: 430
B47: 45789 | C47: =SUM(D47:P47) -> 12168 | D47: 546 | E47: 292 | F47: 1330 | H47: 0 | I47: 10000 | J47: 0 | K47: 0 | L47: 0 | M47: 0 | N47: 0 | O47: 0 | P47: 0
... B66: 45808 | C66: =SUM(D66:P66) -> 4064 | D66: 858 | E66: 1250 | F66: 959 | H66: 0 | I66: 0 | J66: 0 | K66: 0 | L66: 0 | M66: 997 | N66: 0 | O66: 0 | P66: 0
B67: 合計式 | C67: =SUM(D67:P67) -> 318143 | D67: =SUM(D36:D66) -> 5936 | E67: =SUM(E36:E66) -> 14359 | F67: =SUM(F36:F66) -> 24200 | H67: =SUM(H36:H66) -> 57343 | I67: =SUM(I36:I66) -> 22831 | J67: =SUM(J36:J66) -> 0 | K67: =SUM(K36:K66) -> 7370 | L67: =SUM(L36:L66) -> 0 | M67: =SUM(M36:M66) -> 28969 | N67: =SUM(N36:N66) -> 4418 | O67: =SUM(O36:O66) -> 147777 | P67: =SUM(P36:P66) -> 4940
B68: 45809 | C68: =SUM(D68:P68) -> 43207 | D68: 0 | E68: 1050 | F68: 0 | H68: 0 | I68: 0 | J68: 1105 | K68: 0 | L68: 0 | M68: 356 | N68: 40696 | O68: 0 | P68: 0
B69: 45810 | C69: =SUM(D69:P69) -> 10440 | D69: 524 | E69: 0 | F69: 0 | H69: 0 | I69: 0 | J69: 4608 | K69: 0 | L69: 0 | M69: 0 | N69: 5308 | O69: 0 | P69: 0
B70: 45811 | C70: =SUM(D70:P70) -> 0 | D70: 0 | E70: 0 | F70: 0 | H70: 0 | I70: 0 | J70: 0 | K70: 0 | L70: 0 | M70: 0 | N70: 0 | O70: 0 | P70: 0
B71: 45812 | C71: =SUM(D71:P71) -> 550 | D71: 0 | E71: 0 | F71: 550 | H71: 0 | I71: 0 | J71: 0 | K71: 0 | L71: 0 | M71: 0 | N71: 0 | O71: 0 | P71: 0
B72: 45813 | C72: =SUM(D72:P72) -> 3716 | D72: 0 | E72: 355 | F72: 830 | H72: 0 | I72: 0 | J72: 0 | K72: 0 | L72: 0 | M72: 0 | N72: 2531 | O72: 0 | P72: 0
B73: 45814 | C73: =SUM(D73:P73) -> 5245 | D73: 0 | E73: 250 | F73: 96 | H73: 0 | I73: 0 | J73: 1999 | K73: 0 | L73: 0 | M73: 0 | N73: 2900 | O73: 0 | P73: 0
B74: 45815 | C74: =SUM(D74:P74) -> 14143 | D74: 0 | E74: 0 | F74: 203 | H74: 0 | I74: 0 | J74: 0 | K74: 1400 | L74: 0 | M74: 480 | N74: 12060 | O74: 0 | P74: 0
B75: 45816 | C75: =SUM(D75:P75) -> 8820 | D75: 0 | E75: 0 | F75: 790 | H75: 0 | I75: 0 | J75: 0 | K75: 0 | L75: 0 | M75: 0 | N75: 8030 | O75: 0 | P75: 0
B76: 45817 | C76: =SUM(D76:P76) -> 2143 | D76: 0 | E76: 457 | F76: 97 | H76: 0 | I76: 0 | J76: 1237 | K76: 0 | L76: 0 | M76: 28 | N76: 324 | O76: 0 | P76: 0
B77: 45818 | C77: =SUM(D77:P77) -> 1405 | D77: 0 | E77: 945 | F77: 432 | H77: 0 | I77: 0 | J77: 0 | K77: 0 | L77: 0 | M77: 28 | N77: 0 | O77: 0 | P77: 0
B78: 45819 | C78: =SUM(D78:P78) -> 1685 | D78: 0 | E78: 747 | F78: 870 | H78: 0 | I78: 0 | J78: 0 | K78: 0 | L78: 0 | M78: 68 | N78: 0 | O78: 0 | P78: 0
B79: 45820 | C79: =SUM(D79:P79) -> 1068 | D79: 0 | E79: 321 | F79: 719 | H79: 0 | I79: 0 | J79: 0 | K79: 0 | L79: 0 | M79: 28 | N79: 0 | O79: 0 | P79: 0
... B97: 45838 | C97: =SUM(D97:P97) -> 1736 | D97: 0 | E97: 642 | F97: 1080 | H97: 0 | I97: 0 | J97: 0 | K97: 0 | L97: 0 | M97: 14 | N97: 0 | O97: 0 | P97: 0
B98: 合計式 | C98: =SUM(D98:P98) -> 141358 | D98: =SUM(D68:D97) -> 1223 | E98: =SUM(E68:E97) -> 12630 | F98: =SUM(F68:F97) -> 14921 | H98: =SUM(H68:H97) -> 4150 | I98: =SUM(I68:I97) -> 1704 | J98: =SUM(J68:J97) -> 21399 | K98: =SUM(K68:K97) -> 4111 | L98: =SUM(L68:L97) -> 0 | M98: =SUM(M68:M97) -> 3296 | N98: =SUM(N68:N97) -> 76924 | O98: =SUM(O68:O97) -> 0 | P98: =SUM(P68:P97) -> 1000
B99: 45839 | C99: =SUM(D99:P99) -> 3398 | D99: 0 | E99: 746 | F99: 1332 | H99: 1050 | I99: 0 | J99: 0 | K99: 0 | L99: 0 | M99: 270 | N99: 0 | O99: 0 | P99: 0
B100: 45840 | C100: =SUM(D100:P100) -> 10949 | D100: 0 | E100: 828 | F100: 921 | H100: 8184 | I100: 0 | J100: 0 | K100: 0 | L100: 0 | M100: 516 | N100: 0 | O100: 0 | P100: 500
B101: 45841 | C101: =SUM(D101:P101) -> 2856 | D101: 160 | E101: 1100 | F101: 1080 | H101: 0 | I101: 0 | J101: 0 | K101: 0 | L101: 0 | M101: 516 | N101: 0 | O101: 0 | P101: 0
B102: 45842 | C102: =SUM(D102:P102) -> 1311 | D102: 0 | E102: 795 | F102: 0 | H102: 0 | I102: 0 | J102: 0 | K102: 0 | L102: 0 | M102: 516 | N102: 0 | O102: 0 | P102: 0
B103: 45843 | C103: =SUM(D103:P103) -> 8536 | D103: 0 | E103: 0 | F103: 0 | H103: 0 | I103: 0 | J103: 4517 | K103: 0 | L103: 0 | M103: 160 | N103: 0 | O103: 3359 | P103: 500
B104: 45844 | C104: =SUM(D104:P104) -> 3801 | D104: 0 | E104: 0 | F104: 205 | H104: 0 | I104: 0 | J104: 2691 | K104: 400 | L104: 0 | M104: 505 | N104: 0 | O104: 0 | P104: 0
B105: 45845 | C105: =SUM(D105:P105) -> 2466 | D105: 0 | E105: 804 | F105: 816 | H105: 0 | I105: 0 | J105: 0 | K105: 0 | L105: 0 | M105: 516 | N105: 330 | O105: 0 | P105: 0
B106: 45846 | C106: =SUM(D106:P106) -> 8339 | D106: 0 | E106: 800 | F106: 0 | H106: 0 | I106: 0 | J106: 0 | K106: 1750 | L106: 0 | M106: 836 | N106: 4953 | O106: 0 | P106: 0
B107: 45847 | C107: =SUM(D107:P107) -> 2078 | D107: 0 | E107: 0 | F107: 322 | H107: 900 | I107: 0 | J107: 0 | K107: 0 | L107: 0 | M107: 356 | N107: 0 | O107: 0 | P107: 500
B108: 45848 | C108: =SUM(D108:P108) -> 10096 | D108: 0 | E108: 250 | F108: 980 | H108: 850 | I108: 0 | J108: 0 | K108: 7500 | L108: 0 | M108: 516 | N108: 0 | O108: 0 | P108: 0
B109: 45849 | C109: =SUM(D109:P109) -> 2177 | D109: 0 | E109: 561 | F109: 0 | H109: 1100 | I109: 0 | J109: 0 | K109: 0 | L109: 0 | M109: 516 | N109: 0 | O109: 0 | P109: 0
B110: 45850 | C110: =SUM(D110:P110) -> 5796 | D110: 0 | E110: 0 | F110: 0 | H110: 0 | I110: 0 | J110: 0 | K110: 0 | L110: 0 | M110: 0 | N110: 5296 | O110: 0 | P110: 500
... B129: 45869 | C129: =SUM(D129:P129) -> 1115 | D129: 0 | E129: 532 | F129: 0 | H129: 0 | I129: 0 | J129: 0 | K129: 0 | L129: 0 | M129: 583 | N129: 0 | O129: 0 | P129: 0
B130: 合計式 | C130: =SUM(D130:P130) -> 152679 | D130: =SUM(D99:D129) -> 769 | E130: =SUM(E99:E129) -> 12678 | F130: =SUM(F99:F129) -> 13856 | H130: =SUM(H99:H129) -> 37069 | I130: =SUM(I99:I129) -> 1170 | J130: =SUM(J99:J129) -> 11477 | K130: =SUM(K99:K129) -> 9650 | L130: =SUM(L99:L129) -> 0 | M130: =SUM(M99:M129) -> 13594 | N130: =SUM(N99:N129) -> 43022 | O130: =SUM(O99:O129) -> 3894 | P130: =SUM(P99:P129) -> 5500
B131: 45870 | C131: =SUM(D131:P131) -> 12634 | D131: 0 | E131: 682 | F131: 993 | H131: 9873 | I131: 0 | J131: 0 | K131: 0 | L131: 0 | M131: 586 | N131: 0 | O131: 0 | P131: 500
B132: 45871 | C132: =SUM(D132:P132) -> 3033 | D132: 0 | E132: 864 | F132: 0 | H132: 0 | I132: 0 | J132: 1739 | K132: 0 | L132: 0 | M132: 0 | N132: 0 | O132: 0 | P132: 430
B133: 45872 | C133: =SUM(D133:P133) -> 14820 | D133: 0 | E133: 1140 | F133: 0 | H133: 0 | I133: 0 | J133: 0 | K133: 1400 | L133: 0 | M133: 480 | N133: 11800 | O133: 0 | P133: 0
B134: 45873 | C134: =SUM(D134:P134) -> 4119 | D134: 0 | E134: 0 | F134: 739 | H134: 0 | I134: 0 | J134: 1400 | K134: 0 | L134: 0 | M134: 0 | N134: 1980 | O134: 0 | P134: 0
B135: 45874 | C135: =SUM(D135:P135) -> 1046 | D135: 0 | E135: 532 | F135: 514 | H135: 0 | I135: 0 | J135: 0 | K135: 0 | L135: 0 | M135: 0 | N135: 0 | O135: 0 | P135: 0
B136: 45875 | C136: =SUM(D136:P136) -> 6816 | D136: 0 | E136: 0 | F136: 494 | H136: 0 | I136: 0 | J136: 5822 | K136: 0 | L136: 0 | M136: 0 | N136: 0 | O136: 0 | P136: 500
B137: 45876 | C137: =SUM(D137:P137) -> 725 | D137: 0 | E137: 344 | F137: 381 | H137: 0 | I137: 0 | J137: 0 | K137: 0 | L137: 0 | M137: 0 | N137: 0 | O137: 0 | P137: 0
B138: 45877 | C138: =SUM(D138:P138) -> 514 | D138: 127 | E138: 0 | F138: 387 | H138: 0 | I138: 0 | J138: 0 | K138: 0 | L138: 0 | M138: 0 | N138: 0 | O138: 0 | P138: 0
B139: 45878 | C139: =SUM(D139:P139) -> 4275 | D139: 0 | E139: 0 | F139: 430 | H139: 0 | I139: 0 | J139: 3145 | K139: 0 | L139: 0 | M139: 0 | N139: 200 | O139: 0 | P139: 500
B140: 45879 | C140: =SUM(D140:P140) -> 6227 | D140: 0 | E140: 108 | F140: 0 | H140: 6119 | I140: 0 | J140: 0 | K140: 0 | L140: 0 | M140: 0 | N140: 0 | O140: 0 | P140: 0
B141: 45880 | C141: =SUM(D141:P141) -> 4102 | D141: 0 | E141: 386 | F141: 0 | H141: 3200 | I141: 0 | J141: 0 | K141: 0 | L141: 0 | M141: 516 | N141: 0 | O141: 0 | P141: 0
B142: 45881 | C142: =SUM(D142:P142) -> 2948 | D142: 108 | E142: 1100 | F142: 1080 | H142: 0 | I142: 0 | J142: 0 | K142: 0 | L142: 0 | M142: 160 | N142: 0 | O142: 0 | P142: 500
... B161: 45900 | C161: =SUM(D161:P161) -> 15171 | D161: 0 | E161: 130 | F161: 0 | H161: 2724 | I161: 0 | J161: 3041 | K161: 0 | L161: 0 | M161: 816 | N161: 8030 | O161: 430 | P161: 0
B162: 合計式 | C162: =SUM(D162:P162) -> 179782 | D162: =SUM(D131:D161) -> 4924 | E162: =SUM(E131:E161) -> 11145 | F162: =SUM(F131:F161) -> 11892 | H162: =SUM(H131:H161) -> 64576 | I162: =SUM(I131:I161) -> 10772 | J162: =SUM(J131:J161) -> 16697 | K162: =SUM(K131:K161) -> 4128 | L162: =SUM(L131:L161) -> 0 | M162: =SUM(M131:M161) -> 20598 | N162: =SUM(N131:N161) -> 27970 | O162: =SUM(O131:O161) -> 430 | P162: =SUM(P131:P161) -> 6650
B163: 45901 | C163: =SUM(D163:P163) -> 2183 | D163: 108 | E163: 535 | F163: 940 | H163: 0 | I163: 0 | J163: 0 | K163: 0 | L163: 0 | M163: 0 | N163: 0 | O163: 600 | P163: 0
B164: 45902 | C164: =SUM(D164:P164) -> 1478 | D164: 108 | E164: 950 | F164: 0 | H164: 0 | I164: 0 | J164: 420 | K164: 0 | L164: 0 | M164: 0 | N164: 0 | O164: 0 | P164: 0
B165: 45903 | C165: =SUM(D165:P165) -> 797 | D165: 0 | E165: 0 | F165: 0 | H165: 0 | I165: 0 | J165: 797 | K165: 0 | L165: 0 | M165: 0 | N165: 0 | O165: 0 | P165: 0
B166: 45904 | C166: =SUM(D166:P166) -> 2370 | D166: 140 | E166: 607 | F166: 843 | H166: 0 | I166: 0 | J166: 0 | K166: 0 | L166: 0 | M166: 280 | N166: 0 | O166: 0 | P166: 500
B167: 45905 | C167: =SUM(D167:P167) -> 8550 | D167: 140 | E167: 334 | F167: 0 | H167: 7580 | I167: 0 | J167: 0 | K167: 0 | L167: 0 | M167: 496 | N167: 0 | O167: 0 | P167: 0
B168: 45906 | C168: =SUM(D168:P168) -> 5096 | D168: 0 | E168: 942 | F168: 1099 | H168: 0 | I168: 0 | J168: 0 | K168: 1000 | L168: 0 | M168: 1125 | N168: 0 | O168: 0 | P168: 930
B169: 45907 | C169: =SUM(D169:P169) -> 3256 | D169: 0 | E169: 0 | F169: 0 | H169: 0 | I169: 0 | J169: 0 | K169: 0 | L169: 0 | M169: 726 | N169: 2530 | O169: 0 | P169: 0
B170: 45908 | C170: =SUM(D170:P170) -> 4287 | D170: 0 | E170: 0 | F170: 147 | H170: 0 | I170: 0 | J170: 560 | K170: 0 | L170: 0 | M170: 280 | N170: 3300 | O170: 0 | P170: 0
B171: 45909 | C171: =SUM(D171:P171) -> 3606 | D171: 0 | E171: 0 | F171: 546 | H171: 0 | I171: 0 | J171: 0 | K171: 0 | L171: 0 | M171: 280 | N171: 2780 | O171: 0 | P171: 0
B172: 45910 | C172: =SUM(D172:P172) -> 2808 | D172: 0 | E172: 0 | F172: 322 | H172: 1163 | I172: 1163 | J172: 0 | K172: 0 | L172: 0 | M172: 160 | N172: 0 | O172: 0 | P172: 0
B173: 45911 | C173: =SUM(D173:P173) -> 2207 | D173: 0 | E173: 652 | F173: 775 | H173: 0 | I173: 0 | J173: 0 | K173: 0 | L173: 0 | M173: 280 | N173: 0 | O173: 0 | P173: 500
B174: 45912 | C174: =SUM(D174:P174) -> 10949 | D174: 0 | E174: 0 | F174: 1129 | H174: 8500 | I174: 0 | J174: 0 | K174: 0 | L174: 0 | M174: 670 | N174: 220 | O174: 0 | P174: 430
... B177: 45915 | C177: =SUM(D177:P177) -> 6091 | D177: 0 | E177: 1464 | F177: 100 | H177: 0 | I177: 0 | J177: 3447 | K177: 650 | L177: 0 | M177: 0 | N177: 0 | O177: 0 | P177: 430
B178: 45916 | C178: =SUM(D178:P178) -> 1087 | D178: 0 | E178: 0 | F178: 609 | H178: 0 | I178: 0 | J178: 0 | K178: 0 | L178: 0 | M178: 478 | N178: 0 | O178: 0
B179: 45917 | C179: =SUM(D179:P179) -> 5067 | D179: 0 | E179: 858 | F179: 1061 | H179: 2100 | I179: 0 | J179: 0 | K179: 0 | L179: 0 | M179: 548 | N179: 0 | O179: 0 | P179: 500
B180: 45918 | C180: =SUM(D180:P180) -> 2400 | D180: 140 | E180: 900 | F180: 650 | H180: 0 | I180: 0 | J180: 0 | K180: 0 | L180: 0 | M180: 280 | N180: 0 | O180: 0 | P180: 430
B181: 45919 | C181: =SUM(D181:P181) -> 1626 | D181: 0 | E181: 792 | F181: 0 | H181: 0 | I181: 0 | J181: 0 | K181: 0 | L181: 0 | M181: 834 | N181: 0 | O181: 0 | P181: 0
B182: 45920 | C182: =SUM(D182:P182) -> 13155 | D182: 0 | E182: 0 | F182: 267 | H182: 6280 | I182: 6060 | J182: 0 | K182: 0 | L182: 0 | M182: 548 | N182: 0 | O182: 0 | P182: 0
B183: 45921 | C183: =SUM(D183:P183) -> 9556 | D183: 0 | E183: 330 | F183: 0 | H183: 1530 | I183: 5484 | J183: 0 | K183: 300 | L183: 0 | M183: 1847 | N183: 0 | O183: 65 | P183: 0
B184: 45922 | C184: =SUM(D184:P184) -> 6017 | D184: 0 | E184: 100 | F184: 181 | H184: 3149 | I184: 0 | J184: 797 | K184: 0 | L184: 0 | M184: 860 | N184: 0 | O184: 0 | P184: 930
B185: 45923 | C185: =SUM(D185:P185) -> 990 | D185: 0 | E185: 0 | F185: 990 | H185: 0 | I185: 0 | J185: 0 | K185: 0 | L185: 0 | M185: 0 | N185: 0 | O185: 0 | P185: 0
B186: 45924 | C186: =SUM(D186:P186) -> 584 | D186: 0 | E186: 164 | F186: 0 | H186: 0 | I186: 0 | J186: 420 | K186: 0 | L186: 0 | M186: 0 | N186: 0 | O186: 0 | P186: 0
B187: 45925 | C187: =SUM(D187:P187) -> 6612 | D187: 0 | E187: 1100 | F187: 0 | H187: 4000 | I187: 0 | J187: 0 | K187: 0 | L187: 0 | M187: 1082 | N187: 0 | O187: 0 | P187: 430
B188: 45926 | C188: =SUM(D188:P188) -> 6800 | D188: 140 | E188: 0 | F188: 0 | H188: 0 | I188: 0 | J188: 420 | K188: 0 | L188: 0 | M188: 318 | N188: 5422 | O188: 0 | P188: 500
B189: 45927 | C189: =SUM(D189:P189) -> 24162 | D189: 0 | E189: 0 | F189: 0 | H189: 0 | I189: 0 | J189: 1195 | K189: 0 | L189: 18762 | M189: 3818 | N189: 387 | O189: 0 | P189: 0
B190: 45928 | C190: =SUM(D190:P190) -> 3993 | D190: 118 | E190: 840 | F190: 1357 | H190: 0 | I190: 0 | J190: 0 | K190: 0 | L190: 0 | M190: 1678 | N190: 0 | O190: 0 | P190: 0
... B192: 45930 | C192: =SUM(D192:P192) -> 2756 | D192: 0 | E192: 1100 | F192: 1496 | H192: 0 | I192: 0 | J192: 0 | K192: 0 | L192: 0 | M192: 160 | N192: 0 | O192: 0 | P192: 0
...

Sheet FY-3(日次)出費
C2: ※日付以外自動表示 触れない | D2: 手入力 | E2: 手入力 | F2: 手入力 | G2: ※自動表示 触れない | H2: 手入力 | I2: 手入力 | J2: 手入力 | K2: 手入力 | L2: 手入力 | M2: 手入力 | N2: 手入力 | O2: 手入力 | P2: ※切り出し特別管理用項目 →ほかにもあれば列追加
B3: 更新日時 | C3: 46208
B4: 【日付】 | C4: 合計 | D4: 朝飯 | E4: 昼飯 | F4: 晩飯 | G4: 食費合計 | H4: 交際費 | I4: プレゼント | J4: スーパー | K4: 体験 | L4: 結婚式 | M4: 旅費・交通費 | N4: 物品購入費 | O4: その他諸経費 | P4: 趣味・嗜好品(TBC等)
B5: 46113 | C5: {=G5:G1391 + H5:H1391 + I5:I1391 + J5:J1391 + K5:K1391 + L5:L1391 + M5:M1391 + N5:N1391 + O5:O1391 + P5:P1391} -> 1740 | D5: 120 | E5: 120 | F5: 1500 | G5: {=D5:D1391 + E5:E1391 + F5:F1391} -> 1740 | H5: 0 | I5: 0 | J5: 0 | K5: 0 | L5: 0 | M5: 0 | N5: 0 | O5: 0 | P5: 0
B6: 46114 | C6: 3918 | D6: 808 | E6: 1090 | F6: 1520 | G6: 3418 | H6: 0 | I6: 0 | J6: 0 | K6: 0 | L6: 0 | M6: 0 | N6: 0 | O6: 0 | P6: 500
B7: 46115 | C7: 2272 | D7: 0 | E7: 624 | F7: 635 | G7: 1259 | H7: 0 | I7: 680 | J7: 0 | K7: 0 | L7: 0 | M7: 333 | N7: 0 | O7: 0 | P7: 0
B8: 46116 | C8: 45262 | D8: 0 | E8: 1030 | F8: 1978 | G8: 3008 | H8: 24450 | I8: 0 | J8: 3104 | K8: 8800 | L8: 0 | M8: 4220 | N8: 700 | O8: 0 | P8: 980
B9: 46117 | C9: 16486 | D9: 0 | E9: 1250 | F9: 0 | G9: 1250 | H9: 1599 | I9: 0 | J9: 0 | K9: 9900 | L9: 0 | M9: 3737 | N9: 0 | O9: 0 | P9: 0
B10: 46118 | C10: 3114 | D10: 623 | E10: 851 | F10: 1060 | G10: 2534 | H10: 0 | I10: 0 | J10: 0 | K10: 0 | L10: 0 | M10: 0 | N10: 0 | O10: 0 | P10: 580
B11: 46119 | C11: 3748 | D11: 120 | E11: 470 | F11: 0 | G11: 590 | H11: 0 | I11: 0 | J11: 0 | K11: 2050 | L11: 0 | M11: 0 | N11: 1108 | O11: 0 | P11: 0
B12: 46120 | C12: 5335 | D12: 617 | E12: 850 | F12: 990 | G12: 2457 | H12: 0 | I12: 0 | J12: 0 | K12: 0 | L12: 0 | M12: 0 | N12: 2878 | O12: 0 | P12: 0
B13: 46121 | C13: 1955 | D13: 120 | E13: 900 | F13: 935 | G13: 1955 | H13: 0 | I13: 0 | J13: 0 | K13: 0 | L13: 0 | M13: 0 | N13: 0 | O13: 0 | P13: 0
B14: 46122 | C14: 5909 | D14: 120 | E14: 1090 | F14: 0 | G14: 1210 | H14: 0 | I14: 0 | J14: 0 | K14: 0 | L14: 0 | M14: 4699 | N14: 0 | O14: 0 | P14: 0
B15: 46123 | C15: 8786 | D15: 300 | E15: 400 | F15: 1230 | G15: 1930 | H15: 4530 | I15: 0 | J15: 0 | K15: 0 | L15: 0 | M15: 1296 | N15: 0 | O15: 0 | P15: 1030
B16: 46124 | C16: 8118 | D16: 0 | E16: 0 | F16: 0 | G16: 0 | H16: 4410 | I16: 1500 | J16: 1406 | K16: 0 | L16: 0 | M16: 272 | N16: 0 | O16: 0 | P16: 530
B17: 46125 | C17: 3148 | D17: 120 | E17: 1030 | F17: 195 | G17: 1345 | H17: 786 | I17: 0 | J17: 0 | K17: 0 | L17: 0 | M17: 1017 | N17: 0 | O17: 0 | P17: 0
... B34: 46142 | C34: 2081 | D34: 0 | E34: 0 | F34: 372 | G34: 372 | H34: 1500 | I34: 0 | J34: 0 | K34: 0 | L34: 0 | M34: 209 | N34: 0 | O34: 0 | P34: 0
B35: 合計式* | C35: 262636 | D35: =SUM(D5:D34) -> 6654 | E35: =SUM(E5:E34) -> 16849 | F35: =SUM(F5:F34) -> 15727 | G35: 39230 | H35: =SUM(H5:H34) -> 83941 | I35: =SUM(I5:I34) -> 19397 | J35: =SUM(J5:J34) -> 15288 | K35: =SUM(K5:K34) -> 36690 | L35: =SUM(L5:L34) -> 0 | M35: =SUM(M5:M34) -> 49681 | N35: =SUM(N5:N34) -> 7451 | O35: =SUM(O5:O34) -> 1308 | P35: =SUM(P5:P34) -> 9650
B36: 46143 | C36: 6362 | D36: 0 | E36: 0 | F36: 0 | G36: 0 | H36: 0 | I36: 0 | J36: 0 | K36: 5110 | L36: 0 | M36: 272 | N36: 0 | O36: 0 | P36: 980
B37: 46144 | C37: 33407 | D37: 0 | E37: 0 | F37: 0 | G37: 0 | H37: 17659 | I37: 12760 | J37: 2423 | K37: 0 | L37: 0 | M37: 565 | N37: 0 | O37: 0 | P37: 0
B38: 46145 | C38: 25379 | D38: 0 | E38: 0 | F38: 0 | G38: 0 | H38: 0 | I38: 5000 | J38: 5365 | K38: 9800 | L38: 0 | M38: 1254 | N38: 3960 | O38: 0 | P38: 0
B39: 46146 | C39: 194 | D39: 0 | E39: 194 | F39: 0 | G39: 194 | H39: 0 | I39: 0 | J39: 0 | K39: 0 | L39: 0 | M39: 0 | N39: 0 | O39: 0 | P39: 0
B40: 46147 | C40: 3352 | D40: 0 | E40: 752 | F40: 0 | G40: 752 | H40: 1300 | I40: 1300 | J40: 0 | K40: 0 | L40: 0 | M40: 0 | N40: 0 | O40: 0 | P40: 0
B41: 46148 | C41: 3694 | D41: 0 | E41: 0 | F41: 0 | G41: 0 | H41: 586 | I41: 600 | J41: 0 | K41: 0 | L41: 0 | M41: 1528 | N41: 0 | O41: 0 | P41: 980
B42: 46149 | C42: 3251 | D42: 0 | E42: 0 | F42: 1050 | G42: 1050 | H42: 0 | I42: 0 | J42: 0 | K42: 0 | L42: 0 | M42: 781 | N42: 890 | O42: 0 | P42: 530
B43: 46150 | C43: 100 | D43: 0 | E43: 100 | F43: 0 | G43: 100 | H43: 0 | I43: 0 | J43: 0 | K43: 0 | L43: 0 | M43: 0 | N43: 0 | O43: 0 | P43: 0
B44: 46151 | C44: 14084 | D44: 0 | E44: 0 | F44: 0 | G44: 0 | H44: 0 | I44: 0 | J44: 2790 | K44: 10640 | L44: 0 | M44: 0 | N44: 654 | O44: 0 | P44: 0
B45: 46152 | C45: 2175 | D45: 0 | E45: 0 | F45: 0 | G45: 0 | H45: 0 | I45: 0 | J45: 2175 | K45: 0 | L45: 0 | M45: 0 | N45: 0 | O45: 0 | P45: 0
B46: 46153 | C46: 1190 | D46: 0 | E46: 543 | F46: 0 | G46: 543 | H46: 0 | I46: 0 | J46: 647 | K46: 0 | L46: 0 | M46: 0 | N46: 0 | O46: 0 | P46: 0
B47: 46154 | C47: 2264 | D47: 0 | E47: 0 | F47: 0 | G47: 0 | H47: 0 | I47: 0 | J47: 2264 | K47: 0 | L47: 0 | M47: 0 | N47: 0 | O47: 0 | P47: 0
... B66: 46173 | C66: 2940 | D66: 0 | E66: 0 | F66: 0 | G66: 0 | H66: 1771 | I66: 0 | J66: 0 | K66: 0 | L66: 0 | M66: 389 | N66: 330 | O66: 0 | P66: 450
B67: 合計式* | C67: 282057 | D67: =SUM(D36:D66) -> 100 | E67: =SUM(E36:E66) -> 6084 | F67: =SUM(F36:F66) -> 7184 | G67: 13368 | H67: =SUM(H36:H66) -> 86657 | I67: =SUM(I36:I66) -> 21331 | J67: =SUM(J36:J66) -> 23644 | K67: =SUM(K36:K66) -> 89500 | L67: =SUM(L36:L66) -> 0 | M67: =SUM(M36:M66) -> 33168 | N67: =SUM(N36:N66) -> 5834 | O67: =SUM(O36:O66) -> 475 | P67: =SUM(P36:P66) -> 8080
B68: 46174 | C68: 2102 | D68: 0 | E68: 200 | F68: 150 | G68: 350 | H68: 850 | I68: 0 | J68: 0 | K68: 0 | L68: 0 | M68: 422 | N68: 0 | O68: 0 | P68: 480
B69: 46175 | C69: 400 | D69: 0 | E69: 250 | F69: 150 | G69: 400 | H69: 0 | I69: 0 | J69: 0 | K69: 0 | L69: 0 | M69: 0 | N69: 0 | O69: 0 | P69: 0
B70: 46176 | C70: 46001 | D70: 0 | E70: 0 | F70: 0 | G70: 0 | H70: 0 | I70: 0 | J70: 3141 | K70: 40700 | L70: 0 | M70: 180 | N70: 0 | O70: 1500 | P70: 480
B71: 46177 | C71: 450 | D71: 0 | E71: 250 | F71: 200 | G71: 450 | H71: 0 | I71: 0 | J71: 0 | K71: 0 | L71: 0 | M71: 0 | N71: 0 | O71: 0 | P71: 0
B72: 46178 | C72: 7324 | D72: 0 | E72: 850 | F72: 150 | G72: 1000 | H72: 5679 | I72: 0 | J72: 0 | K72: 0 | L72: 0 | M72: 165 | N72: 0 | O72: 0 | P72: 480
B73: 46179 | C73: 17080 | D73: 0 | E73: 0 | F73: 0 | G73: 0 | H73: 15000 | I73: 0 | J73: 0 | K73: 0 | L73: 0 | M73: 1600 | N73: 0 | O73: 0 | P73: 480
B74: 46180 | C74: 4327 | D74: 0 | E74: 0 | F74: 0 | G74: 0 | H74: 3762 | I74: 0 | J74: 0 | K74: 0 | L74: 0 | M74: 565 | N74: 0 | O74: 0 | P74: 0
B75: 46181 | C75: 1612 | D75: 100 | E75: 200 | F75: 0 | G75: 300 | H75: 0 | I75: 0 | J75: 0 | K75: 0 | L75: 0 | M75: 422 | N75: 890 | O75: 0 | P75: 0
B76: 46182 | C76: 3661 | D76: 0 | E76: 230 | F76: 0 | G76: 230 | H76: 0 | I76: 0 | J76: 2951 | K76: 0 | L76: 0 | M76: 0 | N76: 0 | O76: 0 | P76: 480
B77: 46183 | C77: 15411 | D77: 0 | E77: 322 | F77: 0 | G77: 322 | H77: 14276 | I77: 0 | J77: 0 | K77: 0 | L77: 0 | M77: 333 | N77: 0 | O77: 0 | P77: 480
B78: 46184 | C78: 6857 | D78: 120 | E78: 346 | F78: 980 | G78: 1446 | H78: 0 | I78: 0 | J78: 3963 | K78: 0 | L78: 0 | M78: 0 | N78: 968 | O78: 0 | P78: 480
B79: 46185 | C79: 792 | D79: 160 | E79: 322 | F79: 0 | G79: 482 | H79: 0 | I79: 0 | J79: 0 | K79: 0 | L79: 0 | M79: 310 | N79: 0 | O79: 0 | P79: 0
... B97: 46203 | C97: 3545 | D97: 0 | E97: 0 | F97: 0 | G97: 0 | H97: 2580 | I97: 0 | J97: 0 | K97: 0 | L97: 0 | M97: 485 | N97: 0 | O97: 0 | P97: 480
B98: 合計式* | C98: 237904 | D98: =SUM(D68:D97) -> 704 | E98: =SUM(E68:E97) -> 7107 | F98: =SUM(F68:F97) -> 4603 | G98: 12414 | H98: =SUM(H68:H97) -> 86516 | I98: =SUM(I68:I97) -> 2570 | J98: =SUM(J68:J97) -> 17998 | K98: =SUM(K68:K97) -> 82780 | L98: =SUM(L68:L97) -> 0 | M98: =SUM(M68:M97) -> 12548 | N98: =SUM(N68:N97) -> 8428 | O98: =SUM(O68:O97) -> 6010 | P98: =SUM(P68:P97) -> 8640
B99: 46204 | C99: 41710 | D99: 0 | E99: 200 | F99: 0 | G99: 200 | H99: 0 | I99: 0 | J99: 0 | K99: 40700 | L99: 0 | M99: 0 | N99: 810 | O99: 0 | P99: 0
B100: 46205 | C100: 8492 | D100: 0 | E100: 200 | F100: 170 | G100: 370 | H100: 0 | I100: 0 | J100: 7642 | K100: 0 | L100: 0 | M100: 0 | N100: 0 | O100: 0 | P100: 480
B101: 46206 | C101: 8285 | D101: 0 | E101: 490 | F101: 0 | G101: 490 | H101: 7315 | I101: 0 | J101: 0 | K101: 0 | L101: 0 | M101: 0 | N101: 0 | O101: 0 | P101: 480
B102: 46207 | C102: 18000 | D102: 0 | E102: 0 | F102: 0 | G102: 0 | H102: 0 | I102: 0 | J102: 0 | K102: 3000 | L102: 15000 | M102: 0 | N102: 0 | O102: 0 | P102: 0
B103: 46208 | C103: 0 | D103: 0 | E103: 0 | F103: 0 | G103: 0 | H103: 0 | I103: 0 | J103: 0 | K103: 0 | L103: 0 | M103: 0 | N103: 0 | O103: 0 | P103: 0
B104: 46209 | C104: 0 | G104: 0 | L104: 0
B105: 46210 | C105: 0 | G105: 0 | L105: 0
B106: 46211 | C106: 0 | G106: 0 | L106: 0
B107: 46212 | C107: 0 | G107: 0 | L107: 0
B108: 46213 | C108: 0 | G108: 0 | L108: 0
B109: 46214 | C109: 0 | G109: 0 | L109: 0
B110: 46215 | C110: 30000 | G110: 0 | L110: 30000
B111: 46216 | C111: 0 | G111: 0 | L111: 0
B112: 46217 | C112: 0 | G112: 0 | L112: 0
B113: 46218 | C113: 0 | G113: 0 | L113: 0
B114: 46219 | C114: 0 | G114: 0 | L114: 0
B115: 46220 | C115: 0 | G115: 0 | L115: 0
B116: 46221 | C116: 18600 | G116: 0 | K116: 18600 | L116: 0
B117: 46222 | C117: 0 | G117: 0 | L117: 0
B118: 46223 | C118: 0 | G118: 0 | L118: 0
B119: 46224 | C119: 0 | G119: 0 | L119: 0
B120: 46225 | C120: 0 | G120: 0 | L120: 0
B121: 46226 | C121: 0 | G121: 0 | L121: 0
B122: 46227 | C122: 0 | G122: 0 | L122: 0
B123: 46228 | C123: 0 | G123: 0 | L123: 0
B124: 46229 | C124: 0 | G124: 0 | L124: 0
B125: 46230 | C125: 0 | G125: 0 | L125: 0
B126: 46231 | C126: 0 | G126: 0 | L126: 0
B127: 46232 | C127: 0 | G127: 0 | L127: 0
B128: 46233 | C128: 0 | G128: 0 | L128: 0
B129: 46234 | C129: 110000 | F129: 10000 | G129: 10000 | H129: 80000 | J129: 20000 | L129: 0
B130: 合計式* | C130: 235087 | D130: =SUM(D99:D129) -> 0 | E130: =SUM(E99:E129) -> 890 | F130: =SUM(F99:F129) -> 10170 | G130: 11060 | H130: =SUM(H99:H129) -> 87315 | I130: =SUM(I99:I129) -> 0 | J130: =SUM(J99:J129) -> 27642 | K130: =SUM(K99:K129) -> 62300 | L130: =SUM(L99:L129) -> 45000 | M130: =SUM(M99:M129) -> 0 | N130: =SUM(N99:N129) -> 810 | O130: =SUM(O99:O129) -> 0 | P130: =SUM(P99:P129) -> 960
B131: 46235 | C131: 40700 | G131: 0 | K131: 40700
B132: 46236 | C132: 0 | G132: 0
B133: 46237 | C133: 176460 | G133: 0 | H133: 176460
B134: 46238 | C134: 0 | G134: 0
B135: 46239 | C135: 0 | G135: 0
B136: 46240 | C136: 0 | G136: 0
B137: 46241 | C137: 0 | G137: 0
B138: 46242 | C138: 20000 | G138: 0 | L138: 20000
B139: 46243 | C139: 0 | G139: 0
B140: 46244 | C140: 0 | G140: 0
B141: 46245 | C141: 0 | G141: 0
B142: 46246 | C142: 0 | G142: 0
B143: 46247 | C143: 0 | G143: 0
B144: 46248 | C144: 0 | G144: 0
B145: 46249 | C145: 0 | G145: 0
B146: 46250 | C146: 0 | G146: 0
B147: 46251 | C147: 0 | G147: 0
B148: 46252 | C148: 0 | G148: 0
B149: 46253 | C149: 0 | G149: 0
B150: 46254 | C150: 0 | G150: 0
... B161: 46265 | C161: 0 | G161: 0
B162: 合計式* | C162: 237160 | D162: =SUM(D131:D161) -> 0 | E162: =SUM(E131:E161) -> 0 | F162: =SUM(F131:F161) -> 0 | G162: 0 | H162: =SUM(H131:H161) -> 176460 | I162: =SUM(I131:I161) -> 0 | J162: =SUM(J131:J161) -> 0 | K162: =SUM(K131:K161) -> 40700 | L162: =SUM(L131:L161) -> 20000 | M162: =SUM(M131:M161) -> 0 | N162: =SUM(N131:N161) -> 0 | O162: =SUM(O131:O161) -> 0 | P162: =SUM(P131:P161) -> 0
...

Sheet (週次)進捗
B2: 週次進捗管理表
B3: 【合計】* | C3: (月) | E3: (日) | F3: 食費 | G3: 交際費 | H3: 旅費・交通費 | I3: 嗜好品(TBC等)
B4: =SUM(F4:I4) -> 15164 | C4: 45747 | D4: ～ | E4: 45753 | F4: 8344 | G4: 5130 | H4: 400 | I4: 1290
B5: =SUM(F5:I5) -> 14452 | C5: 45754 | D5: ～ | E5: 45760 | F5: 4333 | G5: 7399 | H5: 0 | I5: 2720
B6: =SUM(F6:I6) -> 132279 | C6: 45761 | D6: ～ | E6: 45767 | F6: 10928 | G6: 90378 | H6: 27893 | I6: 3080
B7: =SUM(F7:I7) -> 20101 | C7: 45768 | D7: ～ | E7: 45774 | F7: 9162 | G7: 8569 | H7: 580 | I7: 1790
B8: =SUM(F8:I8) -> 48713 | C8: 45775 | D8: ～ | E8: 45781 | F8: 11800 | G8: 32663 | H8: 2010 | I8: 2240
B9: =SUM(F9:I9) -> 23067 | C9: 45782 | D9: ～ | E9: 45788 | F9: 12497 | G9: 6480 | H9: 1870 | I9: 2220
B10: =SUM(F10:I10) -> 18057 | C10: 45789 | D10: ～ | E10: 45795 | F10: 10123 | G10: 6574 | H10: 0 | I10: 1360
B11: =SUM(F11:I11) -> 38569 | C11: 45796 | D11: ～ | E11: 45802 | F11: 7746 | G11: 13332 | H11: 17491 | I11: 0
B12: =SUM(F12:I12) -> 24522 | C12: 45803 | D12: ～ | E12: 45809 | F12: 7895 | G12: 8373 | H12: 8254 | I12: 0
B13: =SUM(F13:I13) -> 4078 | C13: 45810 | D13: ～ | E13: 45816 | F13: 3598 | G13: 0 | H13: 480 | I13: 0
B14: =SUM(F14:I14) -> 9703 | C14: 45817 | D14: ～ | E14: 45823 | F14: 5913 | G14: 2150 | H14: 1640 | I14: 0
B15: =SUM(F15:I15) -> 7243 | C15: 45824 | D15: ～ | E15: 45830 | F15: 6825 | G15: 0 | H15: 418 | I15: 0
... B68: =SUM(F68:I68) -> 21522 | C68: 46195 | D68: ～ | E68: 46201 | F68: 4087 | G68: 14950 | H68: 565 | I68: 1920
B69: =SUM(F69:I69) -> 0 | C69: 46202 | D69: ～ | E69: 46208
B70: =SUM(F70:I70) -> 0 | C70: 46209 | D70: ～ | E70: 46215
B71: =SUM(F71:I71) -> 0 | C71: 46216 | D71: ～ | E71: 46222
B72: =SUM(F72:I72) -> 0 | C72: 46223 | D72: ～ | E72: 46229
B73: =SUM(F73:I73) -> 0 | C73: 46230 | D73: ～ | E73: 46236
B74: =SUM(F74:I74) -> 0 | C74: 46237 | D74: ～ | E74: 46243
B75: =SUM(F75:I75) -> 0 | C75: 46244 | D75: ～ | E75: 46250
B76: =SUM(F76:I76) -> 0 | C76: 46251 | D76: ～ | E76: 46257
B77: =SUM(F77:I77) -> 0 | C77: 46258 | D77: ～ | E77: 46264
B78: =SUM(F78:I78) -> 0 | C78: 46265 | D78: ～ | E78: 46271
B79: =SUM(F79:I79) -> 0 | C79: 46272 | D79: ～ | E79: 46278
B80: =SUM(F80:I80) -> 0 | C80: 46279 | D80: ～ | E80: 46285
... B82: =SUM(F82:I82) -> 0 | C82: 46293 | D82: ～ | E82: 46299
B83: =SUM(F83:I83) -> 0
B84: =SUM(F84:I84) -> 0
B85: =SUM(F85:I85) -> 0
B86: =SUM(F86:I86) -> 0
B87: =SUM(F87:I87) -> 0
B88: =SUM(F88:I88) -> 0
B89: =SUM(F89:I89) -> 0
B90: =SUM(F90:I90) -> 0
B91: =SUM(F91:I91) -> 0
B92: =SUM(F92:I92) -> 0
B93: =SUM(F93:I93) -> 0
B94: =SUM(F94:I94) -> 0
B95: =SUM(F95:I95) -> 0

Sheet FY-2(月次)支出
D1: ※確定 | E1: ※確定 | F1: ※確定 | G1: ※確定 | H1: ※確定 | I1: ※確定 | J1: ※確定 | K1: ※確定 | L1: ※確定 | M1: ※確定 | N1: ※確定 | O1: ※確定 | P1: ※確定
C2: (FY-2)支出 | D2: 2025年4月 | E2: 2025年5月 | F2: 2025年6月 | G2: 2025年7月 | H2: 2025年8月 | I2: 2025年9月 | J2: 2025年10月 | K2: 2025年11月 | L2: 2025年12月 | M2: 2026年1月 | N2: 2026年2月 | O2: 2026年3月 | P2: 合計 | Q2: 平均
B3: ALL | C3: 〔 固定費及び変動費 〕合計支出額 | D3: =D5+D19 -> 328579 | E3: =E5+E19 -> 458043 | F3: =F5+F19 -> 320775 | G3: =G5+G19 -> 314993 | H3: =H5+H19 -> 335534 | I3: =I5+I19 -> 340477 | J3: =J5+J19 -> 514909 | K3: =K5+K19 -> 566502 | ... P3: =P5+P19 -> 5512188 | Q3: =IFERROR(AVERAGE(D3:O3),"") -> 459349
C4: 収入(手取り)に対する比率 | D4: =(D3/'FY-2(月次)収入'!D4) -> 0.94481426 | E4: =(E3/'FY-2(月次)収入'!E4) -> 1.8194793 | F4: =(F3/'FY-2(月次)収入'!F3) -> 4.6559307 | G4: =(G3/'FY-2(月次)収入'!G4) -> 0.73663619 | H4: =(H3/'FY-2(月次)収入'!H4) -> 0.72268661 | I4: =(I3/'FY-2(月次)収入'!I4) -> 0.62379904 | J4: =(J3/'FY-2(月次)収入'!J4) -> 1.001009 | K4: =(K3/'FY-2(月次)収入'!K4) -> 1.0676707 | L4: =(L3/'FY-2(月次)収入'!L4) -> 1.0778741 | M4: =(M3/'FY-2(月次)収入'!M4) -> 1.5314628 | N4: =(N3/'FY-2(月次)収入'!N4) -> 0.75149744 | ... Q4: =(Q3/'FY-2(月次)収入'!Q4) -> 1.0863116
B5: 固定費：合計支出額 | C5: 【固定費】月次合計: | D5: =SUM(D7:D18) -> 106409 | E5: =SUM(E7:E18) -> 139900 | F5: =SUM(F7:F18) -> 157242 | G5: =SUM(G7:G18) -> 162314 | H5: =SUM(H7:H18) -> 161752 | I5: =SUM(I7:I18) -> 156464 | J5: =SUM(J7:J18) -> 156452 | K5: =SUM(K7:K18) -> 186223 | ... O5: =SUM(O7:O18) -> 173114 | P5: =SUM(D5:O5) -> 1935350 | Q5: =IFERROR(AVERAGE(D5:O5),"") -> 161279.17
B6: 備考 | C6: 収入(手取り)に対する比率 | D6: =(D5/'FY-2(月次)収入'!D4) -> 0.30597433 | E6: =(E5/'FY-2(月次)収入'!E4) -> 0.55572327 | F6: =(F5/'FY-2(月次)収入'!F3) -> 2.2823096 | G6: =(G5/'FY-2(月次)収入'!G4) -> 0.3795842 | H6: =(H5/'FY-2(月次)収入'!H4) -> 0.34838796 | I6: =(I5/'FY-2(月次)収入'!I4) -> 0.28666281 | J6: =(J5/'FY-2(月次)収入'!J4) -> 0.30415055 | K6: =(K5/'FY-2(月次)収入'!K4) -> 0.35096935 | L6: =(L5/'FY-2(月次)収入'!L4) -> 0.34208098 | M6: =(M5/'FY-2(月次)収入'!M4) -> 0.34588523 | N6: =(N5/'FY-2(月次)収入'!N4) -> 0.33976932 | ... Q6: =(Q5/'FY-2(月次)収入'!Q4) -> 0.38140809
B7: 口座振替（みずほ） | C7: 家賃(NE武蔵中原・SA麻布十番)※水道光熱費込み | D7: 59149 | E7: 88700 | F7: 89587 | G7: 89587 | H7: 89587 | I7: 89587 | J7: 89587 | K7: 129987 | L7: 129987 | M7: 129987 | N7: 129955 | O7: 129987 | P7: =SUM(D7:O7) -> 1245687 | Q7: =IFERROR(AVERAGE(D7:O7), "¥0") -> 103807.25
B8: クレカ引落し | C8: ジム(レアレア武蔵中原・JOYFIT麻布十番) | D8: 0 | E8: 13232 | F8: 11000 | G8: 11000 | H8: 11000 | I8: 11000 | J8: 11000 | K8: 9167 | L8: 0 | M8: 8000 | N8: 8000 | O8: 8000 | P8: =SUM(D8:O8) -> 101399 | Q8: =IFERROR(AVERAGE(D8:O8), "¥0") -> 8449.9167
B9: クレカ引落し | C9: 生命保険(プルデンシャル) | D9: 9307 | E9: 9307 | F9: 9307 | G9: 9307 | H9: 9307 | I9: 9307 | J9: 9307 | K9: 9307 | L9: 9307 | M9: 9307 | N9: 9307 | O9: 9307 | P9: =SUM(D9:O9) -> 111684 | Q9: =IFERROR(AVERAGE(D9:O9), "¥0") -> 9307
B10: ★クレカ引落し(2025年7月5日に機種編) ※2027年7月頃に要確認 | C10: 携帯料金(SB)＋YouTubeプレミアム(￥870) | D10: 12753 | E10: 12621 | F10: 12907 | G10: 12906 | H10: 15784 | I10: 9028 | J10: 9160 | K10: 9402 | L10: 9233 | M10: 9006 | N10: 9235 | O10: 9214 | P10: =SUM(D10:O10) -> 131249 | Q10: =IFERROR(AVERAGE(D10:O10), "¥0") -> 10937.417
B11: クレカ→anapay→pasmo→給料日に精算 | C11: 定期券代 | D11: 8830 | E11: 0 | F11: 22591 | G11: 20340 | H11: 20510 | I11: 20510 | J11: 20510 | K11: 11590 | L11: 11590 | M11: 12420 | N11: 12420 | O11: 12420 | P11: =SUM(D11:O11) -> 173731 | Q11: =IFERROR(AVERAGE(D11:O11), "¥0") -> 14477.583
B12: 口座振替 | C12: 脱毛支払い(プラム) | D12: 11400 | E12: 11400 | F12: 11400 | G12: 11400 | H12: 11400 | I12: 11400 | J12: 11400 | K12: 11400 | L12: 11400 | M12: 11400 | N12: 0 | O12: 0 | P12: =SUM(D12:O12) -> 114000 | Q12: =IFERROR(AVERAGE(D12:O12), "¥0") -> 9500
B13: クレカ引落し | C13: iCloud拡張会費 | D13: 450 | E13: 450 | F13: 450 | G13: 450 | H13: 450 | I13: 450 | J13: 450 | K13: 450 | L13: 450 | M13: 450 | N13: 150 | O13: 150 | P13: =SUM(D13:O13) -> 4800 | Q13: =IFERROR(AVERAGE(D13:O13), "¥0") -> 400
C14: BASE FOOD/ナッシュのサブスク | D14: 0 | E14: 0 | F14: 0 | G14: 7324 | H14: 3714 | I14: 5182 | J14: 5038 | K14: 4920 | L14: 4920 | M14: 4920 | N14: 4036 | O14: 4036 | P14: =SUM(D14:O14) -> 44090 | Q14: =IFERROR(AVERAGE(D14:O14), "¥0") -> 3674.1667
B15: クレカ引落し | C15: ChatGPTプラス | D15: 3000 | E15: 3000 | F15: 0 | G15: 0 | H15: 0 | I15: 0 | J15: 0 | K15: 0 | L15: 0 | M15: 0 | N15: 0 | O15: 0 | P15: =SUM(D15:O15) -> 6000 | Q15: =IFERROR(AVERAGE(D15:O15), "¥0") -> 500
B16: クレカ引落し | C16: Netflix | D16: 1190 | E16: 1190 | F16: 0 | G16: 0 | H16: 0 | I16: 0 | J16: 0 | K16: 0 | L16: 0 | M16: 0 | N16: 0 | O16: 0 | P16: =SUM(D16:O16) -> 2380 | Q16: =IFERROR(AVERAGE(D16:O16), "¥0") -> 198.33333
B17: 口座振替 | C17: しがく会費 | D17: 330 | E17: 0 | F17: 0 | G17: 0 | H17: 0 | I17: 0 | J17: 0 | K17: 0 | L17: 0 | M17: 0 | N17: 0 | O17: 0 | P17: =SUM(D17:O17) -> 330 | Q17: =IFERROR(AVERAGE(D17:O17), "¥0") -> 27.5
B18: 口座振替 | C18: Abemaプレミアム | D18: 0 | E18: 0 | F18: 0 | G18: 0 | H18: 0 | I18: 0 | J18: 0 | K18: 0 | L18: 0 | M18: 0 | N18: 0 | O18: 0 | P18: =SUM(D18:O18) -> 0 | Q18: =IFERROR(AVERAGE(D18:O18), "¥0") -> 0
B19: 変動費：合計支出額 | C19: 【変動費】月次合計: | D19: =D20+D26+D30 -> 222170 | E19: =E20+E26+E30 -> 318143 | F19: =F20+F26+F30 -> 163533 | G19: =G20+G26+G30 -> 152679 | H19: =H20+H26+H30 -> 173782 | I19: =I20+I26+I30 -> 184013 | J19: =J20+J26+J30 -> 358457 | K19: =K20+K26+K30 -> 380279 | ... P19: =P20+P26+P30 -> 3576838 | Q19: =IFERROR(AVERAGE(D19:O19),"") -> 298069.83
B20: 食費（会食以外） | C20: 月次合計: | D20: =SUM(D22:D25) -> 85785 | E20: =SUM(E22:E25) -> 124669 | F20: =SUM(F22:F25) -> 56027 | G20: =SUM(G22:G25) -> 77019 | H20: =SUM(H22:H25) -> 120006 | I20: =SUM(I22:I25) -> 88754 | J20: =SUM(J22:J25) -> 112702 | K20: =SUM(K22:K25) -> 131664 | ... O20: =SUM(O22:O25) -> 241537 | P20: =SUM(D20:O20) -> 1521059 | Q20: =IFERROR(AVERAGE(D20:O20),"") -> 126754.92
C21: 収入(手取り)に対する比率 | D21: =(D20/'FY-2(月次)収入'!D4) -> 0.24667094 | E21: =(E20/'FY-2(月次)収入'!E4) -> 0.49522134 | F21: =(F20/'FY-2(月次)収入'!F3) -> 0.81321122 | G21: =(G20/'FY-2(月次)収入'!G4) -> 0.18011506 | H21: =(H20/'FY-2(月次)収入'!H4) -> 0.25847375 | I21: =(I20/'FY-2(月次)収入'!I4) -> 0.1626091 | J21: =(J20/'FY-2(月次)収入'!J4) -> 0.21909835 | K21: =(K20/'FY-2(月次)収入'!K4) -> 0.24814351 | L21: =(L20/'FY-2(月次)収入'!L4) -> 0.38236402 | M21: =(M20/'FY-2(月次)収入'!M4) -> 0.29251907 | N21: =(N20/'FY-2(月次)収入'!N4) -> 0.25184498 | ... Q21: =(Q20/'FY-2(月次)収入'!Q4) -> 0.29976191
C22: 食費（1人） | D22: 36623 | E22: 44495 | F22: 28774 | G22: 27303 | H22: 27961 | I22: 27170 | J22: 48661 | K22: 36375 | L22: ='FY-2(日次)出費'!G288 -> 34176 | M22: ='FY-2(日次)出費'!G320 -> 35662 | N22: ='FY-2(日次)出費'!G349 -> 37034 | O22: ='FY-2(日次)出費'!G381 -> 38188 | P22: =SUM(D22:O22) -> 422422 | Q22: =IFERROR(AVERAGE(D22:O22), "¥0") -> 35201.833
C23: 交際費（誰かと飲み・ごはん）※旅行中も | D23: 44765 | E23: 57343 | F23: 4150 | G23: ='FY-2(日次)出費'!H130 -> 37069 | H23: 64576 | I23: 40401 | J23: 40652 | K23: 62264 | L23: ='FY-2(日次)出費'!H288 -> 125214 | M23: ='FY-2(日次)出費'!H320 -> 89607 | N23: ='FY-2(日次)出費'!H349 -> 68187 | O23: ='FY-2(日次)出費'!H381 -> 165996 | P23: =SUM(D23:O23) -> 800224 | Q23: =IFERROR(AVERAGE(D23:O23), "¥0") -> 66685.333
C24: プレゼント・奢り等 | D24: 4397 | E24: 22831 | F24: 1704 | G24: ='FY-2(日次)出費'!I130 -> 1170 | H24: 10772 | I24: 12707 | J24: 15486 | K24: 18665 | L24: ='FY-2(日次)出費'!I288 -> 25489 | M24: ='FY-2(日次)出費'!I320 -> 22293 | N24: ='FY-2(日次)出費'!I349 -> 9703 | O24: ='FY-2(日次)出費'!I381 -> 19864 | P24: =SUM(D24:O24) -> 165081 | Q24: =IFERROR(AVERAGE(D24:O24), "¥0") -> 13756.75
C25: スーパー(まとめ買い)費用※Amazonも含む | D25: 0 | E25: 0 | F25: 21399 | G25: 11477 | H25: 16697 | I25: 8476 | J25: 7903 | K25: 14360 | L25: ='FY-2(日次)出費'!J288 -> 12838 | M25: ='FY-2(日次)出費'!J320 -> 9309 | N25: ='FY-2(日次)出費'!J349 -> 13384 | O25: ='FY-2(日次)出費'!J381 -> 17489 | P25: =SUM(D25:O25) -> 133332 | Q25: =IFERROR(AVERAGE(D25:O25), "¥0") -> 11111
B26: 自己投資・1人体験 | C26: 月次合計: | D26: =SUM(D28:D29) -> 47960 | E26: =SUM(E28:E29) -> 7370 | F26: =SUM(F28:F29) -> 4111 | G26: =SUM(G28:G29) -> 9650 | H26: =SUM(H28:H29) -> 4128 | I26: =SUM(I28:I29) -> 53955 | J26: =SUM(J28:J29) -> 17020 | K26: =SUM(K28:K29) -> 8300 | ... O26: =SUM(O28:O29) -> 22540 | P26: =SUM(D26:O26) -> 313897 | Q26: =IFERROR(AVERAGE(D26:O26),"") -> 26158.083
C27: 収入(手取り)に対する比率 | D27: =(D26/'FY-2(月次)収入'!D4) -> 0.13790684 | E27: =(E26/'FY-2(月次)収入'!E4) -> 0.029275772 | F27: =(F26/'FY-2(月次)収入'!F3) -> 0.059669647 | G27: =(G26/'FY-2(月次)収入'!G4) -> 0.022567293 | H27: =(H26/'FY-2(月次)収入'!H4) -> 0.0088910523 | I27: =(I26/'FY-2(月次)収入'!I4) -> 0.098852719 | J27: =(J26/'FY-2(月次)収入'!J4) -> 0.033087735 | K27: =(K26/'FY-2(月次)収入'!K4) -> 0.015642781 | L27: =(L26/'FY-2(月次)収入'!L4) -> 0.13326474 | M27: =(M26/'FY-2(月次)収入'!M4) -> 0.083837403 | N27: =(N26/'FY-2(月次)収入'!N4) -> 0.049056658 | ... Q27: =(Q26/'FY-2(月次)収入'!Q4) -> 0.061861088
C28: 1人体験(運動,散髪,グリーン車,1人映画鑑賞) | D28: 4400 | E28: 7370 | F28: 4111 | G28: ='FY-2(日次)出費'!K130 -> 9650 | H28: 4128 | I28: 1950 | J28: 9020 | K28: 8300 | L28: 38910 | M28: ='FY-2(日次)出費'!K320 -> 44960 | N28: ='FY-2(日次)出費'!K349 -> 24993 | O28: ='FY-2(日次)出費'!K381 -> 22540 | P28: =SUM(D28:O28) -> 180332 | Q28: =IFERROR(AVERAGE(D28:O28), "¥0") -> 15027.667
C29: 結婚式 | D29: 43560 | E29: 0 | F29: 0 | G29: 0 | H29: 0 | I29: 52005 | J29: 8000 | K29: 0 | L29: 30000 | M29: ='FY-2(日次)出費'!L320 -> 0 | N29: ='FY-2(日次)出費'!L349 -> 0 | O29: ='FY-2(日次)出費'!L381 -> 0 | P29: =SUM(D29:O29) -> 133565 | Q29: =IFERROR(AVERAGE(D29:O29), "¥0") -> 11130.417
B30: 諸経費・備品購入費 | C30: 月次合計: | D30: =SUM(D32:D35) -> 88425 | E30: =SUM(E32:E35) -> 186104 | F30: =SUM(F32:F35) -> 103395 | G30: =SUM(G32:G35) -> 66010 | H30: =SUM(H32:H35) -> 49648 | I30: =SUM(I32:I35) -> 41304 | J30: =SUM(J32:J35) -> 228735 | K30: =SUM(K32:K35) -> 240315 | ... O30: =SUM(O32:O35) -> 133672 | P30: =SUM(D30:O30) -> 1741882 | Q30: =IFERROR(AVERAGE(D30:O30),"") -> 145156.83
C31: 収入(手取り)に対する比率 | D31: =(D30/'FY-2(月次)収入'!D4) -> 0.25426214 | E31: =(E30/'FY-2(月次)収入'!E4) -> 0.73925893 | F31: =(F30/'FY-2(月次)収入'!F3) -> 1.5007402 | G31: =(G30/'FY-2(月次)収入'!G4) -> 0.15436964 | H31: =(H30/'FY-2(月次)収入'!H4) -> 0.10693386 | I31: =(I30/'FY-2(月次)収入'!I4) -> 0.075674408 | J31: =(J30/'FY-2(月次)収入'!J4) -> 0.44467233 | K31: =(K30/'FY-2(月次)収入'!K4) -> 0.45291506 | L31: =(L30/'FY-2(月次)収入'!L4) -> 0.22016434 | M31: =(M30/'FY-2(月次)収入'!M4) -> 0.80922114 | N31: =(N30/'FY-2(月次)収入'!N4) -> 0.11082647 | ... Q31: =(Q30/'FY-2(月次)収入'!Q4) -> 0.34328049
C32: 旅費・交通費(交通系ICと新幹線代) | D32: 29173 | E32: 28969 | F32: 3296 | G32: ='FY-2(日次)出費'!M130 -> 13594 | H32: 20598 | I32: 18940 | J32: 47043 | K32: 11966 | L32: ='FY-2(日次)出費'!M288 -> 69829 | M32: ='FY-2(日次)出費'!M320 -> 65493 | N32: ='FY-2(日次)出費'!M349 -> 18170 | O32: ='FY-2(日次)出費'!M381 -> 74334 | P32: =SUM(D32:O32) -> 401405 | Q32: =IFERROR(AVERAGE(D32:O32), "¥0") -> 33450.417
C33: 物品購入費(生活用品・贅沢品など物品全般) | D33: 49492 | E33: 4418 | F33: 76924 | G33: ='FY-2(日次)出費'!N130 -> 43022 | H33: 21970 | I33: 15079 | J33: 41297 | K33: 47119 | L33: ='FY-2(日次)出費'!N288 -> 37826 | M33: ='FY-2(日次)出費'!N320 -> 360173 | N33: ='FY-2(日次)出費'!N349 -> 588 | O33: ='FY-2(日次)出費'!N381 -> 39229 | P33: =SUM(D33:O33) -> 737137 | Q33: =IFERROR(AVERAGE(D33:O33), "¥0") -> 61428.083
C34: その他諸経費(引越し費・処分費・手数料等) | D34: 0 | E34: 147777 | F34: 22175 | G34: ='FY-2(日次)出費'!O130 -> 3894 | H34: 430 | I34: 775 | J34: 132955 | K34: 169190 | L34: ='FY-2(日次)出費'!O288 -> 110 | M34: ='FY-2(日次)出費'!O320 -> 220 | N34: ='FY-2(日次)出費'!O349 -> 29355 | O34: ='FY-2(日次)出費'!O381 -> 11709 | P34: =SUM(D34:O34) -> 518590 | Q34: =IFERROR(AVERAGE(D34:O34), "¥0") -> 43215.833
C35: 嗜好品(TBC) | D35: 9760 | E35: 4940 | F35: 1000 | G35: ='FY-2(日次)出費'!P130 -> 5500 | H35: 6650 | I35: 6510 | J35: 7440 | K35: 12040 | L35: ='FY-2(日次)出費'!P288 -> 6080 | M35: ='FY-2(日次)出費'!P320 -> 8080 | N35: ='FY-2(日次)出費'!P349 -> 8350 | O35: ='FY-2(日次)出費'!P381 -> 8400 | P35: =SUM(D35:O35) -> 84750 | Q35: =IFERROR(AVERAGE(D35:O35), "¥0") -> 7062.5
B36: 支払い利息 | C36: 月次合計: | D36: =SUM(D37:D38) -> 7219 | E36: =SUM(E37:E38) -> 5148 | F36: =SUM(F37:F38) -> 25437 | G36: =SUM(G37:G38) -> 195613 | H36: =SUM(H37:H38) -> 174487 | I36: =SUM(I37:I38) -> 188705 | J36: =SUM(J37:J38) -> 14433 | K36: =SUM(K37:K38) -> 4142 | ... O36: =SUM(O37:O38) -> 0 | P36: =SUM(D36:O36) -> 899819 | Q36: =IFERROR(AVERAGE(D36:O36),"") -> 74984.917
C37: ①元金返済金額 | D37: 0 | E37: 0 | F37: 10762 | G37: 179852 | H37: 167170 | I37: 182978 | J37: 10000 | K37: 0 | L37: 280000 | M37: 0 | N37: 0 | O37: 0 | P37: =SUM(D37:O37) -> 830762 | Q37: =IFERROR(AVERAGE(D37:O37), "¥0") -> 69230.167
C38: ②返済利子 | D38: 7219 | E38: 5148 | F38: 14675 | G38: 15761 | H38: 7317 | I38: 5727 | J38: 4433 | K38: 4142 | L38: 4635 | M38: 0 | N38: 0 | O38: 0 | P38: =SUM(D38:O38) -> 69057 | Q38: =IFERROR(AVERAGE(D38:O38), "¥0") -> 5754.75
B39: 税金 ※収入タブ参照 | C39: 月次合計: | D39: =SUM(D40:D41) -> 0 | E39: =SUM(E40:E41) -> 0 | F39: =SUM(F40:F41) -> 0 | G39: =SUM(G40:G41) -> 0 | H39: =SUM(H40:H41) -> 0 | I39: =SUM(I40:I41) -> 0 | J39: =SUM(J40:J41) -> 0 | K39: =SUM(K40:K41) -> 0 | ... O39: =SUM(O40:O41) -> 0 | P39: =SUM(D39:O39) -> 0 | Q39: =IFERROR(AVERAGE(D39:O39),"") -> 0
C40: 住民税(給与天引き：収入予実に記載) | D40: 0 | E40: 0 | F40: 0 | G40: 0 | H40: 0 | I40: 0 | J40: 0 | K40: 0 | L40: 0 | M40: 0 | N40: 0 | O40: 0 | P40: =SUM(D40:O40) -> 0 | Q40: =IFERROR(AVERAGE(D40:O40), "¥0") -> 0
C41: 社会保険料(給与天引き：収入予実に記載) | D41: 0 | E41: 0 | F41: 0 | G41: 0 | H41: 0 | I41: 0 | J41: 0 | K41: 0 | L41: 0 | M41: 0 | N41: 0 | O41: 0 | P41: =SUM(D41:O41) -> 0 | Q41: =IFERROR(AVERAGE(D41:O41), "¥0") -> 0

Sheet FY-3(月次)支出 
D1: ※確定 | E1: ※確定 | F1: ※確定 | G1: 未確定 | H1: 未確定 | I1: 未確定 | J1: 未確定 | K1: 未確定 | L1: 未確定 | M1: 未確定 | N1: 未確定 | O1: 未確定 | P1: 未確定
C2: (FY-3)支出 | D2: 2026年4月 | E2: 2026年5月 | F2: 2026年6月 | G2: 2026年7月 | H2: 2026年8月 | I2: 2026年9月 | J2: 2026年10月 | K2: 2026年11月 | L2: 2026年12月 | M2: 2027年1月 | N2: 2027年2月 | O2: 2027年3月 | P2: 合計 | Q2: 平均
B3: ALL | C3: 〔 固定費及び変動費 〕合計支出額 | D3: =D5+D17 -> 440344 | E3: =E5+E17 -> 447333 | F3: =F5+F17 -> 392616 | G3: =G5+G17 -> 494717 | H3: =H5+H17 -> 588753 | I3: =I5+I17 -> 849403 | J3: =J5+J17 -> 529403 | K3: =K5+K17 -> 529403 | ... P3: =P5+P17 -> 6089552 | Q3: =IFERROR(AVERAGE(D3:O3),"") -> 507462.67
C4: 収入(手取り)に対する比率 | D4: =(D3/'FY-2(月次)収入'!D4) -> 1.2661895 | E4: =(E3/'FY-2(月次)収入'!E4) -> 1.7769361 | F4: =(F3/'FY-2(月次)収入'!F3) -> 5.6986763 | G4: =(G3/'FY-2(月次)収入'!G4) -> 1.1569351 | H4: =(H3/'FY-2(月次)収入'!H4) -> 1.2680799 | I4: =(I3/'FY-2(月次)収入'!I4) -> 1.556219 | J4: =(J3/'FY-2(月次)収入'!J4) -> 1.029186 | K4: =(K3/'FY-2(月次)収入'!K4) -> 0.99775124 | L4: =(L3/'FY-2(月次)収入'!L4) -> 0.79174264 | M4: =(M3/'FY-2(月次)収入'!M4) -> 0.93124223 | N4: =(N3/'FY-2(月次)収入'!N4) -> 0.80351991 | ... Q4: =(Q3/'FY-2(月次)収入'!Q4) -> 1.2000953
B5: 固定費：合計支出額 | C5: 【固定費】月次合計: | D5: =SUM(D7:D16) -> 177708 | E5: =SUM(E7:E16) -> 165276 | F5: =SUM(F7:F16) -> 154712 | G5: =SUM(G7:G16) -> 151717 | H5: =SUM(H7:H16) -> 155753 | I5: =SUM(I7:I16) -> 156403 | J5: =SUM(J7:J16) -> 156403 | K5: =SUM(K7:K16) -> 156403 | ... O5: =SUM(O7:O16) -> 156403 | P5: =SUM(D5:O5) -> 1899955 | Q5: =IFERROR(AVERAGE(D5:O5),"") -> 158329.58
B6: 備考 | C6: 収入(手取り)に対する比率 | D6: =(D5/'FY-2(月次)収入'!D4) -> 0.51099143 | E6: =(E5/'FY-2(月次)収入'!E4) -> 0.65652409 | F6: =(F5/'FY-2(月次)収入'!F3) -> 2.2455876 | G6: =(G5/'FY-2(月次)収入'!G4) -> 0.35480227 | H6: =(H5/'FY-2(月次)収入'!H4) -> 0.33546707 | I6: =(I5/'FY-2(月次)収入'!I4) -> 0.28655105 | J6: =(J5/'FY-2(月次)収入'!J4) -> 0.30405529 | K6: =(K5/'FY-2(月次)収入'!K4) -> 0.29476842 | L6: =(L5/'FY-2(月次)収入'!L4) -> 0.30246706 | M6: =(M5/'FY-2(月次)収入'!M4) -> 0.29164638 | N6: =(N5/'FY-2(月次)収入'!N4) -> 0.30692749 | ... Q6: =(Q5/'FY-2(月次)収入'!Q4) -> 0.37443264
B7: 口座振替（みずほ） | C7: 家賃(SA麻布十番)※水道光熱費込み | D7: 129987 | E7: 129987 | F7: 129987 | G7: 129987 | H7: 129987 | I7: 129987 | J7: 129987 | K7: 129987 | L7: 129987 | M7: 129987 | N7: 129955 | O7: 129987 | P7: =SUM(D7:O7) -> 1559812 | Q7: =IFERROR(AVERAGE(D7:O7), "¥0") -> 129984.33
B8: クレカ引落し | C8: ジム(JOYFIT麻布十番) | D8: 8000 | E8: 8000 | F8: 0 | G8: 0 | H8: 0 | I8: 0 | J8: 0 | K8: 0 | L8: 0 | M8: 0 | N8: 0 | O8: 0 | P8: =SUM(D8:O8) -> 16000 | Q8: =IFERROR(AVERAGE(D8:O8), "¥0") -> 1333.3333
B9: クレカ引落し | C9: 生命保険(プルデンシャル) | D9: 9307 | E9: 0 | F9: 0 | G9: 0 | H9: 0 | I9: 0 | J9: 0 | K9: 0 | L9: 0 | M9: 0 | N9: 0 | O9: 0 | P9: =SUM(D9:O9) -> 9307 | Q9: =IFERROR(AVERAGE(D9:O9), "¥0") -> 775.58333
B10: ★クレカ引落し(2025年7月5日に機種編) ※2027年7月頃に要確認 ※apple wotchの機種代2027円3月で終わり | C10: 携帯料金(SB)＋YouTubeプレミアム(￥870) | D10: 12218 | E10: 9093 | F10: 9137 | G10: 9200 | H10: 9200 | I10: 9200 | J10: 9200 | K10: 9200 | L10: 9200 | M10: 9200 | N10: 9200 | O10: 9200 | P10: =SUM(D10:O10) -> 113248 | Q10: =IFERROR(AVERAGE(D10:O10), "¥0") -> 9437.3333
B11: クレカ→anapay→pasmo→給料日に精算 | C11: 定期券代 | D11: 13030 | E11: 13030 | F11: 12380 | G11: 12380 | H11: 12380 | I11: 13030 | J11: 13030 | K11: 13030 | L11: 13030 | M11: 13030 | N11: 13030 | O11: 13030 | P11: =SUM(D11:O11) -> 154410 | Q11: =IFERROR(AVERAGE(D11:O11), "¥0") -> 12867.5
B12: クレカ（EPOS）引落し | C12: iCloud拡張会費 | D12: 150 | E12: 150 | F12: 150 | G12: 150 | H12: 150 | I12: 150 | J12: 150 | K12: 150 | L12: 150 | M12: 150 | N12: 150 | O12: 150 | P12: =SUM(D12:O12) -> 1800 | Q12: =IFERROR(AVERAGE(D12:O12), "¥0") -> 150
B13: クレカ（PayPayカード）払い | C13: BASE FOOD/ナッシュのサブスク | D13: 4036 | E13: 4036 | F13: 3058 | G13: 0 | H13: 4036 | I13: 4036 | J13: 4036 | K13: 4036 | L13: 4036 | M13: 4036 | N13: 4036 | O13: 4036 | P13: =SUM(D13:O13) -> 43418 | Q13: =IFERROR(AVERAGE(D13:O13), "¥0") -> 3618.1667
B14: クレカ引落し | C14: Kindleサブスク | D14: 980 | E14: 980 | F14: 0 | G14: 0 | H14: 0 | I14: 0 | J14: 0 | K14: 0 | L14: 0 | M14: 0 | N14: 0 | O14: 0 | P14: =SUM(D14:O14) -> 1960 | Q14: =IFERROR(AVERAGE(D14:O14), "¥0") -> 163.33333
B15: クレカ引落し | C15: Netflix | D15: 0 | E15: 0 | F15: 0 | G15: 0 | H15: 0 | I15: 0 | J15: 0 | K15: 0 | L15: 0 | M15: 0 | N15: 0 | O15: 0 | P15: =SUM(D15:O15) -> 0 | Q15: =IFERROR(AVERAGE(D15:O15), "¥0") -> 0
B16: 口座振替 | C16: Abemaプレミアム | D16: 0 | E16: 0 | F16: 0 | G16: 0 | H16: 0 | I16: 0 | J16: 0 | K16: 0 | L16: 0 | M16: 0 | N16: 0 | O16: 0 | P16: =SUM(D16:O16) -> 0 | Q16: =IFERROR(AVERAGE(D16:O16), "¥0") -> 0
B17: 変動費：合計支出額 | C17: 【変動費】月次合計: | D17: =D18+D24+D28 -> 262636 | E17: =E18+E24+E28 -> 282057 | F17: =F18+F24+F28 -> 237904 | G17: =G18+G24+G28 -> 343000 | H17: =H18+H24+H28 -> 433000 | I17: =I18+I24+I28 -> 693000 | J17: =J18+J24+J28 -> 373000 | K17: =K18+K24+K28 -> 373000 | ... P17: =P18+P24+P28 -> 4189597 | Q17: =IFERROR(AVERAGE(D17:O17),"") -> 349133.08
B18: 食費（会食以外） | C18: 月次合計: | D18: =SUM(D20:D23) -> 157856 | E18: =SUM(E20:E23) -> 145000 | F18: =SUM(F20:F23) -> 119498 | G18: =SUM(G20:G23) -> 205000 | H18: =SUM(H20:H23) -> 305000 | I18: =SUM(I20:I23) -> 305000 | J18: =SUM(J20:J23) -> 155000 | K18: =SUM(K20:K23) -> 155000 | ... O18: =SUM(O20:O23) -> 155000 | P18: =SUM(D18:O18) -> 2167354 | Q18: =IFERROR(AVERAGE(D18:O18),"") -> 180612.83
C19: 収入(手取り)に対する比率 | D19: =(D18/'FY-2(月次)収入'!D4) -> 0.45390789 | E19: =(E18/'FY-2(月次)収入'!E4) -> 0.57598195 | F19: =(F18/'FY-2(月次)収入'!F3) -> 1.7344693 | G19: =(G18/'FY-2(月次)収入'!G4) -> 0.47940881 | H19: =(H18/'FY-2(月次)収入'!H4) -> 0.65692126 | I19: =(I18/'FY-2(月次)収入'!I4) -> 0.55880047 | J19: =(J18/'FY-2(月次)収入'!J4) -> 0.30132779 | K19: =(K18/'FY-2(月次)収入'!K4) -> 0.29212423 | L19: =(L18/'FY-2(月次)収入'!L4) -> 0.29975381 | M19: =(M18/'FY-2(月次)収入'!M4) -> 0.28903019 | N19: =(N18/'FY-2(月次)収入'!N4) -> 0.30423646 | ... Q19: =(Q18/'FY-2(月次)収入'!Q4) -> 0.42713016
C20: 食費（1人） | D20: ='FY-3(日次)出費'!G35 -> 39230 | E20: ='FY-3(日次)出費'!G67 -> 13368 | F20: ='FY-3(日次)出費'!G98 -> 12414 | G20: 30000 | H20: 30000 | I20: 30000 | J20: 30000 | K20: 30000 | L20: 30000 | M20: 30000 | N20: 30000 | O20: 30000 | P20: =SUM(D20:O20) -> 335012 | Q20: =IFERROR(AVERAGE(D20:O20), "¥0") -> 27917.667
C21: 交際費（誰かと飲み・ごはん）※旅行中も | D21: ='FY-3(日次)出費'!H35 -> 83941 | E21: ='FY-3(日次)出費'!H67 -> 86657 | F21: ='FY-3(日次)出費'!H98 -> 86516 | G21: 150000 | H21: 250000 | I21: 250000 | J21: 100000 | K21: 100000 | L21: 100000 | M21: 100000 | N21: 100000 | O21: 100000 | P21: =SUM(D21:O21) -> 1507114 | Q21: =IFERROR(AVERAGE(D21:O21), "¥0") -> 125592.83
C22: プレゼント・奢り等 | D22: ='FY-3(日次)出費'!I35 -> 19397 | E22: ='FY-3(日次)出費'!I67 -> 21331 | F22: ='FY-3(日次)出費'!I98 -> 2570 | G22: 10000 | H22: 10000 | I22: 10000 | J22: 10000 | K22: 10000 | L22: 10000 | M22: 10000 | N22: 10000 | O22: 10000 | P22: =SUM(D22:O22) -> 133298 | Q22: =IFERROR(AVERAGE(D22:O22), "¥0") -> 11108.167
C23: スーパー(まとめ買い)費用※Amazonも含む | D23: ='FY-3(日次)出費'!J35 -> 15288 | E23: ='FY-3(日次)出費'!J67 -> 23644 | F23: ='FY-3(日次)出費'!J98 -> 17998 | G23: 15000 | H23: 15000 | I23: 15000 | J23: 15000 | K23: 15000 | L23: 15000 | M23: 15000 | N23: 15000 | O23: 15000 | P23: =SUM(D23:O23) -> 191930 | Q23: =IFERROR(AVERAGE(D23:O23), "¥0") -> 15994.167
B24: 自己投資・1人体験 | C24: 月次合計: | D24: =SUM(D26:D27) -> 36690 | E24: =SUM(E26:E27) -> 89500 | F24: =SUM(F26:F27) -> 82780 | G24: =SUM(G26:G27) -> 90000 | H24: =SUM(H26:H27) -> 90000 | I24: =SUM(I26:I27) -> 60000 | J24: =SUM(J26:J27) -> 90000 | K24: =SUM(K26:K27) -> 90000 | ... O24: =SUM(O26:O27) -> 60000 | P24: =SUM(D24:O24) -> 868970 | Q24: =IFERROR(AVERAGE(D24:O24),"") -> 72414.167
C25: 収入(手取り)に対する比率 | D25: =(D24/'FY-2(月次)収入'!D4) -> 0.10550046 | E25: =(E24/'FY-2(月次)収入'!E4) -> 0.35551989 | F25: =(F24/'FY-2(月次)収入'!F3) -> 1.2015211 | G25: =(G24/'FY-2(月次)収入'!G4) -> 0.21047216 | H25: =(H24/'FY-2(月次)収入'!H4) -> 0.19384562 | I25: =(I24/'FY-2(月次)収入'!I4) -> 0.10992796 | J25: =(J24/'FY-2(月次)収入'!J4) -> 0.17496452 | K25: =(K24/'FY-2(月次)収入'!K4) -> 0.16962052 | L25: =(L24/'FY-2(月次)収入'!L4) -> 0.11603373 | M25: =(M24/'FY-2(月次)収入'!M4) -> 0.11188266 | N25: =(N24/'FY-2(月次)収入'!N4) -> 0.11776895 | ... Q25: =(Q24/'FY-2(月次)収入'!Q4) -> 0.17125181
C26: 1人体験(運動,散髪,グリーン車,1人映画鑑賞) | D26: ='FY-3(日次)出費'!K35 -> 36690 | E26: ='FY-3(日次)出費'!K67 -> 89500 | F26: ='FY-3(日次)出費'!K98 -> 82780 | G26: 60000 | H26: 60000 | I26: 60000 | J26: 60000 | K26: 60000 | L26: 60000 | M26: 60000 | N26: 60000 | O26: 60000 | P26: =SUM(D26:O26) -> 748970 | Q26: =IFERROR(AVERAGE(D26:O26), "¥0") -> 62414.167
C27: 結婚式 | D27: ='FY-3(日次)出費'!L35 -> 0 | E27: ='FY-3(日次)出費'!L67 -> 0 | F27: ='FY-3(日次)出費'!L98 -> 0 | G27: 30000 | H27: 30000 | I27: 0 | J27: 30000 | K27: 30000 | L27: 0 | M27: 0 | N27: 0 | O27: 0 | P27: =SUM(D27:O27) -> 120000 | Q27: =IFERROR(AVERAGE(D27:O27), "¥0") -> 10000
B28: 諸経費・備品購入費 | C28: 月次合計: | D28: =SUM(D30:D33) -> 68090 | E28: =SUM(E30:E33) -> 47557 | F28: =SUM(F30:F33) -> 35626 | G28: =SUM(G30:G33) -> 48000 | H28: =SUM(H30:H33) -> 38000 | I28: =SUM(I30:I33) -> 328000 | J28: =SUM(J30:J33) -> 128000 | K28: =SUM(K30:K33) -> 128000 | ... O28: =SUM(O30:O33) -> 128000 | P28: =SUM(D28:O28) -> 1153273 | Q28: =IFERROR(AVERAGE(D28:O28),"") -> 96106.083
C29: 収入(手取り)に対する比率 | D29: =(D28/'FY-2(月次)収入'!D4) -> 0.19578976 | E29: =(E28/'FY-2(月次)収入'!E4) -> 0.18891016 | F29: =(F28/'FY-2(月次)収入'!F3) -> 0.51709824 | G29: =(G28/'FY-2(月次)収入'!G4) -> 0.11225182 | H29: =(H28/'FY-2(月次)収入'!H4) -> 0.081845927 | I29: =(I28/'FY-2(月次)収入'!I4) -> 0.60093952 | J29: =(J28/'FY-2(月次)収入'!J4) -> 0.24883843 | K29: =(K28/'FY-2(月次)収入'!K4) -> 0.24123807 | L29: =(L28/'FY-2(月次)収入'!L4) -> 0.073488031 | M29: =(M28/'FY-2(月次)収入'!M4) -> 0.238683 | N29: =(N28/'FY-2(月次)収入'!N4) -> 0.074587004 | ... Q29: =(Q28/'FY-2(月次)収入'!Q4) -> 0.22728068
C30: 旅費・交通費(交通系ICと新幹線代) | D30: ='FY-3(日次)出費'!M35 -> 49681 | E30: ='FY-3(日次)出費'!M67 -> 33168 | F30: ='FY-3(日次)出費'!M98 -> 12548 | G30: 15000 | H30: 15000 | I30: 15000 | J30: 15000 | K30: 15000 | L30: 15000 | M30: 15000 | N30: 15000 | O30: 15000 | P30: =SUM(D30:O30) -> 230397 | Q30: =IFERROR(AVERAGE(D30:O30), "¥0") -> 19199.75
C31: 物品購入費(生活用品・贅沢品など物品全般) | D31: ='FY-3(日次)出費'!N35 -> 7451 | E31: ='FY-3(日次)出費'!N67 -> 5834 | F31: ='FY-3(日次)出費'!N98 -> 8428 | G31: 20000 | H31: 10000 | I31: 300000 | J31: 100000 | K31: 100000 | L31: 10000 | M31: 100000 | N31: 10000 | O31: 100000 | P31: =SUM(D31:O31) -> 771713 | Q31: =IFERROR(AVERAGE(D31:O31), "¥0") -> 64309.417
C32: その他諸経費(引越し費・処分費・手数料等) | D32: ='FY-3(日次)出費'!O35 -> 1308 | E32: ='FY-3(日次)出費'!O67 -> 475 | F32: ='FY-3(日次)出費'!O98 -> 6010 | G32: 5000 | H32: 5000 | I32: 5000 | J32: 5000 | K32: 5000 | L32: 5000 | M32: 5000 | N32: 5000 | O32: 5000 | P32: =SUM(D32:O32) -> 52793 | Q32: =IFERROR(AVERAGE(D32:O32), "¥0") -> 4399.4167
C33: 嗜好品(TBC) | D33: ='FY-3(日次)出費'!P35 -> 9650 | E33: ='FY-3(日次)出費'!P67 -> 8080 | F33: ='FY-3(日次)出費'!P98 -> 8640 | G33: 8000 | H33: 8000 | I33: 8000 | J33: 8000 | K33: 8000 | L33: 8000 | M33: 8000 | N33: 8000 | O33: 8000 | P33: =SUM(D33:O33) -> 98370 | Q33: =IFERROR(AVERAGE(D33:O33), "¥0") -> 8197.5
B34: 支払い利息 | C34: 月次合計: | D34: =SUM(D35:D36) -> 0 | E34: =SUM(E35:E36) -> 0 | F34: =SUM(F35:F36) -> 0 | G34: =SUM(G35:G36) -> 0 | H34: =SUM(H35:H36) -> 0 | I34: =SUM(I35:I36) -> 0 | J34: =SUM(J35:J36) -> 0 | K34: =SUM(K35:K36) -> 0 | ... O34: =SUM(O35:O36) -> 0 | P34: =SUM(D34:O34) -> 0 | Q34: =IFERROR(AVERAGE(D34:O34),"") -> 0
C35: ①元金返済金額 | D35: 0 | E35: 0 | F35: 0 | G35: 0 | H35: 0 | I35: 0 | J35: 0 | K35: 0 | L35: 0 | M35: 0 | N35: 0 | O35: 0 | P35: =SUM(D35:O35) -> 0 | Q35: =IFERROR(AVERAGE(D35:O35), "¥0") -> 0
C36: ②返済利子 | D36: 0 | E36: 0 | F36: 0 | G36: 0 | H36: 0 | I36: 0 | J36: 0 | K36: 0 | L36: 0 | M36: 0 | N36: 0 | O36: 0 | P36: =SUM(D36:O36) -> 0 | Q36: =IFERROR(AVERAGE(D36:O36), "¥0") -> 0
B37: 税金 ※収入タブ参照 | C37: 月次合計: | D37: =SUM(D38:D39) -> 0 | E37: =SUM(E38:E39) -> 0 | F37: =SUM(F38:F39) -> 0 | G37: =SUM(G38:G39) -> 0 | H37: =SUM(H38:H39) -> 0 | I37: =SUM(I38:I39) -> 0 | J37: =SUM(J38:J39) -> 0 | K37: =SUM(K38:K39) -> 0 | ... O37: =SUM(O38:O39) -> 0 | P37: =SUM(D37:O37) -> 0 | Q37: =IFERROR(AVERAGE(D37:O37),"") -> 0
C38: 住民税(給与天引き：収入予実に記載) | D38: 0 | E38: 0 | F38: 0 | G38: 0 | H38: 0 | I38: 0 | J38: 0 | K38: 0 | L38: 0 | M38: 0 | N38: 0 | O38: 0 | P38: =SUM(D38:O38) -> 0 | Q38: =IFERROR(AVERAGE(D38:O38), "¥0") -> 0
C39: 社会保険料(給与天引き：収入予実に記載) | D39: 0 | E39: 0 | F39: 0 | G39: 0 | H39: 0 | I39: 0 | J39: 0 | K39: 0 | L39: 0 | M39: 0 | N39: 0 | O39: 0 | P39: =SUM(D39:O39) -> 0 | Q39: =IFERROR(AVERAGE(D39:O39), "¥0") -> 0

Sheet FY-2(月次)収入
D1: ※確定 | E1: ※確定 | F1: ※確定 | G1: ※確定 | H1: ※確定 | I1: ※確定 | J1: ※確定 | K1: ※確定 | L1: ※確定 | M1: ※確定 | N1: ※確定 | O1: ※確定 | P1: ※確定
C2: (FY-2)収入 | D2: 2025年4月 | E2: 2025年5月 | F2: 2025年6月 | G2: 2025年7月 | H2: 2025年8月 | I2: 2025年9月 | J2: 2025年10月 | K2: 2025年11月 | L2: 2025年12月 | M2: 2026年1月 | N2: 2026年2月 | O2: 2026年3月 | P2: 合計 | Q2: 平均
B3: 収入 | C3: 月次合計(可処分所得) | D3: =SUM(D4:D8) -> 362756 | E3: =SUM(E4:E8) -> 280024 | F3: =SUM(F4:F8) -> 68896 | G3: =SUM(G4:G8) -> 473086 | H3: =SUM(H4:H8) -> 502474 | I3: =SUM(I4:I8) -> 584444 | J3: =SUM(J4:J8) -> 524857 | K3: =SUM(K4:K8) -> 584601.18 | ... O3: =SUM(O4:O8) -> 773052.25 | P3: =SUM(D3:O3) -> 6192587.7 | Q3: =IFERROR(AVERAGE(D3:O3),"") -> 516048.98
